Workbook

Sheet Hoja1
D2: PANDERETA | G2: 18 HUECOS | N2: TECHO 12 | Q2: TECHO 15 | S2: ARTESANAL | U2: TECHO 08
B3: FECHA | C3: CLIENTE | D3: SIPAN | E3: CERAMICOS | F3: CALCA | G3: CERAMICOS | H3: TORRE FUERTE | I3: LARK | J3: FORTALEZA | K3: CRUZ CHALPON | L3: TAISON | M3: SIPAN | N3: LARK | O3: ITAL | P3: FORTALEZA | Q3: ITAL | R3: FORTALEZA | S3: BODOQUE | T3: PEQUEÑO | U3: CERAMICOS
A4: INGRESO | C4: INICIAL | D4: 5232 | E4: 904 | F4: 304 | G4: 1136 | H4: 1470 | I4: 885 | J4: 4499 | K4: 1652 | L4: 402 | M4: 103 | N4: 11 | O4: 1022 | P4: 416 | Q4: 1721 | R4: 517 | S4: 1125 | T4: 2358 | U4: 52
B5: 45203 | C5: M5P-711 | O5: 1200
B6: 45203 | C6: AZABACHE | D6: 4312
B7: 45204 | C7: M6I-897 | T7: 3000
B8: 45205 | C8: DEVOLUCION | T8: 500
B9: 45208 | C9: M5P-711 | T9: 300
B10: 45208 | C10: AZABACHE | D10: 2600
B11: 45210 | C11: AZABACHE | D11: 4110
B12: 45211 | C12: AZABACHE | D12: 816
B13: 45211 | C13: AZABACHE | D13: 4140
B14: 45213 | C14: M5P-711 | S14: 3000
B15: 45213 | C15: M6I-897 | O15: 1200
A17: SALIDADA | B17: 45202 | C17: VENTAS H&C | T17: 20
B18: 45202 | C18: VENTAS H&C | T18: 20
B19: 45202 | C19: VENTAS H&C | H19: 150
B20: 45202 | C20: VENTAS H&C | D20: 1000
B21: 45202 | C21: VENTAS H&C | O21: 530
B22: 45203 | C22: VENTAS H&C | S22: 500
B23: 45203 | C23: VENTAS H&C | T23: 1000
B24: 45203 | C24: VENTAS H&C | T24: =20+20 -> 40
B25: 45203 | C25: VENTAS H&C | D25: 500
B26: 45203 | C26: VENTAS H&C | D26: 1000
B27: 45203 | C27: VENTAS H&C | D27: 2500
B28: 45203 | C28: VENTAS H&C | O28: 1000 | P28: 150
B29: 45203 | C29: VENTAS H&C | R29: 140
B30: 45203 | C30: ARCENIO MEJIA | J30: 1000
B31: 45204 | C31: VENTAS H&C | T31: 20
B32: 45204 | C32: VENTAS H&C | T32: 500
B33: 45204 | C33: VENTAS H&C | S33: 250
B34: 45204 | C34: VENTAS H&C | D34: 500
B35: 45204 | C35: VENTAS H&C | D35: 680
B36: 45204 | C36: VENTAS H&C | O36: 180
B37: 45205 | C37: VENTAS H&C | S37: 350
B38: 45205 | C38: VENTAS H&C | J38: 1000
B39: 45205 | C39: VENTAS H&C | J39: 250
B40: 45206 | C40: VENTAS H&C | D40: 1000
B41: 45207 | C41: VENTAS H&C | F41: 20
B42: 45208 | C42: VENTAS H&C | T42: 100
B43: 45208 | C43: VENTAS H&C | D43: 1000
B44: 45208 | C44: VENTAS H&C | O44: 60
B45: 45209 | C45: VENTAS H&C | H45: 15
B46: 45209 | C46: VENTAS H&C | D46: 1000
B47: 45209 | C47: VENTAS H&C | D47: 500
B48: 45210 | C48: VENTAS H&C | H48: 10
B49: 45210 | C49: VENTAS H&C | D49: 500
B50: 45210 | C50: VENTAS H&C | D50: 1000
B51: 45210 | C51: VENTAS H&C | D51: 1000
B52: 45210 | C52: VENTAS H&C | D52: 2000
B53: 45210 | C53: VENTAS H&C | T53: 800
B54: 45211 | C54: VENTAS H&C | R54: 55
B55: 45211 | C55: JH | D55: 1000 | Q55: 500
B56: 45211 | C56: JH
B57: 45212 | C57: VENTAS H&C | O57: 124
B58: 45212 | C58: VENTAS H&C | O58: 320
B59: 45213 | C59: VENTAS H&C | O59: 450
B60: 45215 | C60: VENTAS H&C | T60: 320
B61: 45215 | C61: VENTAS H&C | D61: 2430
B62: 45215 | C62: VENTAS H&C | O62: 50
A65: SALDO | D65: =SUM(D4:D16)-SUM(D17:D64) -> 3600 | E65: =SUM(E4:E16)-SUM(E17:E64) -> 904 | F65: =SUM(F4:F16)-SUM(F17:F64) -> 284 | G65: =SUM(G4:G16)-SUM(G17:G64) -> 1136 | H65: =SUM(H4:H16)-SUM(H17:H64) -> 1295 | I65: =SUM(I4:I16)-SUM(I17:I64) -> 885 | J65: =SUM(J4:J16)-SUM(J17:J64) -> 2249 | K65: =SUM(K4:K16)-SUM(K17:K64) -> 1652 | ... U65: =SUM(U4:U16)-SUM(U17:U64) -> 52
D67: =+D65*0.38 -> 1368 | E67: =+E65*0.38 -> 343.52 | F67: =+F65*0.48 -> 136.32 | G67: =+G65*0.64 -> 727.04 | H67: =+H65*0.6 -> 777 | I67: =+I65*0.89 -> 787.65 | J67: =+J65*0.68 -> 1529.32 | K67: =+K65*0.66 -> 1090.32 | L67: =+L65*0.7 -> 281.4 | M67: =+M65*0.62 -> 63.86 | N67: =+N65*2.3 -> 25.3 | O67: =+O65*1.77 -> 1253.16 | P67: =+P65*2.35 -> 625.1 | Q67: =+Q65*1.92 -> 2344.32 | R67: =+R65*2.45 -> 788.9 | S67: =+S65*0.42 -> 1270.5 | T67: =+T65*0.32 -> 1068.16 | U67: =+U65*2 -> 104 | V67: =SUM(D67:U67) -> 14583.87
F71: 0.625 | G71: 4
F72: 0.5 | G72: 14
F73: 12 | G73: 2
F74: 0.375 | G74: 6
F75: 8 | G75: 4
F76: 6 | G76: 2
G77: =SUM(G71:G76) -> 32

Sheet STOCK 16 a 21
D2: PANDERETA | H2: 18 HUECOS | O2: TECHO 12 | R2: TECHO 15 | T2: ARTESANAL | V2: TIPO 4 | W2: TECHO 08
B3: FECHA | C3: CLIENTE | D3: SIPAN | E3: CHALPON | F3: CERAMICOS | G3: CALCA | H3: CERAMICOS | I3: TORRE FUERTE | J3: LARK | K3: FORTALEZA | L3: CRUZ CHALPON | M3: TAISON | N3: SIPAN | O3: LARK | P3: ITAL | Q3: FORTALEZA | R3: ITAL | S3: FORTALEZA | T3: BODOQUE | U3: PEQUEÑO | V3: FORTALEZA | W3: CERAMICOS
A4: INGRESO | C4: INICIAL | D4: 3550 | E4: 2852 | F4: 906 | G4: 206 | H4: 1000 | I4: 1309 | J4: 886 | K4: 2239 | L4: 1652 | M4: 405 | N4: 100 | P4: 701 | R4: 1166 | S4: 308 | T4: 3020 | U4: 3324 | V4: 278 | W4: 52
B5: 45216 | C5: M5P-711 | K5: 3500
B6: 45216 | C6: M6I-897 | O6: 1200
B7: 45218 | C7: M6I-897 | P7: 1200
B8: 45219 | C8: AZABACHE | D8: 2670
B9: 45220 | C9: M5P-711 | R9: 1000
A11: SALIDADA | B11: 45216 | C11: VENTAS H&C | P11: 130 | U11: 20
B12: 45216 | C12: PATRICIA | K12: 1200
B13: 45216 | C13: KELY | O13: 280
B14: 45217 | C14: VENTAS H&C | H14: 450
B15: 45218 | C15: JH | R15: 800
B16: 45218 | C16: VENTAS H&C | P16: =280+780 -> 1060
B17: 45219 | C17: VENTAS H&C | T17: 130 | U17: 70
B18: 45220 | C18: VENTAS H&C | D18: =150+1500+1000 -> 2650 | E18: 6
A24: SALDO | D24: =SUM(D4:D10)-SUM(D11:D23) -> 3570 | E24: =SUM(E4:E10)-SUM(E11:E23) -> 2846 | F24: =SUM(F4:F10)-SUM(F11:F23) -> 906 | G24: =SUM(G4:G10)-SUM(G11:G23) -> 206 | H24: =SUM(H4:H10)-SUM(H11:H23) -> 550 | I24: =SUM(I4:I10)-SUM(I11:I23) -> 1309 | J24: =SUM(J4:J10)-SUM(J11:J23) -> 886 | K24: =SUM(K4:K10)-SUM(K11:K23) -> 4539 | ... W24: =SUM(W4:W10)-SUM(W11:W23) -> 52
D26: =+D24*0.38 -> 1356.6 | E26: =+E24*0.41 -> 1166.86 | F26: =+F24*0.38 -> 344.28 | G26: =+G24*0.48 -> 98.88 | H26: =+H24*0.64 -> 352 | I26: =+I24*0.6 -> 785.4 | J26: =+J24*0.89 -> 788.54 | K26: =+K24*0.68 -> 3086.52 | L26: =+L24*0.66 -> 1090.32 | M26: =+M24*0.7 -> 283.5 | N26: =+N24*0.62 -> 62 | O26: =+O24*2.3 -> 2116 | P26: =+P24*1.77 -> 1258.47 | Q26: =+Q24*2.35 -> 0 | R26: =+R24*1.92 -> 2622.72 | S26: =+S24*2.45 -> 754.6 | T26: =+T24*0.42 -> 1213.8 | U26: =+U24*0.32 -> 1034.88 | V26: =+V24*0.8 -> 222.4 | W26: =+W24*2 -> 104 | X26: =SUM(D26:W26) -> 18741.77
G30: 0.625 | H30: 4
G31: 0.5 | H31: 14
G32: 12 | H32: 2
G33: 0.375 | H33: 6
G34: 8 | H34: 4
G35: 6 | H35: 2
H36: =SUM(H30:H35) -> 32

Sheet STOCK 22 a 28
D2: PANDERETA | H2: 18 HUECOS | O2: TECHO 12 | R2: TECHO 15 | T2: ARTESANAL | V2: TIPO 4 | W2: TECHO 08
B3: FECHA | C3: CLIENTE | D3: SIPAN | E3: CHALPON | F3: CERAMICOS | G3: CALCA | H3: CERAMICOS | I3: TORRE FUERTE | J3: LARK | K3: FORTALEZA | L3: CRUZ CHALPON | M3: TAISON | N3: SIPAN | O3: LARK | P3: ITAL | Q3: FORTALEZA | R3: ITAL | S3: FORTALEZA | T3: BODOQUE | U3: PEQUEÑO | V3: FORTALEZA | W3: CERAMICOS
A4: INGRESO | C4: INICIAL | D4: ='STOCK 16 a 21'!D24 -> 3570 | E4: ='STOCK 16 a 21'!E24 -> 2846 | F4: ='STOCK 16 a 21'!F24 -> 906 | G4: ='STOCK 16 a 21'!G24 -> 206 | H4: ='STOCK 16 a 21'!H24 -> 550 | I4: ='STOCK 16 a 21'!I24 -> 1309 | J4: ='STOCK 16 a 21'!J24 -> 886 | K4: ='STOCK 16 a 21'!K24 -> 4539 | ... W4: ='STOCK 16 a 21'!W24 -> 52
B5: 45223 | C5: AZABACHE | D5: 2150
B6: 45226 | C6: M5P-711 | T6: 3000
A11: SALIDADA | B11: 45222 | C11: VENTAS H&C | D11: 600 | T11: =2000+500 -> 2500
B12: 45223 | C12: VENTAS H&C | D12: =250+1000 -> 1250
B13: 45224 | C13: VENTAS H&C | D13: 200 | G13: 50 | P13: 20 | T13: 390
B14: 45225 | C14: VENTAS H&C | J14: 500 | U14: 75
A25: SALDO | D25: =SUM(D4:D10)-SUM(D11:D24) -> 3670 | E25: =SUM(E4:E10)-SUM(E11:E24) -> 2846 | F25: =SUM(F4:F10)-SUM(F11:F24) -> 906 | G25: =SUM(G4:G10)-SUM(G11:G24) -> 156 | H25: =SUM(H4:H10)-SUM(H11:H24) -> 550 | I25: =SUM(I4:I10)-SUM(I11:I24) -> 1309 | J25: =SUM(J4:J10)-SUM(J11:J24) -> 386 | K25: =SUM(K4:K10)-SUM(K11:K24) -> 4539 | ... W25: =SUM(W4:W10)-SUM(W11:W24) -> 52
D27: =+D25*0.38 -> 1394.6 | E27: =+E25*0.41 -> 1166.86 | F27: =+F25*0.38 -> 344.28 | G27: =+G25*0.48 -> 74.88 | H27: =+H25*0.64 -> 352 | I27: =+I25*0.6 -> 785.4 | J27: =+J25*0.89 -> 343.54 | K27: =+K25*0.68 -> 3086.52 | L27: =+L25*0.66 -> 1090.32 | M27: =+M25*0.7 -> 283.5 | N27: =+N25*0.62 -> 62 | O27: =+O25*2.3 -> 2116 | P27: =+P25*1.77 -> 1223.07 | Q27: =+Q25*2.35 -> 0 | R27: =+R25*1.92 -> 2622.72 | S27: =+S25*2.45 -> 754.6 | T27: =+T25*0.42 -> 1260 | U27: =+U25*0.32 -> 1010.88 | V27: =+V25*0.8 -> 222.4 | W27: =+W25*2 -> 104 | X27: =SUM(D27:W27) -> 18297.57
Q29: 232
G31: 0.625 | H31: 4
G32: 0.5 | H32: 14
G33: 12 | H33: 2
G34: 0.375 | H34: 6
G35: 8 | H35: 4
G36: 6 | H36: 2
H37: =SUM(H31:H36) -> 32

Sheet STOCK 29 a 04
D2: PANDERETA | H2: 18 HUECOS | O2: TECHO 12 | R2: TECHO 15 | T2: ARTESANAL | V2: TIPO 4 | W2: TECHO 08
B3: FECHA | C3: CLIENTE | D3: SIPAN | E3: CHALPON | F3: CERAM | G3: CALCA | H3: CERAM | I3: TORRE FUERTE | J3: LARK | K3: FORTALEZA | L3: CRUZ CHALPON | M3: TAISON | N3: SIPAN | O3: LARK | P3: ITAL | Q3: FORTALEZA | R3: ITAL | S3: FORTALEZA | T3: BODOQUE | U3: PEQUEÑO | V3: FORTALEZA | W3: CERAM
A4: INGRESO | C4: INICIAL | D4: ='STOCK 22 a 28'!D25 -> 3670 | E4: ='STOCK 22 a 28'!E25 -> 2846 | F4: ='STOCK 22 a 28'!F25 -> 906 | G4: ='STOCK 22 a 28'!G25 -> 156 | H4: ='STOCK 22 a 28'!H25 -> 550 | I4: ='STOCK 22 a 28'!I25 -> 1309 | J4: ='STOCK 22 a 28'!J25 -> 386 | K4: ='STOCK 22 a 28'!K25 -> 4539 | ... W4: ='STOCK 22 a 28'!W25 -> 52
B5: 45229 | C5: M6I-897 | J5: 1000
B6: 45230 | C6: M6I-897 | D6: 500
B7: 45230 | C7: M5P-711 | R7: 150
B8: 45231 | C8: M6I-897 | S8: 560
B9: 45233 | C9: M6I-897 | I9: 2200
B10: 45234 | C10: M6I-897 | D10: 1500
A12: SALIDADA | B12: 45229 | C12: VENTAS H&C | I12: 1200 | K12: 2000 | P12: 6 | S12: 300
B13: 45229 | C13: JH | D13: 2000
B14: 45230 | C14: VENTAS H&C | D14: 50 | M14: 200 | T14: =430+20 -> 450
B15: 45232 | C15: VENTAS H&C | D15: 1000
B16: 45233 | C16: VENTAS H&C | I16: 500 | M16: 100 | P16: 150 | R16: 400
B17: 45234 | C17: VENTAS H&C | D17: 70
A21: SALDO | D21: =SUM(D4:D11)-SUM(D12:D20) -> 2550 | E21: =SUM(E4:E11)-SUM(E12:E20) -> 2846 | F21: =SUM(F4:F11)-SUM(F12:F20) -> 906 | G21: =SUM(G4:G11)-SUM(G12:G20) -> 156 | H21: =SUM(H4:H11)-SUM(H12:H20) -> 550 | I21: =SUM(I4:I11)-SUM(I12:I20) -> 1809 | J21: =SUM(J4:J11)-SUM(J12:J20) -> 1386 | K21: =SUM(K4:K11)-SUM(K12:K20) -> 2539 | ... W21: =SUM(W4:W11)-SUM(W12:W20) -> 52
D23: =+D21*0.38 -> 969 | E23: =+E21*0.41 -> 1166.86 | F23: =+F21*0.38 -> 344.28 | G23: =+G21*0.48 -> 74.88 | H23: =+H21*0.64 -> 352 | I23: =+I21*0.6 -> 1085.4 | J23: =+J21*0.89 -> 1233.54 | K23: =+K21*0.68 -> 1726.52 | L23: =+L21*0.66 -> 1090.32 | M23: =+M21*0.7 -> 73.5 | N23: =+N21*0.62 -> 62 | O23: =+O21*2.3 -> 2116 | P23: =+P21*1.77 -> 946.95 | Q23: =+Q21*2.35 -> 0 | R23: =+R21*1.92 -> 2142.72 | S23: =+S21*2.36 -> 1340.48 | T23: =+T21*0.42 -> 1071 | U23: =+U21*0.32 -> 1010.88 | V23: =+V21*0.8 -> 222.4 | W23: =+W21*2 -> 104 | X23: =SUM(D23:W23) -> 17132.73
S24: =2.45-2.36 -> 0.09
Q25: 232 | S25: =8*S24 -> 0.72
G27: 0.625 | H27: 4
G28: 0.5 | H28: 14
G29: 12 | H29: 2
G30: 0.375 | H30: 6
G31: 8 | H31: 4
G32: 6 | H32: 2
H33: =SUM(H27:H32) -> 32

Sheet STOCK 05 a 11
D2: PANDERETA | H2: 18 HUECOS | O2: TECHO 12 | R2: TECHO 15 | T2: ARTESANAL | V2: TIPO 4 | W2: TECHO 08
B3: FECHA | C3: CLIENTE | D3: SIPAN | E3: CHALPON | F3: CERAM | G3: CALCA | H3: CERAM | I3: TORRE FUERTE | J3: LARK | K3: FORTALEZA | L3: CRUZ CHALPON | M3: TAISON | N3: SIPAN | O3: LARK | P3: ITAL | Q3: FORTALEZA | R3: ITAL | S3: FORTALEZA | T3: BODOQUE | U3: PEQUEÑO | V3: FORTALEZA | W3: CERAM
A4: INGRESO | C4: INICIAL | D4: ='STOCK 29 a 04'!D21 -> 2550 | E4: ='STOCK 29 a 04'!E21 -> 2846 | F4: ='STOCK 29 a 04'!F21 -> 906 | G4: ='STOCK 29 a 04'!G21 -> 156 | H4: ='STOCK 29 a 04'!H21 -> 550 | I4: ='STOCK 29 a 04'!I21 -> 1809 | J4: ='STOCK 29 a 04'!J21 -> 1386 | K4: ='STOCK 29 a 04'!K21 -> 2539 | ... W4: ='STOCK 29 a 04'!W21 -> 52
B5: 45239 | C5: M6I-897 | R5: 340
B6: 45239 | C6: M5P-711 | D6: 4500
B7: 45240 | C7: M6I-897 | D7: 4500 | P7: 650
B8: 45240 | C8: M5P-711 | T8: 2000 | U8: 1000
A12: SALIDADA | B12: 45236 | C12: VENTAS H&C | H12: 550 | T12: 300 | U12: 100
B13: 45237 | C13: VENTAS H&C | I13: 1000 | T13: 1000 | U13: 1000
B14: 45238 | C14: VENTAS H&C | T14: 200 | U14: 400
B15: 45239 | C15: VENTAS H&C | U15: 1000
B16: 45240 | C16: VENTAS H&C | T16: =400+45 -> 445
B17: 45241 | C17: VENTAS H&C | T17: 80
A21: SALDO | D21: =SUM(D4:D11)-SUM(D12:D20) -> 11550 | E21: =SUM(E4:E11)-SUM(E12:E20) -> 2846 | F21: =SUM(F4:F11)-SUM(F12:F20) -> 906 | G21: =SUM(G4:G11)-SUM(G12:G20) -> 156 | H21: =SUM(H4:H11)-SUM(H12:H20) -> 0 | I21: =SUM(I4:I11)-SUM(I12:I20) -> 809 | J21: =SUM(J4:J11)-SUM(J12:J20) -> 1386 | K21: =SUM(K4:K11)-SUM(K12:K20) -> 2539 | ... W21: =SUM(W4:W11)-SUM(W12:W20) -> 52
D23: =2550*0.38+9000*0.36 -> 4209 | E23: =+E21*0.41 -> 1166.86 | F23: =+F21*0.38 -> 344.28 | G23: =+G21*0.48 -> 74.88 | H23: =+H21*0.64 -> 0 | I23: =+I21*0.6 -> 485.4 | J23: =+J21*0.89 -> 1233.54 | K23: =+K21*0.68 -> 1726.52 | L23: =+L21*0.66 -> 1090.32 | M23: =+M21*0.7 -> 73.5 | N23: =+N21*0.62 -> 62 | O23: =+O21*2.3 -> 2116 | P23: =+P21*1.77 -> 2097.45 | Q23: =+Q21*2.35 -> 0 | R23: =+R21*1.92 -> 2795.52 | S23: =+S21*2.36 -> 1340.48 | T23: =+T21*0.42 -> 1060.5 | U23: =+U21*0.32 -> 530.88 | V23: =+V21*0.8 -> 222.4 | W23: =+W21*2 -> 104 | X23: =SUM(D23:W23) -> 20733.53
C25: REAL | D25: 11687 | E25: 2874 | F25: 906 | G25: 206 | H25: 115 | I25: 804 | J25: 1381 | K25: 2515 | L25: 1647 | M25: 96 | N25: 100 | O25: 931 | P25: 1184 | R25: 1510 | S25: 567 | T25: 2107 | U25: 1489 | V25: 288 | W25: 54
C26: DIFERENCIA | D26: =D25-D21 -> 137 | E26: =E25-E21 -> 28 | F26: =F25-F21 -> 0 | G26: =G25-G21 -> 50 | H26: =H25-H21 -> 115 | I26: =I25-I21 -> -5 | J26: =J25-J21 -> -5 | K26: =K25-K21 -> -24 | ... W26: =W25-W21 -> 2

Sheet STOCK 12 a 18
D2: PANDERETA | H2: 18 HUECOS | O2: TECHO 12 | R2: TECHO 15 | T2: ARTESANAL | V2: TIPO 4 | W2: TECHO 08
B3: FECHA | C3: CLIENTE | D3: SIPAN | E3: CHALPON | F3: CERAM | G3: CALCA | H3: CERAM | I3: TORRE FUERTE | J3: LARK | K3: FORTALEZA | L3: CRUZ CHALPON | M3: TAISON | N3: SIPAN | O3: LARK | P3: ITAL | Q3: FORTALEZA | R3: ITAL | S3: FORTALEZA | T3: BODOQUE | U3: PEQUEÑO | V3: FORTALEZA | W3: CERAM
A4: INGRESO | C4: INICIAL | D4: ='STOCK 05 a 11'!D21 -> 11550 | E4: ='STOCK 05 a 11'!E21 -> 2846 | F4: ='STOCK 05 a 11'!F21 -> 906 | G4: ='STOCK 05 a 11'!G21 -> 156 | H4: ='STOCK 05 a 11'!H21 -> 0 | I4: ='STOCK 05 a 11'!I21 -> 809 | J4: ='STOCK 05 a 11'!J21 -> 1386 | K4: ='STOCK 05 a 11'!K21 -> 2539 | ... W4: ='STOCK 05 a 11'!W21 -> 52
B5: 45243 | C5: M6I-897 | R5: 200
B6: 45243 | C6: M5P-711 | D6: 3300
B7: 45244 | C7: JH | H7: 4000
B8: 45247 | C8: M5P-711 | U8: 1000
B9: 45248 | C9: M5P-711 | D9: 4500
A13: SALIDADA | B13: 45242 | C13: VENTAS H&C | G13: =20+30 -> 50
B14: 45243 | C14: VENTAS H&C | D14: =1000+1450 -> 2450 | K14: 1000 | P14: 350 | R14: 24
B15: 45244 | C15: VENTAS H&C | O15: 360 | R15: 300 | U15: 500
B16: 45245 | C16: VENTAS H&C | D16: 2000 | G16: 80 | P16: 50 | T16: 50 | U16: 100
B17: 45246 | C17: VENTAS H&C | D17: 23 | U17: 150
B18: 45247 | C18: VENTAS H&C | D18: =1000+50+500 -> 1550 | N18: 100 | P18: 20 | U18: 20
B19: 45248 | C19: VENTAS H&C | D19: =1000+200 -> 1200 | U19: 300
A22: SALDO | D22: =SUM(D4:D12)-SUM(D13:D21) -> 12127 | E22: =SUM(E4:E12)-SUM(E13:E21) -> 2846 | F22: =SUM(F4:F12)-SUM(F13:F21) -> 906 | G22: =SUM(G4:G12)-SUM(G13:G21) -> 26 | H22: =SUM(H4:H12)-SUM(H13:H21) -> 4000 | I22: =SUM(I4:I12)-SUM(I13:I21) -> 809 | J22: =SUM(J4:J12)-SUM(J13:J21) -> 1386 | K22: =SUM(K4:K12)-SUM(K13:K21) -> 1539 | ... W22: =SUM(W4:W12)-SUM(W13:W21) -> 52
D24: =D22*0.36 -> 4365.72 | E24: =+E22*0.41 -> 1166.86 | F24: =+F22*0.38 -> 344.28 | G24: =+G22*0.48 -> 12.48 | H24: =+H22*0.57 -> 2280 | I24: =+I22*0.6 -> 485.4 | J24: =+J22*0.89 -> 1233.54 | K24: =+K22*0.68 -> 1046.52 | L24: =+L22*0.66 -> 1090.32 | M24: =+M22*0.7 -> 73.5 | N24: =+N22*0.62 -> 0 | O24: =+O22*2.3 -> 1288 | P24: =+P22*1.77 -> 1354.05 | Q24: =+Q22*2.35 -> 0 | R24: =+R22*1.92 -> 2557.44 | S24: =+S22*2.36 -> 1340.48 | T24: =+T22*0.42 -> 1039.5 | U24: =+U22*0.32 -> 508.48 | V24: =+V22*0.8 -> 222.4 | W24: =+W22*2 -> 104 | X24: =SUM(D24:W24) -> 20512.97
C26: REAL
H34: 182015Mj

Sheet STOCK 19 a 25
D2: PANDERETA | H2: 18 HUECOS | O2: TECHO 12 | R2: TECHO 15 | T2: ARTESANAL | V2: TIPO 4 | W2: TECHO 08
B3: FECHA | C3: CLIENTE | D3: SIPAN | E3: CHALPON | F3: CERAM | G3: CALCA | H3: CERAM | I3: TORRE FUERTE | J3: LARK | K3: FORTALEZA | L3: CRUZ CHALPON | M3: TAISON | N3: SIPAN | O3: LARK | P3: ITAL | Q3: FORTALEZA | R3: ITAL | S3: FORTALEZA | T3: BODOQUE | U3: PEQUEÑO | V3: FORTALEZA | W3: CERAM
A4: INGRESO | C4: INICIAL | D4: ='STOCK 12 a 18'!D22 -> 12127 | E4: ='STOCK 12 a 18'!E22 -> 2846 | F4: ='STOCK 12 a 18'!F22 -> 906 | G4: ='STOCK 12 a 18'!G22 -> 26 | H4: ='STOCK 12 a 18'!H22 -> 4000 | I4: ='STOCK 12 a 18'!I22 -> 809 | J4: ='STOCK 12 a 18'!J22 -> 1386 | K4: ='STOCK 12 a 18'!K22 -> 1539 | ... W4: ='STOCK 12 a 18'!W22 -> 52
B5: 45251 | C5: M6I-897 | D5: 500
B6: 45251 | C6: DEV MORANTE | D6: 500
B7: 45252 | C7: M6I-897 | P7: 650
B8: 45254 | C8: M6I-897 | D8: 4500
A14: SALIDADA | B14: 45250 | C14: VENTAS H&C | D14: =500+630 -> 1130 | E14: 500 | H14: =10+50 -> 60 | T14: 20 | U14: 1000
B15: 45251 | C15: VENTAS H&C | D15: 500 | J15: 1 | P15: 150 | T15: 60
B16: 45252 | C16: VENTAS H&C | I16: 700 | P16: 275
B17: 45252 | C17: VENTAS JORDY | D17: 1500
B18: 45253 | C18: VENTAS H&C | D18: =500+1000 -> 1500 | K18: 100 | P18: 50
B19: 45254 | C19: VENTAS H&C | D19: 1000 | K19: =500+1000-90 -> 1410 | P19: 400 | U19: 30
B20: 45254 | C20: VENTAS JORDY | D20: 1000
A24: SALDO | D24: =SUM(D4:D13)-SUM(D14:D23) -> 10997 | E24: =SUM(E4:E13)-SUM(E14:E23) -> 2346 | F24: =SUM(F4:F13)-SUM(F14:F23) -> 906 | G24: =SUM(G4:G13)-SUM(G14:G23) -> 26 | H24: =SUM(H4:H13)-SUM(H14:H23) -> 3940 | I24: =SUM(I4:I13)-SUM(I14:I23) -> 109 | J24: =SUM(J4:J13)-SUM(J14:J23) -> 1385 | K24: =SUM(K4:K13)-SUM(K14:K23) -> 29 | ... W24: =SUM(W4:W13)-SUM(W14:W23) -> 52
D26: =D24*0.36 -> 3958.92 | E26: =+E24*0.41 -> 961.86 | F26: =+F24*0.38 -> 344.28 | G26: =+G24*0.48 -> 12.48 | H26: =+H24*0.57 -> 2245.8 | I26: =+I24*0.6 -> 65.4 | J26: =+J24*0.89 -> 1232.65 | K26: =+K24*0.68 -> 19.72 | L26: =+L24*0.66 -> 1090.32 | M26: =+M24*0.7 -> 73.5 | N26: =+N24*0.62 -> 0 | O26: =+O24*2.3 -> 1288 | P26: =+P24*1.77 -> 955.8 | Q26: =+Q24*2.35 -> 0 | R26: =+R24*1.92 -> 2557.44 | S26: =+S24*2.36 -> 1340.48 | T26: =+T24*0.42 -> 1005.9 | U26: =+U24*0.32 -> 178.88 | V26: =+V24*0.8 -> 222.4 | W26: =+W24*2 -> 104 | X26: =SUM(D26:W26) -> 17657.83
C28: REAL
C29: DIFERENCIA | D29: =D28-D24 -> -10997 | E29: =E28-E24 -> -2346 | F29: =F28-F24 -> -906 | G29: =G28-G24 -> -26 | H29: =H28-H24 -> -3940 | I29: =I28-I24 -> -109 | J29: =J28-J24 -> -1385 | K29: =K28-K24 -> -29 | ... W29: =W28-W24 -> -52
H36: 182015Mj

Sheet STOCK 26 a 02
D2: PANDERETA | H2: 18 HUECOS | O2: TECHO 12 | R2: TECHO 15 | T2: ARTESANAL | V2: TIPO 4 | W2: TECHO 08
B3: FECHA | C3: CLIENTE | D3: SIPAN | E3: CHALPON | F3: CERAM | G3: CALCA | H3: CERAM | I3: TORRE FUERTE | J3: LARK | K3: FORTALEZA | L3: CRUZ CHALPON | M3: TAISON | N3: SIPAN | O3: LARK | P3: ITAL | Q3: FORTALEZA | R3: ITAL | S3: FORTALEZA | T3: BODOQUE | U3: PEQUEÑO | V3: FORTALEZA | W3: CERAM
A4: INGRESO | C4: INICIAL | D4: ='STOCK 19 a 25'!D24 -> 10997 | E4: ='STOCK 19 a 25'!E24 -> 2346 | F4: ='STOCK 19 a 25'!F24 -> 906 | G4: ='STOCK 19 a 25'!G24 -> 26 | H4: ='STOCK 19 a 25'!H24 -> 3940 | I4: ='STOCK 19 a 25'!I24 -> 109 | J4: ='STOCK 19 a 25'!J24 -> 1385 | K4: ='STOCK 19 a 25'!K24 -> 29 | ... W4: ='STOCK 19 a 25'!W24 -> 52
B5: 45262 | C5: M6I-897 | T5: 2830
A11: SALIDADA | B11: 45257 | C11: VENTAS JORDY | L11: 1652 | M11: 74
B12: 45257 | C12: MERMAS | K12: 29 | M12: 31
B13: 45257 | C13: VENTAS H&C | D13: 200 | H13: 150 | R13: 250 | T13: =300+20 -> 320 | U13: 250
B14: 45258 | C14: VENTAS H&C | D14: 1 | H14: 23
B15: 45259 | C15: VENTAS H&C | E15: 2000 | T15: 1000
B16: 45260 | C16: VENTAS H&C | D16: =1000+1000 -> 2000 | H16: 490
B17: 45261 | C17: VENTAS H&C | O17: 360 | P17: 30 | R17: 20
B18: 45262 | C18: VENTAS H&C | R18: 600
A21: SALDO | D21: =SUM(D4:D10)-SUM(D11:D20) -> 8796 | E21: =SUM(E4:E10)-SUM(E11:E20) -> 346 | F21: =SUM(F4:F10)-SUM(F11:F20) -> 906 | G21: =SUM(G4:G10)-SUM(G11:G20) -> 26 | H21: =SUM(H4:H10)-SUM(H11:H20) -> 3277 | I21: =SUM(I4:I10)-SUM(I11:I20) -> 109 | J21: =SUM(J4:J10)-SUM(J11:J20) -> 1385 | K21: =SUM(K4:K10)-SUM(K11:K20) -> 0 | ... W21: =SUM(W4:W10)-SUM(W11:W20) -> 52
D23: =D21*0.36 -> 3166.56 | E23: =+E21*0.41 -> 141.86 | F23: =+F21*0.38 -> 344.28 | G23: =+G21*0.48 -> 12.48 | H23: =+H21*0.57 -> 1867.89 | I23: =+I21*0.6 -> 65.4 | J23: =+J21*0.89 -> 1232.65 | K23: =+K21*0.68 -> 0 | L23: =+L21*0.66 -> 0 | M23: =+M21*0.7 -> 0 | N23: =+N21*0.62 -> 0 | O23: =+O21*2.3 -> 460 | P23: =+P21*1.77 -> 902.7 | Q23: =+Q21*2.35 -> 0 | R23: =+R21*1.92 -> 887.04 | S23: =+S21*2.36 -> 1340.48 | T23: =+T21*0.42 -> 1640.1 | U23: =+U21*0.32 -> 98.88 | V23: =+V21*0.8 -> 222.4 | W23: =+W21*2 -> 104 | X23: =SUM(D23:W23) -> 12486.72
C25: REAL
C26: DIFERENCIA | D26: =D25-D21 -> -8796 | E26: =E25-E21 -> -346 | F26: =F25-F21 -> -906 | G26: =G25-G21 -> -26 | H26: =H25-H21 -> -3277 | I26: =I25-I21 -> -109 | J26: =J25-J21 -> -1385 | K26: =K25-K21 -> 0 | ... W26: =W25-W21 -> -52
H33: 182015Mj

Sheet STOCK 03 a 09
D2: PANDERETA | H2: 18 HUECOS | O2: TECHO 12 | R2: TECHO 15 | T2: ARTESANAL | V2: TIPO 4 | W2: TECHO 08
B3: FECHA | C3: CLIENTE | D3: SIPAN | E3: CHALPON | F3: CERAM | G3: CALCA | H3: CERAM | I3: TORRE FUERTE | J3: LARK | K3: FORTALEZA | L3: CRUZ CHALPON | M3: TAISON | N3: SIPAN | O3: LARK | P3: ITAL | Q3: FORTALEZA | R3: ITAL | S3: FORTALEZA | T3: BODOQUE | U3: PEQUEÑO | V3: FORTALEZA | W3: CERAM
A4: INGRESO | D4: ='STOCK 26 a 02'!D21 -> 8796 | E4: ='STOCK 26 a 02'!E21 -> 346 | F4: ='STOCK 26 a 02'!F21 -> 906 | G4: ='STOCK 26 a 02'!G21 -> 26 | H4: ='STOCK 26 a 02'!H21 -> 3277 | I4: ='STOCK 26 a 02'!I21 -> 109 | J4: ='STOCK 26 a 02'!J21 -> 1385 | K4: ='STOCK 26 a 02'!K21 -> 0 | ... W4: ='STOCK 26 a 02'!W21 -> 52
B5: 45265 | C5: M5P-711 | K5: 1500
B6: 45267 | C6: M6I-897 | D6: 4500 | P6: 700 | R6: 500
B7: 45268 | C7: M5P-711 | U7: 3000
B8: 45269 | C8: M6I-897 | K8: 1500
A11: SALIDADA | B11: 45264 | C11: H&C VENTAS | D11: 500 | P11: 230
B12: 45265 | C12: H&C VENTAS | D12: 1000 | K12: 500 | P12: =30+80 -> 110
B13: 45266 | C13: H&C VENTAS | J13: 1000 | P13: 90
B14: 45267 | C14: H&C VENTAS | T14: =5+10 -> 15
B15: 45268 | C15: H&C VENTAS | K15: 500
B16: 45269 | C16: H&C VENTAS | E16: 300
A21: SALDO | D21: =SUM(D4:D10)-SUM(D11:D20) -> 11796 | E21: =SUM(E4:E10)-SUM(E11:E20) -> 46 | F21: =SUM(F4:F10)-SUM(F11:F20) -> 906 | G21: =SUM(G4:G10)-SUM(G11:G20) -> 26 | H21: =SUM(H4:H10)-SUM(H11:H20) -> 3277 | I21: =SUM(I4:I10)-SUM(I11:I20) -> 109 | J21: =SUM(J4:J10)-SUM(J11:J20) -> 385 | K21: =SUM(K4:K10)-SUM(K11:K20) -> 2000 | ... W21: =SUM(W4:W10)-SUM(W11:W20) -> 52
D23: =D21*0.36 -> 4246.56 | E23: =+E21*0.41 -> 18.86 | F23: =+F21*0.38 -> 344.28 | G23: =+G21*0.48 -> 12.48 | H23: =+H21*0.57 -> 1867.89 | I23: =+I21*0.6 -> 65.4 | J23: =+J21*0.89 -> 342.65 | K23: =+K21*0.68 -> 1360 | L23: =+L21*0.66 -> 0 | M23: =+M21*0.7 -> 0 | N23: =+N21*0.62 -> 0 | O23: =+O21*2.3 -> 460 | P23: =+P21*1.77 -> 1380.6 | Q23: =+Q21*2.35 -> 0 | R23: =+R21*1.92 -> 1847.04 | S23: =+S21*2.36 -> 1340.48 | T23: =+T21*0.42 -> 1633.8 | U23: =+U21*0.32 -> 1058.88 | V23: =+V21*0.8 -> 222.4 | W23: =+W21*2 -> 104 | X23: =SUM(D23:W23) -> 16305.32

Sheet STOCK 10 a 16
D2: PANDERETA | H2: 18 HUECOS | O2: TECHO 12 | R2: TECHO 15 | T2: ARTESANAL | V2: TIPO 4 | W2: TECHO 08
B3: FECHA | C3: CLIENTE | D3: SIPAN | E3: CHALPON | F3: CERAM | G3: CALCA | H3: CERAM | I3: TORRE FUERTE | J3: LARK | K3: FORTALEZA | L3: CRUZ CHALPON | M3: TAISON | N3: SIPAN | O3: LARK | P3: ITAL | Q3: FORTALEZA | R3: ITAL | S3: FORTALEZA | T3: BODOQUE | U3: PEQUEÑO | V3: FORTALEZA | W3: CERAM
A4: INGRESO | D4: ='STOCK 03 a 09'!D21 -> 11796 | E4: ='STOCK 03 a 09'!E21 -> 46 | F4: ='STOCK 03 a 09'!F21 -> 906 | G4: ='STOCK 03 a 09'!G21 -> 26 | H4: ='STOCK 03 a 09'!H21 -> 3277 | I4: ='STOCK 03 a 09'!I21 -> 109 | J4: ='STOCK 03 a 09'!J21 -> 385 | K4: ='STOCK 03 a 09'!K21 -> 2000 | ... W4: ='STOCK 03 a 09'!W21 -> 52
B5: 45272 | C5: M6I-897 | J5: 2458
B6: 45272 | C6: M5P-711 | P6: 1200 | Q6: 600 | S6: 500
B7: 45273 | C7: M6I-897 | R7: 1000
B8: 45275 | C8: M6I-897 | D8: 4500
A11: SALIDADA | B11: 45271 | C11: VENTAS H&C | D11: =3000+200 -> 3200 | H11: 28 | P11: 800 | R11: 450 | U11: 1000
B12: 45272 | C12: VENTAS H&C | J12: 370
B13: 45273 | C13: VENTAS H&C | D13: 70
B14: 45274 | C14: VENTAS H&C | D14: 1000 | K14: 1000 | P14: 250 | R14: =50+34 -> 84 | T14: 35 | U14: 500
B15: 45275 | C15: VENTAS H&C | D15: 1000 | P15: =30+20 -> 50
B16: 45276 | C16: VENTAS H&C | H16: 1000
A21: SALDO | D21: =SUM(D4:D10)-SUM(D11:D20) -> 11026 | E21: =SUM(E4:E10)-SUM(E11:E20) -> 46 | F21: =SUM(F4:F10)-SUM(F11:F20) -> 906 | G21: =SUM(G4:G10)-SUM(G11:G20) -> 26 | H21: =SUM(H4:H10)-SUM(H11:H20) -> 2249 | I21: =SUM(I4:I10)-SUM(I11:I20) -> 109 | J21: =SUM(J4:J10)-SUM(J11:J20) -> 2473 | K21: =SUM(K4:K10)-SUM(K11:K20) -> 1000 | ... W21: =SUM(W4:W10)-SUM(W11:W20) -> 52
D23: =D21*0.36 -> 3969.36 | E23: =+E21*0.41 -> 18.86 | F23: =+F21*0.38 -> 344.28 | G23: =+G21*0.48 -> 12.48 | H23: =+H21*0.57 -> 1281.93 | I23: =+I21*0.6 -> 65.4 | J23: =+J21*0.89-(2458*0.02) -> 2151.81 | K23: =+K21*0.68 -> 680 | L23: =+L21*0.66 -> 0 | M23: =+M21*0.7 -> 0 | N23: =+N21*0.62 -> 0 | O23: =+O21*2.3 -> 460 | P23: =+P21*1.77 -> 1557.6 | Q23: =+Q21*2.26 -> 1356 | R23: =+R21*1.92 -> 2741.76 | S23: =+S21*2.36 -> 2520.48 | T23: =+T21*0.42 -> 1619.1 | U23: =+U21*0.32 -> 578.88 | V23: =+V21*0.8 -> 222.4 | W23: =+W21*2 -> 104 | X23: =SUM(D23:W23) -> 19684.34
J25: =2458*0.87 -> 2138.46
J26: =15*0.89 -> 13.35

Sheet STOCK 17 a 23
D2: PANDERETA | H2: 18 HUECOS | O2: TECHO 12 | R2: TECHO 15 | T2: ARTESANAL | V2: TIPO 4 | W2: TECHO 08
B3: FECHA | C3: CLIENTE | D3: SIPAN | E3: CHALPON | F3: CERAM | G3: CALCA | H3: CERAM | I3: TORRE FUERTE | J3: LARK | K3: FORTALEZA | L3: CRUZ CHALPON | M3: TAISON | N3: SIPAN | O3: LARK | P3: ITAL | Q3: FORTALEZA | R3: ITAL | S3: FORTALEZA | T3: BODOQUE | U3: PEQUEÑO | V3: FORTALEZA | W3: CERAM
A4: INGRESO | D4: ='STOCK 10 a 16'!D21 -> 11026 | E4: ='STOCK 10 a 16'!E21 -> 46 | F4: ='STOCK 10 a 16'!F21 -> 906 | G4: ='STOCK 10 a 16'!G21 -> 26 | H4: ='STOCK 10 a 16'!H21 -> 2249 | I4: ='STOCK 10 a 16'!I21 -> 109 | J4: ='STOCK 10 a 16'!J21 -> 2473 | K4: ='STOCK 10 a 16'!K21 -> 1000 | ... W4: ='STOCK 10 a 16'!W21 -> 52
B5: 45279 | C5: M6I-897 | K5: 3500
B6: 45279 | C6: M5P-711 | U6: 2000
B7: 45280 | C7: AZABACHE | D7: 3300
B8: 45282 | C8: M5P-711 | T8: 2500
B9: 45283 | C9: M6I-897 | K9: 1500
A11: SALIDADA | B11: 45278 | C11: VENTAS H&C | O11: 200 | T11: 1000 | U11: =20+500 -> 520
B12: 45279 | C12: VENTAS H&C | D12: 1000 | U12: 25
B13: 45280 | C13: VENTAS H&C | D13: 1500 | R13: 5
B14: 45282 | C14: VENTAS H&C | T14: =1000+10 -> 1010 | U14: 10
B15: 45283 | C15: VENTAS H&C | D15: 50
A21: SALDO | D21: =SUM(D4:D10)-SUM(D11:D20) -> 11776 | E21: =SUM(E4:E10)-SUM(E11:E20) -> 46 | F21: =SUM(F4:F10)-SUM(F11:F20) -> 906 | G21: =SUM(G4:G10)-SUM(G11:G20) -> 26 | H21: =SUM(H4:H10)-SUM(H11:H20) -> 2249 | I21: =SUM(I4:I10)-SUM(I11:I20) -> 109 | J21: =SUM(J4:J10)-SUM(J11:J20) -> 2473 | K21: =SUM(K4:K10)-SUM(K11:K20) -> 6000 | ... W21: =SUM(W4:W10)-SUM(W11:W20) -> 52
D23: =D21*0.36 -> 4239.36 | E23: =+E21*0.41 -> 18.86 | F23: =+F21*0.38 -> 344.28 | G23: =+G21*0.48 -> 12.48 | H23: =+H21*0.57 -> 1281.93 | I23: =+I21*0.6 -> 65.4 | J23: =+J21*0.89-(2458*0.02) -> 2151.81 | K23: =+K21*0.68 -> 4080 | L23: =+L21*0.66 -> 0 | M23: =+M21*0.7 -> 0 | N23: =+N21*0.62 -> 0 | O23: =+O21*2.3 -> 0 | P23: =+P21*1.77 -> 1557.6 | Q23: =+Q21*2.26 -> 1356 | R23: =+R21*1.92 -> 2732.16 | S23: =+S21*2.36 -> 2520.48 | T23: =+T21*0.42 -> 1824.9 | U23: =+U21*0.32 -> 1041.28 | V23: =+V21*0.8 -> 222.4 | W23: =+W21*2 -> 104 | X23: =SUM(D23:W23) -> 23552.94
J25: =2458*0.87 -> 2138.46
J26: =15*0.89 -> 13.35

Sheet STOCK 24 a 30
D2: PANDERETA | H2: 18 HUECOS | O2: TECHO 12 | R2: TECHO 15 | T2: ARTESANAL | V2: TIPO 4 | W2: TECHO 08
B3: FECHA | C3: CLIENTE | D3: SIPAN | E3: CHALPON | F3: CERAM | G3: CALCA | H3: CERAM | I3: TORRE FUERTE | J3: LARK | K3: FORTALEZA | L3: CRUZ CHALPON | M3: TAISON | N3: SIPAN | O3: LARK | P3: ITAL | Q3: FORTALEZA | R3: ITAL | S3: FORTALEZA | T3: BODOQUE | U3: PEQUEÑO | V3: FORTALEZA | W3: CERAM
A4: INGRESO | D4: ='STOCK 17 a 23'!D21 -> 11776 | E4: ='STOCK 17 a 23'!E21 -> 46 | F4: ='STOCK 17 a 23'!F21 -> 906 | G4: ='STOCK 17 a 23'!G21 -> 26 | H4: ='STOCK 17 a 23'!H21 -> 2249 | I4: ='STOCK 17 a 23'!I21 -> 109 | J4: ='STOCK 17 a 23'!J21 -> 2473 | K4: ='STOCK 17 a 23'!K21 -> 6000 | ... W4: ='STOCK 17 a 23'!W21 -> 52
B5: 45286 | C5: M6I-897 | J5: 500
B6: 45287 | C6: M5P-711 | E6: 4500
B7: 45289 | C7: M6I-897 | J7: 2000
B8: 45290 | C8: M6I-897 | O8: 1200
A11: SALIDADA | B11: 45286 | C11: VENTAS H&C | T11: 100
B12: 45286 | C12: JORDY H | J12: 2000
B13: 45287 | C13: JORDY H | D13: 2700 | K13: 1000
B14: 45287 | C14: VENTAS H&C | D14: =500+400+2000 -> 2900 | T14: 200
B15: 45288 | C15: VENTAS H&C | D15: 350 | T15: 300
B16: 45289 | C16: VENTAS H&C | H16: 800 | T16: 100
B17: 45290 | C17: VENTAS H&C | D17: =2000+100+1000 -> 3100 | E17: 346 | O17: 900
X19: =+X23-X21 -> 219.71
A21: SALDO | D21: =SUM(D4:D10)-SUM(D11:D20) -> 2726 | E21: =SUM(E4:E10)-SUM(E11:E20) -> 4200 | F21: =SUM(F4:F10)-SUM(F11:F20) -> 906 | G21: =SUM(G4:G10)-SUM(G11:G20) -> 26 | H21: =SUM(H4:H10)-SUM(H11:H20) -> 1449 | I21: =SUM(I4:I10)-SUM(I11:I20) -> 109 | J21: =SUM(J4:J10)-SUM(J11:J20) -> 2973 | K21: =SUM(K4:K10)-SUM(K11:K20) -> 5000 | ... W21: =SUM(W4:W10)-SUM(W11:W20) -> 52 | X21: =SUM(X22:X29) -> 21407.07
D23: =D21*0.36 -> 981.36 | E23: =+E21*0.4 -> 1680 | F23: =+F21*0.38 -> 344.28 | G23: =+G21*0.48 -> 12.48 | H23: =+H21*0.57 -> 825.93 | I23: =+I21*0.6 -> 65.4 | J23: =+J21*0.87 -> 2586.51 | K23: =+K21*0.68 -> 3400 | L23: =+L21*0.66 -> 0 | M23: =+M21*0.7 -> 0 | N23: =+N21*0.62 -> 0 | O23: =+O21*2.22 -> 666 | P23: =+P21*1.77 -> 1557.6 | Q23: =+Q21*2.26 -> 1356 | R23: =+R21*1.92 -> 2732.16 | S23: =+S21*2.36 -> 2520.48 | T23: =+T21*0.42 -> 1530.9 | U23: =+U21*0.32 -> 1041.28 | V23: =+V21*0.8 -> 222.4 | W23: =+W21*2 -> 104 | X23: =SUM(D23:W23) -> 21626.78
D25: 2889 | E25: 4210 | F25: 906 | H25: 1552 | I25: 103 | J25: 2955 | K25: 5020 | O25: 300 | P25: 870 | Q25: 602 | R25: 1444 | S25: 1068 | T25: 3012 | U25: 3042 | V25: 280 | W25: 43
D27: =+D25-D21 -> 163 | E27: =+E25-E21 -> 10 | F27: =+F25-F21 -> 0 | G27: =+G25-G21 -> -26 | H27: =+H25-H21 -> 103 | I27: =+I25-I21 -> -6 | J27: =+J25-J21 -> -18 | K27: =+K25-K21 -> 20 | ... W27: =+W25-W21 -> -9
D28: =+D27*0.36 -> 58.68 | E28: =+E27*0.4 -> 4 | H28: =+H27*0.57 -> 58.71 | K28: =+K27*0.68 -> 13.6 | Q28: =+Q27*2.26 -> 4.52 | R28: =+R27*1.92 -> 40.32 | V28: =+V27*0.8 -> 1.6 | X28: =SUM(D28:W28) -> 181.43
F29: =F27*0.38 -> 0 | G29: =G27*0.48 -> -12.48 | I29: =I27*0.6 -> -3.6 | J29: =J27*0.87 -> -15.66 | P29: =P27*1.77 -> -17.7 | T29: =T27*0.42 -> -265.86 | U29: =U27*0.32 -> -67.84 | W29: =W27*2 -> -18 | X29: =SUM(D29:W29) -> -401.14

Sheet STOCK 31 a 06
D2: PANDERETA | H2: 18 HUECOS | O2: TECHO 12 | R2: TECHO 15 | U2: ARTESANAL | W2: TIPO 4 | X2: TECHO 08
B3: FECHA | C3: CLIENTE | D3: SIPAN | E3: CHALPON | F3: CERAM | G3: CALCA | H3: CERAM | I3: TORRE FUERTE | J3: LARK | K3: FORTALEZA | L3: CRUZ CHALPON | M3: TAISON | N3: SIPAN | O3: LARK | P3: ITAL | Q3: FORTALEZA | R3: ITAL | T3: FORTALEZA | U3: BODOQUE | V3: PEQUEÑO | W3: FORTALEZA | X3: CERAM
A4: INGRESO | D4: ='STOCK 24 a 30'!D25 -> 2889 | E4: ='STOCK 24 a 30'!E25 -> 4210 | F4: ='STOCK 24 a 30'!F25 -> 906 | G4: ='STOCK 24 a 30'!G25 -> 0 | H4: ='STOCK 24 a 30'!H25 -> 1552 | I4: ='STOCK 24 a 30'!I25 -> 103 | J4: ='STOCK 24 a 30'!J25 -> 2955 | K4: ='STOCK 24 a 30'!K25 -> 5020 | ... R4: ='STOCK 24 a 30'!R25 -> 1444 | T4: ='STOCK 24 a 30'!S25 -> 1068 | U4: ='STOCK 24 a 30'!T25 -> 3012 | V4: ='STOCK 24 a 30'!U25 -> 3042 | W4: ='STOCK 24 a 30'!V25 -> 280 | X4: ='STOCK 24 a 30'!W25 -> 43
B5: 45293 | C5: M6I-897 | S5: 500
B6: 45296 | C6: M6I-897 | D6: 4500
B7: 45297 | C7: M6I-897 | D7: 4500
B8: 45297 | C8: M5P-711 | P8: 700 | R8: 300
A11: SALIDADA | B11: 45293 | C11: VENTAS H&C | D11: 700 | U11: 150
B12: 45294 | C12: VENTAS H&C | K12: 220 | R12: 590 | U12: 50
B13: 45295 | C13: VENTAS H&C | D13: =2000+50 -> 2050
B14: 45296 | C14: VENTAS H&C | D14: 2000 | U14: 100 | V14: 100
B15: 45297 | C15: VENTAS H&C | J15: 200 | V15: 300
A21: SALDO | D21: =SUM(D4:D10)-SUM(D11:D20) -> 7139 | E21: =SUM(E4:E10)-SUM(E11:E20) -> 4210 | F21: =SUM(F4:F10)-SUM(F11:F20) -> 906 | G21: =SUM(G4:G10)-SUM(G11:G20) -> 0 | H21: =SUM(H4:H10)-SUM(H11:H20) -> 1552 | I21: =SUM(I4:I10)-SUM(I11:I20) -> 103 | J21: =SUM(J4:J10)-SUM(J11:J20) -> 2755 | K21: =SUM(K4:K10)-SUM(K11:K20) -> 4800 | ... X21: =SUM(X4:X10)-SUM(X11:X20) -> 43
D23: =D21*0.36 -> 2570.04 | E23: =+E21*0.4 -> 1684 | F23: =+F21*0.38 -> 344.28 | G23: =+G21*0.48 -> 0 | H23: =+H21*0.57 -> 884.64 | I23: =+I21*0.6 -> 61.8 | J23: =+J21*0.87 -> 2396.85 | K23: =+K21*0.68 -> 3264 | L23: =+L21*0.66 -> 0 | M23: =+M21*0.7 -> 0 | N23: =+N21*0.62 -> 0 | O23: =+O21*2.22 -> 666 | P23: =+P21*1.77 -> 2778.9 | Q23: =+Q21*2.26 -> 1360.52 | R23: =+R21*1.92 -> 2215.68 | S23: =+S21*2.47 -> 1235 | T23: =+T21*2.36 -> 2520.48 | U23: =+U21*0.42 -> 1139.04 | V23: =+V21*0.32 -> 845.44 | W23: =+W21*0.8 -> 224 | X23: =+X21*2 -> 86
X25: =SUM(D23:X23) -> 24276.67

Sheet STOCK 07 a 13
D2: PANDERETA | H2: 18 HUECOS | O2: TECHO 12 | R2: TECHO 15 | U2: ARTESANAL | W2: TIPO 4 | X2: TECHO 08
B3: FECHA | C3: CLIENTE | D3: SIPAN | E3: CHALPON | F3: CERAM | G3: CALCA | H3: CERAM | I3: TORRE FUERTE | J3: LARK | K3: FORTALEZA | L3: CRUZ CHALPON | M3: TAISON | N3: SIPAN | O3: LARK | P3: ITAL | Q3: FORTALEZA | R3: ITAL | T3: FORTALEZA | U3: BODOQUE | V3: PEQUEÑO | W3: FORTALEZA | X3: CERAM
A4: INGRESO | D4: ='STOCK 31 a 06'!D21 -> 7139 | E4: ='STOCK 31 a 06'!E21 -> 4210 | F4: ='STOCK 31 a 06'!F21 -> 906 | G4: ='STOCK 31 a 06'!G21 -> 0 | H4: ='STOCK 31 a 06'!H21 -> 1552 | I4: ='STOCK 31 a 06'!I21 -> 103 | J4: ='STOCK 31 a 06'!J21 -> 2755 | K4: ='STOCK 31 a 06'!K21 -> 4800 | ... X4: ='STOCK 31 a 06'!X21 -> 43
B5: 45300 | C5: M6I-897 | P5: 550
B6: 45301 | C6: M6I-897 | K6: 3500
B7: 45302 | C7: M6I-897 | D7: 4500
A11: SALIDADA | B11: 45298 | C11: VENTAS H&C | E11: 190 | H11: 40
B12: 45299 | C12: VENTAS H&C | D12: =2000+500 -> 2500 | P12: 8 | V12: =100+500+30 -> 630
B13: 45301 | C13: VENTAS H&C | H13: 80
B14: 45302 | C14: VENTAS H&C | D14: 1000
B15: 45303 | C15: VENTAS H&C | D15: 2000
B16: 45304 | C16: VENTAS H&C | P16: 300 | V16: =1000+400 -> 1400
A21: SALDO | D21: =SUM(D4:D10)-SUM(D11:D20) -> 6139 | E21: =SUM(E4:E10)-SUM(E11:E20) -> 4020 | F21: =SUM(F4:F10)-SUM(F11:F20) -> 906 | G21: =SUM(G4:G10)-SUM(G11:G20) -> 0 | H21: =SUM(H4:H10)-SUM(H11:H20) -> 1432 | I21: =SUM(I4:I10)-SUM(I11:I20) -> 103 | J21: =SUM(J4:J10)-SUM(J11:J20) -> 2755 | K21: =SUM(K4:K10)-SUM(K11:K20) -> 8300 | ... X21: =SUM(X4:X10)-SUM(X11:X20) -> 43
D23: =D21*0.36 -> 2210.04 | E23: =+E21*0.4 -> 1608 | F23: =+F21*0.38 -> 344.28 | G23: =+G21*0.48 -> 0 | H23: =+H21*0.57 -> 816.24 | I23: =+I21*0.6 -> 61.8 | J23: =+J21*0.87 -> 2396.85 | K23: =+K21*0.68+(3500*0.02) -> 5714 | L23: =+L21*0.66 -> 0 | M23: =+M21*0.7 -> 0 | N23: =+N21*0.62 -> 0 | O23: =+O21*2.22 -> 666 | P23: =+P21*1.77+(550*0.03) -> 3223.74 | Q23: =+Q21*2.26 -> 1360.52 | R23: =+R21*1.92 -> 2215.68 | S23: =+S21*2.47 -> 1235 | T23: =+T21*2.36 -> 2520.48 | U23: =+U21*0.42 -> 1139.04 | V23: =+V21*0.32 -> 195.84 | W23: =+W21*0.8 -> 224 | X23: =+X21*2 -> 86
X25: =SUM(D23:X23) -> 26017.51

Sheet STOCK 14 a 20
D2: PANDERETA | H2: 18 HUECOS | O2: TECHO 12 | R2: TECHO 15 | U2: ARTESANAL | W2: TIPO 4 | X2: TECHO 08
B3: FECHA | C3: CLIENTE | D3: SIPAN | E3: CHALPON | F3: CERAM | G3: CALCA | H3: CERAM | I3: TORRE FUERTE | J3: LARK | K3: FORTALEZA | L3: CRUZ CHALPON | M3: TAISON | N3: SIPAN | O3: LARK | P3: ITAL | Q3: FORTALEZA | R3: ITAL | T3: FORTALEZA | U3: BODOQUE | V3: PEQUEÑO | W3: FORTALEZA | X3: CERAM
A4: INGRESO | D4: ='STOCK 07 a 13'!D21 -> 6139 | E4: ='STOCK 07 a 13'!E21 -> 4020 | F4: ='STOCK 07 a 13'!F21 -> 906 | G4: ='STOCK 07 a 13'!G21 -> 0 | H4: ='STOCK 07 a 13'!H21 -> 1432 | I4: ='STOCK 07 a 13'!I21 -> 103 | J4: ='STOCK 07 a 13'!J21 -> 2755 | K4: ='STOCK 07 a 13'!K21 -> 8300 | ... X4: ='STOCK 07 a 13'!X21 -> 43
B5: 45307 | C5: M6I-897 | D5: 4500 | R5: 300
B6: 45308 | C6: M5P-711 | D6: 2500
B7: 45309 | C7: M5P-711 | V7: 3500
B8: 45310 | C8: M6I-897 | D8: 4500
B9: 45311 | C9: M6I-897 | H9: 3000 | P9: 1200
B10: 45311 | C10: M5P-711 | R10: 1000
A12: SALIDADA | B12: 45305 | C12: VENTAS H&C | V12: 32
B13: 45306 | C13: VENTAS H&C | K13: 1000 | P13: =500 -> 500
B14: 45306 | C14: ARCENIO | D14: 2000
B15: 45307 | C15: VENTAS H&C | D15: 250 | U15: 500
B16: 45308 | C16: VENTAS H&C | D16: =48+250 -> 298 | P16: 536 | R16: =260+650 -> 910
B17: 45309 | C17: VENTAS H&C | F17: 400 | H17: 380 | V17: 20
B18: 45310 | C18: VENTAS H&C | E18: 450 | H18: 500 | V18: 400
B19: 45311 | C19: VENTAS H&C | P19: 700 | V19: 600
A23: SALDO | D23: =SUM(D4:D11)-SUM(D12:D22) -> 15091 | E23: =SUM(E4:E11)-SUM(E12:E22) -> 3570 | F23: =SUM(F4:F11)-SUM(F12:F22) -> 506 | G23: =SUM(G4:G11)-SUM(G12:G22) -> 0 | H23: =SUM(H4:H11)-SUM(H12:H22) -> 3552 | I23: =SUM(I4:I11)-SUM(I12:I22) -> 103 | J23: =SUM(J4:J11)-SUM(J12:J22) -> 2755 | K23: =SUM(K4:K11)-SUM(K12:K22) -> 7300 | ... X23: =SUM(X4:X11)-SUM(X12:X22) -> 43
D25: =D23*0.36-11500*0.01 -> 5317.76 | E25: =+E23*0.4 -> 1428 | F25: =+F23*0.38 -> 192.28 | G25: =+G23*0.48 -> 0 | H25: =+H23*0.57+3000*0.02 -> 2084.64 | I25: =+I23*0.6 -> 61.8 | J25: =+J23*0.87 -> 2396.85 | K25: =+K23*0.68+(3500*0.02) -> 5034 | L25: =+L23*0.66 -> 0 | M25: =+M23*0.7 -> 0 | N25: =+N23*0.62 -> 0 | O25: =+O23*2.22 -> 666 | P25: =+P23*1.8 -> 2296.8 | Q25: =+Q23*2.26 -> 1360.52 | R25: =+R23*1.92+1300*0.03 -> 3003.48 | S25: =+S23*2.47 -> 1235 | T25: =+T23*2.36 -> 2520.48 | U25: =+U23*0.42 -> 929.04 | V25: =+V23*0.32 -> 979.2 | W25: =+W23*0.8 -> 224 | X25: =+X23*2 -> 86
X27: =SUM(D25:X25) -> 29815.85

Sheet STOCK 21 a 27
D2: PANDERETA | H2: 18 HUECOS | O2: TECHO 12 | R2: TECHO 15 | U2: ARTESANAL | W2: TIPO 4 | X2: TECHO 08
B3: FECHA | C3: CLIENTE | D3: SIPAN | E3: CHALPON | F3: CERAM | G3: CALCA | H3: CERAM | I3: TORRE FUERTE | J3: LARK | K3: FORTALEZA | L3: CRUZ CHALPON | M3: TAISON | N3: SIPAN | O3: LARK | P3: ITAL | Q3: FORTALEZA | R3: ITAL | S3: LARK | T3: FORTALEZA | U3: BODOQUE | V3: PEQUEÑO | W3: FORTALEZA | X3: CERAM
A4: INGRESO | D4: ='STOCK 14 a 20'!D23 -> 15091 | E4: ='STOCK 14 a 20'!E23 -> 3570 | F4: ='STOCK 14 a 20'!F23 -> 506 | G4: ='STOCK 14 a 20'!G23 -> 0 | H4: ='STOCK 14 a 20'!H23 -> 3552 | I4: ='STOCK 14 a 20'!I23 -> 103 | J4: ='STOCK 14 a 20'!J23 -> 2755 | K4: ='STOCK 14 a 20'!K23 -> 7300 | ... X4: ='STOCK 14 a 20'!X23 -> 43
B5: 45314 | C5: M6I-897 | D5: 4500
B6: 45315 | C6: M6I-897 | P6: 750
B7: 45316 | C7: M5P-711 | H7: 650
B8: 45317 | C8: M6I-897 | U8: 2150
B9: 45317 | C9: M5P-711 | D9: 500
A12: SALIDADA | B12: 45313 | C12: VENTAS H&C | D12: 70 | K12: 3000 | R12: 600
B13: 45313 | C13: VENTA JORDY | D13: 3000
B14: 45314 | C14: VENTAS H&C | U14: 200 | V14: 100
B15: 45315 | C15: VENTAS H&C | D15: =1000+1000 -> 2000 | V15: 250
B16: 45316 | C16: VENTA JORDY | D16: 1500 | K16: 500
B17: 45317 | C17: VENTA JORDY | D17: 2000 | U17: 1000
B18: 45317 | C18: VENTAS H&C | V18: 30
B19: 45318 | C19: VENTAS H&C | D19: 1000 | J19: 470 | V19: 6
A24: SALDO | D24: =SUM(D4:D11)-SUM(D12:D23) -> 10521 | E24: =SUM(E4:E11)-SUM(E12:E23) -> 3570 | F24: =SUM(F4:F11)-SUM(F12:F23) -> 506 | G24: =SUM(G4:G11)-SUM(G12:G23) -> 0 | H24: =SUM(H4:H11)-SUM(H12:H23) -> 4202 | I24: =SUM(I4:I11)-SUM(I12:I23) -> 103 | J24: =SUM(J4:J11)-SUM(J12:J23) -> 2285 | K24: =SUM(K4:K11)-SUM(K12:K23) -> 3800 | ... X24: =SUM(X4:X11)-SUM(X12:X23) -> 43
D26: =D24*0.35 -> 3682.35 | E26: =+E24*0.4 -> 1428 | F26: =+F24*0.38 -> 192.28 | G26: =+G24*0.48 -> 0 | H26: =+H24*0.59-552*0.02 -> 2468.14 | I26: =+I24*0.6 -> 61.8 | J26: =+J24*0.87 -> 1987.95 | K26: =+K24*0.68+(3500*0.02) -> 2654 | L26: =+L24*0.66 -> 0 | M26: =+M24*0.7 -> 0 | N26: =+N24*0.62 -> 0 | O26: =+O24*2.22 -> 666 | P26: =+P24*1.8 -> 3646.8 | Q26: =+Q24*2.26 -> 1360.52 | R26: =+R24*1.95 -> 1840.8 | S26: =+S24*2.47 -> 1235 | T26: =+T24*2.36 -> 2520.48 | U26: =+U24*0.42 -> 1328.04 | V26: =+V24*0.32 -> 855.68 | W26: =+W24*0.8 -> 224 | X26: =+X24*2 -> 86
H28: 2384.64 | X28: =SUM(D26:X26) -> 26237.84

Sheet STOCK 28 a 03
D2: PANDERETA | H2: 18 HUECOS | O2: TECHO 12 | R2: TECHO 15 | U2: ARTESANAL | W2: TIPO 4 | X2: TECHO 08
B3: FECHA | C3: CLIENTE | D3: SIPAN | E3: CHALPON | F3: CERAM | G3: CALCA | H3: CERAM | I3: TORRE FUERTE | J3: LARK | K3: FORTALEZA | L3: CRUZ CHALPON | M3: TAISON | N3: SIPAN | O3: LARK | P3: ITAL | Q3: FORTALEZA | R3: ITAL | S3: LARK | T3: FORTALEZA | U3: BODOQUE | V3: PEQUEÑO | W3: FORTALEZA | X3: CERAM
A4: INGRESO | D4: ='STOCK 21 a 27'!D24 -> 10521 | E4: ='STOCK 21 a 27'!E24 -> 3570 | F4: ='STOCK 21 a 27'!F24 -> 506 | G4: ='STOCK 21 a 27'!G24 -> 0 | H4: ='STOCK 21 a 27'!H24 -> 4202 | I4: ='STOCK 21 a 27'!I24 -> 103 | J4: ='STOCK 21 a 27'!J24 -> 2285 | K4: ='STOCK 21 a 27'!K24 -> 3800 | ... X4: ='STOCK 21 a 27'!X24 -> 43
B5: 45322 | C5: M6I-897 | D5: 4000
B6: 45322 | C6: M5P-711 | K6: 3500
B7: 45323 | C7: M6I-897 | R7: 1000
B8: 45325 | C8: M6I-897 | D8: 4500
B9: 45325 | C9: M5P-711 | U9: 1000 | V9: 500
A11: SALIDADA | B11: 45320 | C11: VENTAS H&C | H11: 100 | R11: 160 | V11: 30
B12: 45320 | C12: VENTA JORDY | K12: 3500
B13: 45321 | C13: VENTA JORDY | D13: 4000
B14: 45321 | C14: VENTAS H&C | D14: =1000+1000 -> 2000
B15: 45322 | C15: VENTA JORDY | R15: 260
B16: 45322 | C16: VENTAS H&C | D16: 150 | P16: 60 | U16: 50
B17: 45323 | C17: VENTA JORDY | D17: 1000
B18: 45323 | C18: VENTAS H&C | R18: 200 | V18: =500+40 -> 540
B19: 45324 | C19: VENTAS H&C | D19: 1000 | U19: 170 | V19: 300
B20: 45324 | C20: VENTA JORDY | E20: 1000
B21: 45325 | C21: VENTAS H&C | V21: 12
A24: SALDO | D24: =SUM(D4:D10)-SUM(D11:D23) -> 10871 | E24: =SUM(E4:E10)-SUM(E11:E23) -> 2570 | F24: =SUM(F4:F10)-SUM(F11:F23) -> 506 | G24: =SUM(G4:G10)-SUM(G11:G23) -> 0 | H24: =SUM(H4:H10)-SUM(H11:H23) -> 4102 | I24: =SUM(I4:I10)-SUM(I11:I23) -> 103 | J24: =SUM(J4:J10)-SUM(J11:J23) -> 2285 | K24: =SUM(K4:K10)-SUM(K11:K23) -> 3800 | ... X24: =SUM(X4:X10)-SUM(X11:X23) -> 43
D26: =D24*0.35 -> 3804.85 | E26: =+E24*0.4 -> 1028 | F26: =+F24*0.38 -> 192.28 | G26: =+G24*0.48 -> 0 | H26: =+H24*0.59-452*0.02 -> 2411.14 | I26: =+I24*0.6 -> 61.8 | J26: =+J24*0.87 -> 1987.95 | K26: =+K24*0.7 -> 2660 | L26: =+L24*0.66 -> 0 | M26: =+M24*0.7 -> 0 | N26: =+N24*0.62 -> 0 | O26: =+O24*2.22 -> 666 | P26: =+P24*1.8 -> 3538.8 | Q26: =+Q24*2.26 -> 1360.52 | R26: =+R24*1.95 -> 2581.8 | S26: =+S24*2.47 -> 1235 | T26: =+T24*2.36 -> 2520.48 | U26: =+U24*0.42 -> 1655.64 | V26: =+V24*0.32 -> 733.44 | W26: =+W24*0.8 -> 224 | X26: =+X24*2 -> 86
H28: 2384.64 | X28: =SUM(D26:X26) -> 26747.7

Sheet STOCK 04 a 10
D2: PANDERETA | H2: 18 HUECOS | O2: TECHO 12 | R2: TECHO 15 | U2: ARTESANAL | W2: SUPER KK | X2: TIPO 4 | Y2: TECHO 08
B3: FECHA | C3: CLIENTE | D3: SIPAN | E3: CHALPON | F3: CERAM | G3: FORTALEZA | H3: CERAM | I3: TORRE FUERTE | J3: LARK | K3: FORTALEZA | L3: CRUZ CHALPON | M3: TAISON | N3: SIPAN | O3: LARK | P3: ITAL | Q3: FORTALEZA | R3: ITAL | S3: LARK | T3: FORTALEZA | U3: BODOQUE | V3: PEQUEÑO | W3: CERAMICOS | X3: FORTALEZA | Y3: CERAM
A4: INGRESO | D4: ='STOCK 28 a 03'!D24 -> 10871 | E4: ='STOCK 28 a 03'!E24 -> 2570 | F4: ='STOCK 28 a 03'!F24 -> 506 | G4: ='STOCK 28 a 03'!G24 -> 0 | H4: ='STOCK 28 a 03'!H24 -> 4102 | I4: ='STOCK 28 a 03'!I24 -> 103 | J4: ='STOCK 28 a 03'!J24 -> 2285 | K4: ='STOCK 28 a 03'!K24 -> 3800 | ... V4: ='STOCK 28 a 03'!V24 -> 2292 | X4: ='STOCK 28 a 03'!W24 -> 280 | Y4: ='STOCK 28 a 03'!X24 -> 43
B5: 45327 | C5: M8B-893 | N5: 1000
B6: 45329 | C6: M8B-893 | D6: 60
B7: 45329 | C7: M6I-897 | K7: 2000
B8: 45329 | C8: M5P-711 | V8: 3000
B9: 45330 | C9: M8B-893 | G9: 5060
B10: 45330 | C10: M6I-897 | U10: 2000 | W10: 500
B11: 45331 | C11: M8B-893 | D11: 1060
B12: 45331 | C12: M6I-897
B13: 45331 | C13: M5P-711 | V13: 3000
A16: SALIDADA | B16: 45326 | C16: VENTAS H&C | U16: 50
B17: 45327 | C17: VENTAS H&C | U17: =500+500 -> 1000
B18: 45328 | C18: VENTAS H&C | D18: 1000 | E18: 400 | U18: 1000 | V18: =200 -> 200
B19: 45329 | C19: VENTAS H&C | H19: 100 | K19: 1000 | V19: 1500
B20: 45330 | C20: VENTAS H&C | E20: 500 | H20: 6 | U20: 1000 | V20: =300+25 -> 325
B21: 45330 | C21: VENTA JORDY | J21: 2000 | U21: 1000
B22: 45331 | C22: VENTAS H&C | H22: 200 | R22: =10+400 -> 410 | V22: =152+200 -> 352
B23: 45331 | C23: VENTA JORDY | R23: 362
B24: 45332 | C24: VENTAS H&C | D24: =500+1000 -> 1500 | P24: 400 | U24: 200
A27: SALDO | D27: =SUM(D4:D15)-SUM(D16:D26) -> 9491 | E27: =SUM(E4:E15)-SUM(E16:E26) -> 1670 | F27: =SUM(F4:F15)-SUM(F16:F26) -> 506 | G27: =SUM(G4:G15)-SUM(G16:G26) -> 5060 | H27: =SUM(H4:H15)-SUM(H16:H26) -> 3796 | I27: =SUM(I4:I15)-SUM(I16:I26) -> 103 | J27: =SUM(J4:J15)-SUM(J16:J26) -> 285 | K27: =SUM(K4:K15)-SUM(K16:K26) -> 4800 | ... Y27: =SUM(Y4:Y15)-SUM(Y16:Y26) -> 43
D29: =D27*0.35 -> 3321.85 | E29: =+E27*0.4 -> 668 | F29: =+F27*0.38 -> 192.28 | G29: =+G27*0.45 -> 2277 | H29: =+H27*0.59-146*0.02 -> 2236.72 | I29: =+I27*0.6 -> 61.8 | J29: =+J27*0.87 -> 247.95 | K29: =+K27*0.7 -> 3360 | L29: =+L27*0.66 -> 0 | M29: =+M27*0.7 -> 0 | N29: =+N27*0.55 -> 550 | O29: =+O27*2.22 -> 666 | P29: =+P27*1.8 -> 2818.8 | Q29: =+Q27*2.26 -> 1360.52 | R29: =+R27*1.95 -> 1076.4 | S29: =+S27*2.47 -> 1235 | T29: =+T27*2.36 -> 2520.48 | U29: =+U27*0.42 -> 710.64 | V29: =+V27*0.32 -> 1892.8 | W29: =+W27*2.3 -> 1150 | X29: =+X27*0.8 -> 224 | Y29: =+Y27*2 -> 86
C31: STOCK REAL | D31: 8229 | E31: 1668 | F31: 500 | G31: 5060 | H31: 3883 | J31: 282 | K31: 4790 | N31: 1010 | O31: 300 | P31: 1570 | Q31: 600 | R31: 555 | S31: 500 | T31: 1068 | U31: 2896 | V31: 5998 | W31: 502 | X31: 320 | Y31: =SUM(D29:Y29) -> 26656.24
C33: DIFERENCIA | D33: =+D31-D27 -> -1262 | E33: =+E31-E27 -> -2 | F33: =+F31-F27 -> -6 | G33: =+G31-G27 -> 0 | H33: =+H31-H27 -> 87 | I33: =+I31-I27 -> -103 | J33: =+J31-J27 -> -3 | K33: =+K31-K27 -> -10 | ... X33: =+X31-X27 -> 40
C35: DIF/SOLES | D35: =D33*0.35 -> -441.7 | E35: =E33*0.4 -> -0.8 | F35: =F33*0.38 -> -2.28 | G35: =G33*0.45 -> 0 | H35: =H33*0.59 -> 51.33 | I35: =I33*0.6 -> -61.8 | J35: =J33*0.87 -> -2.61 | K35: =K33*0.7 -> -7 | L35: =L33*0.4 -> 0 | M35: =M33*0.4 -> 0 | N35: =N33*0.55 -> 5.5 | O35: =O33*0.4 -> 0 | P35: =P33*1.8 -> 7.2 | Q35: =Q33*2.26 -> -4.52 | R35: =R33*1.95 -> 5.85 | S35: =S33*0.4 -> 0 | T35: =T33*0.4 -> 0 | U35: =U33*0.42 -> 505.68 | V35: =V33*0.32 -> 26.56 | W35: =W33*2.3 -> 4.6 | X35: =X33*0.8 -> 32

Sheet STOCK 11 a 17
D2: PANDERETA | H2: 18 HUECOS | O2: TECHO 12 | R2: TECHO 15 | U2: ARTESANAL | W2: SUPER KK | X2: TIPO 4 | Y2: TECHO 08
B3: FECHA | C3: CLIENTE | D3: SIPAN | E3: CHALPON | F3: CERAM | G3: FORTALEZA | H3: CERAM | I3: TORRE FUERTE | J3: LARK | K3: FORTALEZA | L3: CRUZ CHALPON | M3: TAISON | N3: SIPAN | O3: LARK | P3: ITAL | Q3: FORTALEZA | R3: ITAL | S3: LARK | T3: FORTALEZA | U3: BODOQUE | V3: PEQUEÑO | W3: CERAMICOS | X3: FORTALEZA | Y3: CERAM
A4: INGRESO | D4: ='STOCK 04 a 10'!D27 -> 9491 | E4: ='STOCK 04 a 10'!E27 -> 1670 | F4: ='STOCK 04 a 10'!F27 -> 506 | G4: ='STOCK 04 a 10'!G27 -> 5060 | H4: ='STOCK 04 a 10'!H27 -> 3796 | I4: ='STOCK 04 a 10'!I27 -> 103 | J4: ='STOCK 04 a 10'!J27 -> 285 | K4: ='STOCK 04 a 10'!K27 -> 4800 | ... Y4: ='STOCK 04 a 10'!Y27 -> 43
B5: 45334 | C5: M8B-893 | J5: 1500
B6: 45335 | C6: M5P-711 | D6: 4000
B7: 45336 | C7: M6I-897 | R7: 1000
B8: 45337 | C8: M6I-897 | D8: 4500
B9: 45338 | C9: M6I-897 | D9: 4500
B10: 45338 | C10: M5P-711 | U10: 2000
A12: SALIDADA | B12: 45334 | C12: VENTAS H&C | Q12: 530 | R12: 200 | U12: =300+500 -> 800
B13: 45329 | C13: VENTA JORDY | D13: 3000
B14: 45334 | C14: VENTA JORDY | O14: 180
B15: 45335 | C15: VENTA JORDY | K15: 1000
B16: 45335 | C16: VENTAS H&C | H16: 500 | U16: 1000
B17: 45336 | C17: VENTA JORDY | D17: 1000
B18: 45336 | C18: VENTAS H&C | K18: =100+200 -> 300 | U18: 30
B19: 45337 | C19: VENTAS H&C | D19: 500 | K19: 2500
B20: 45338 | C20: VENTAS H&C | K20: =70+8 -> 78
B21: 45339 | C21: VENTAS H&C | U21: 500 | V21: =150+150 -> 300
A27: SALDO | D27: =SUM(D4:D11)-SUM(D12:D26) -> 17991 | E27: =SUM(E4:E11)-SUM(E12:E26) -> 1670 | F27: =SUM(F4:F11)-SUM(F12:F26) -> 506 | G27: =SUM(G4:G11)-SUM(G12:G26) -> 5060 | H27: =SUM(H4:H11)-SUM(H12:H26) -> 3296 | I27: =SUM(I4:I11)-SUM(I12:I26) -> 103 | J27: =SUM(J4:J11)-SUM(J12:J26) -> 1785 | K27: =SUM(K4:K11)-SUM(K12:K26) -> 922 | ... Y27: =SUM(Y4:Y11)-SUM(Y12:Y26) -> 43
D29: =D27*0.35 -> 6296.85 | E29: =+E27*0.4 -> 668 | F29: =+F27*0.38 -> 192.28 | G29: =+G27*0.45 -> 2277 | H29: =+H27*0.59 -> 1944.64 | I29: =+I27*0.6 -> 61.8 | J29: =+J27*0.87 -> 1552.95 | K29: =+K27*0.7 -> 645.4 | L29: =+L27*0.66 -> 0 | M29: =+M27*0.7 -> 0 | N29: =+N27*0.55 -> 550 | O29: =+O27*2.22 -> 266.4 | P29: =+P27*1.8 -> 2818.8 | Q29: =+Q27*2.26 -> 162.72 | R29: =+R27*1.85+(352*0.1) -> 2536.4 | S29: =+S27*2.47 -> 1235 | T29: =+T27*2.36 -> 2520.48 | U29: =+U27*0.42 -> 572.04 | V29: =+V27*0.32 -> 1796.8 | W29: =+W27*2.3 -> 1150 | X29: =+X27*0.8 -> 224 | Y29: =+Y27*2 -> 86
Y31: =SUM(D29:Y29) -> 27557.56
D34: 231

Sheet STOCK 18 a 24
D2: PANDERETA | H2: 18 HUECOS | O2: TECHO 12 | R2: TECHO 15 | U2: ARTESANAL | W2: SUPER KK | X2: TIPO 4 | Y2: TECHO 08
B3: FECHA | C3: CLIENTE | D3: SIPAN | E3: CHALPON | F3: CERAM | G3: FORTALEZA | H3: CERAM | I3: TORRE FUERTE | J3: LARK | K3: FORTALEZA | L3: CRUZ CHALPON | M3: TAISON | N3: SIPAN | O3: LARK | P3: ITAL | Q3: FORTALEZA | R3: ITAL | S3: LARK | T3: FORTALEZA | U3: BODOQUE | V3: PEQUEÑO | W3: CERAMICOS | X3: FORTALEZA | Y3: CERAM
A4: INGRESO | D4: ='STOCK 11 a 17'!D27 -> 17991 | E4: ='STOCK 11 a 17'!E27 -> 1670 | F4: ='STOCK 11 a 17'!F27 -> 506 | G4: ='STOCK 11 a 17'!G27 -> 5060 | H4: ='STOCK 11 a 17'!H27 -> 3296 | I4: ='STOCK 11 a 17'!I27 -> 103 | J4: ='STOCK 11 a 17'!J27 -> 1785 | K4: ='STOCK 11 a 17'!K27 -> 922 | ... Y4: ='STOCK 11 a 17'!Y27 -> 43
B5: 45341 | C5: M8B-897 | R5: 727
B6: 45343 | C6: M6I-897 | K6: 3500
B7: 45344 | C7: M8B-897 | K7: 2000
B8: 45346 | C8: M8B-897 | P8: 500
A11: SALIDADA | B11: 45340 | C11: VENTAS H&C | V11: 150
B12: 45341 | C12: VENTAS H&C | D12: 500
B13: 45342 | C13: VENTAS H&C | R13: 150 | U13: =250+100 -> 350 | W13: 100
B14: 45343 | C14: VENTAS H&C | N14: 100
B15: 45344 | C15: VENTAS H&C | D15: 500 | G15: 1000 | V15: 300
B16: 45345 | C16: VENTAS H&C | H16: 200 | U16: 1012
B17: 45345 | C17: VENTASJORDY | J17: 1700
B18: 45346 | C18: VENTAS H&C | R18: 200
A24: SALDO | D24: =SUM(D4:D10)-SUM(D11:D23) -> 16991 | E24: =SUM(E4:E10)-SUM(E11:E23) -> 1670 | F24: =SUM(F4:F10)-SUM(F11:F23) -> 506 | G24: =SUM(G4:G10)-SUM(G11:G23) -> 4060 | H24: =SUM(H4:H10)-SUM(H11:H23) -> 3096 | I24: =SUM(I4:I10)-SUM(I11:I23) -> 103 | J24: =SUM(J4:J10)-SUM(J11:J23) -> 85 | K24: =SUM(K4:K10)-SUM(K11:K23) -> 6422 | ... Y24: =SUM(Y4:Y10)-SUM(Y11:Y23) -> 43
D26: =D24*0.35 -> 5946.85 | E26: =+E24*0.4 -> 668 | F26: =+F24*0.38 -> 192.28 | G26: =+G24*0.45 -> 1827 | H26: =+H24*0.59 -> 1826.64 | I26: =+I24*0.6 -> 61.8 | J26: =+J24*0.87 -> 73.95 | K26: =+K24*0.7 -> 4495.4 | L26: =+L24*0.66 -> 0 | M26: =+M24*0.7 -> 0 | N26: =+N24*0.55 -> 495 | O26: =+O24*2.22 -> 266.4 | P26: =+P24*1.75+(1566*0.05) -> 3693.8 | Q26: =+Q24*2.26 -> 162.72 | R26: =+R24*1.85+(2*0.1) -> 3198.85 | S26: =+S24*2.47 -> 1235 | T26: =+T24*2.36 -> 2520.48 | U26: =+U24*0.42 -> 0 | V26: =+V24*0.32 -> 1652.8 | W26: =+W24*2.3 -> 920 | X26: =+X24*0.8 -> 224 | Y26: =+Y24*2 -> 86
Y28: =SUM(D26:Y26) -> 29546.97
D31: 231

Sheet STOCK 25 a 02
D2: PANDERETA | H2: 18 HUECOS | O2: TECHO 12 | R2: TECHO 15 | U2: ARTESANAL | W2: SUPER KK | X2: TIPO 4 | Y2: TECHO 08
B3: FECHA | C3: CLIENTE | D3: SIPAN | E3: CHALPON | F3: CERAM | G3: FORTALEZA | H3: CERAM | I3: TORRE FUERTE | J3: LARK | K3: FORTALEZA | L3: CRUZ CHALPON | M3: TAISON | N3: SIPAN | O3: LARK | P3: ITAL | Q3: FORTALEZA | R3: ITAL | S3: LARK | T3: FORTALEZA | U3: BODOQUE | V3: PEQUEÑO | W3: CERAMICOS | X3: FORTALEZA | Y3: CERAM
A4: INGRESO | D4: ='STOCK 18 a 24'!D24 -> 16991 | E4: ='STOCK 18 a 24'!E24 -> 1670 | F4: ='STOCK 18 a 24'!F24 -> 506 | G4: ='STOCK 18 a 24'!G24 -> 4060 | H4: ='STOCK 18 a 24'!H24 -> 3096 | I4: ='STOCK 18 a 24'!I24 -> 103 | J4: ='STOCK 18 a 24'!J24 -> 85 | K4: ='STOCK 18 a 24'!K24 -> 6422 | ... Y4: ='STOCK 18 a 24'!Y24 -> 43
B5: 45349 | C5: M8B-893 | J5: 1000
B6: 45349 | C6: M6I-897 | U6: 3000
B7: 45350 | C7: M6I-897 | P7: 700
B8: 45351 | C8: M8B-893 | W8: 1000
B9: 45351 | C9: M6I-897 | M9: 1000
A11: SALIDADA | B11: 45347 | C11: VENTAS H&C | V11: 100
B12: 45348 | C12: VENTAS H&C | P12: 500 | R12: 500 | T12: 197
B13: 45349 | C13: VENTAS H&C | D13: 1000 | H13: 2000 | J13: 60 | V13: 200
B14: 45350 | C14: VENTAS H&C | H14: 250 | J14: 300 | U14: 1000
B15: 45351 | C15: VENTAS H&C | D15: 200 | P15: 130 | U15: 40
B16: 45352 | C16: VENTAS H&C | D16: =80+100+200 -> 380 | H16: 80 | K16: 1000 | V16: 1300
B17: 45353 | C17: VENTA JORDY | K17: 500 | U17: 1000
B18: 45353 | C18: VENTAS H&C | D18: 200 | U18: =100+150+100+500 -> 850
A24: SALDO | D24: =SUM(D4:D10)-SUM(D11:D23) -> 15211 | E24: =SUM(E4:E10)-SUM(E11:E23) -> 1670 | F24: =SUM(F4:F10)-SUM(F11:F23) -> 506 | G24: =SUM(G4:G10)-SUM(G11:G23) -> 4060 | H24: =SUM(H4:H10)-SUM(H11:H23) -> 766 | I24: =SUM(I4:I10)-SUM(I11:I23) -> 103 | J24: =SUM(J4:J10)-SUM(J11:J23) -> 725 | K24: =SUM(K4:K10)-SUM(K11:K23) -> 4922 | ... Y24: =SUM(Y4:Y10)-SUM(Y11:Y23) -> 43
D26: =D24*0.35 -> 5323.85 | E26: =+E24*0.4 -> 668 | F26: =+F24*0.38 -> 192.28 | G26: =+G24*0.45 -> 1827 | H26: =+H24*0.59 -> 451.94 | I26: =+I24*0.6 -> 61.8 | J26: =+J24*0.87 -> 630.75 | K26: =+K24*0.7 -> 3445.4 | L26: =+L24*0.66 -> 0 | M26: =+M24*0.64 -> 640 | N26: =+N24*0.55 -> 495 | O26: =+O24*2.22 -> 266.4 | P26: =+P24*1.75+(936*0.05) -> 3784.8 | Q26: =+Q24*2.26 -> 162.72 | R26: =+R24*1.85 -> 2273.65 | S26: =+S24*2.47 -> 1235 | T26: =+T24*2.36 -> 2055.56 | U26: =+U24*0.42 -> 46.2 | V26: =+V24*0.32 -> 1140.8 | W26: =+W24*2+(400*0.3) -> 2920 | X26: =+X24*0.8 -> 224 | Y26: =+Y24*2 -> 86
Y28: =SUM(D26:Y26) -> 27931.15
D31: 231

Sheet STOCK 03 a 009
D2: PANDERETA | H2: 18 HUECOS | O2: TECHO 12 | R2: TECHO 15 | U2: ARTESANAL | W2: SUPER KK | X2: TIPO 4 | Y2: TECHO 08
B3: FECHA | C3: CLIENTE | D3: SIPAN | E3: CHALPON | F3: CERAM | G3: FORTALEZA | H3: CERAM | I3: TORRE FUERTE | J3: LARK | K3: FORTALEZA | L3: CRUZ CHALPON | M3: TAISON | N3: SIPAN | O3: LARK | P3: ITAL | Q3: FORTALEZA | R3: ITAL | S3: LARK | T3: FORTALEZA | U3: BODOQUE | V3: PEQUEÑO | W3: CERAMICOS | X3: FORTALEZA | Y3: CERAM
A4: INGRESO | D4: ='STOCK 25 a 02'!D24 -> 15211 | E4: ='STOCK 25 a 02'!E24 -> 1670 | F4: ='STOCK 25 a 02'!F24 -> 506 | G4: ='STOCK 25 a 02'!G24 -> 4060 | H4: ='STOCK 25 a 02'!H24 -> 766 | I4: ='STOCK 25 a 02'!I24 -> 103 | J4: ='STOCK 25 a 02'!J24 -> 725 | K4: ='STOCK 25 a 02'!K24 -> 4922 | ... Y4: ='STOCK 25 a 02'!Y24 -> 43
B5: 45355 | C5: M8B-893 | U5: 2200 | V5: 1000
B6: 45356 | C6: M8B-893 | R6: 200
B7: 45357 | C7: M8B-893 | G7: 2000 | K7: 2000
B8: 45357 | C8: M6I-897 | H8: 2000
B9: 45358 | C9: M8B-893 | D9: 3000
B10: 45358 | C10: M6I-897 | U10: 500
A13: SALIDADA | B13: 45355 | C13: VENTAS H&C | G13: 1000 | P13: 150 | U13: 110 | V13: 250 | W13: 800
B14: 403 | C14: VENTA JORDY | G14: 2000
B15: 45356 | C15: VENTAS H&C | D15: 470 | H15: 200
B16: 45356 | C16: VENTA JORDY | K16: 2000 | P16: 500
B17: 45357 | C17: VENTAS H&C | R17: 200
B18: 45359 | C18: VENTAS H&C | H18: 600
A23: SALDO | D23: =SUM(D4:D12)-SUM(D13:D22) -> 17741 | E23: =SUM(E4:E12)-SUM(E13:E22) -> 1670 | F23: =SUM(F4:F12)-SUM(F13:F22) -> 506 | G23: =SUM(G4:G12)-SUM(G13:G22) -> 3060 | H23: =SUM(H4:H12)-SUM(H13:H22) -> 1966 | I23: =SUM(I4:I12)-SUM(I13:I22) -> 103 | J23: =SUM(J4:J12)-SUM(J13:J22) -> 725 | K23: =SUM(K4:K12)-SUM(K13:K22) -> 4922 | ... Y23: =SUM(Y4:Y12)-SUM(Y13:Y22) -> 43
D25: =D23*0.34+(14741*0.01) -> 6179.35 | E25: =+E23*0.4 -> 668 | F25: =+F23*0.38 -> 192.28 | G25: =+G23*0.45 -> 1377 | H25: =+H23*0.59 -> 1159.94 | I25: =+I23*0.6 -> 61.8 | J25: =+J23*0.87 -> 630.75 | K25: =+K23*0.7 -> 3445.4 | L25: =+L23*0.66 -> 0 | M25: =+M23*0.64 -> 640 | N25: =+N23*0.55 -> 495 | O25: =+O23*2.22 -> 266.4 | P25: =+P23*1.75+(286*0.05) -> 2614.8 | Q25: =+Q23*2.26 -> 162.72 | R25: =+R23*1.85 -> 2273.65 | S25: =+S23*2.47 -> 1235 | T25: =+T23*2.36 -> 2055.56 | U25: =+U23*0.42 -> 1134 | V25: =+V23*0.32 -> 1380.8 | W25: =+W23*2+(400*0.3) -> 1320 | X25: =+X23*0.8 -> 224 | Y25: =+Y23*2 -> 86
Y27: =SUM(D25:Y25) -> 27602.45
V28: 24832.45
V29: 6324
D30: 231

Sheet STOCK 10 a 016
D2: PANDERETA | H2: 18 HUECOS | O2: TECHO 12 | R2: TECHO 15 | U2: ARTESANAL | W2: SUPER KK | X2: TIPO 4 | Y2: TECHO 08
B3: FECHA | C3: CLIENTE | D3: SIPAN | E3: CHALPON | F3: CERAM | G3: FORTALEZA | H3: CERAM | I3: TORRE FUERTE | J3: LARK | K3: FORTALEZA | L3: CRUZ CHALPON | M3: TAISON | N3: SIPAN | O3: LARK | P3: ITAL | Q3: FORTALEZA | R3: ITAL | S3: LARK | T3: FORTALEZA | U3: BODOQUE | V3: PEQUEÑO | W3: CERAMICOS | X3: FORTALEZA | Y3: CERAM
A4: INGRESO | D4: ='STOCK 03 a 009'!D23 -> 17741 | E4: ='STOCK 03 a 009'!E23 -> 1670 | F4: ='STOCK 03 a 009'!F23 -> 506 | G4: ='STOCK 03 a 009'!G23 -> 3060 | H4: ='STOCK 03 a 009'!H23 -> 1966 | I4: ='STOCK 03 a 009'!I23 -> 103 | J4: ='STOCK 03 a 009'!J23 -> 725 | K4: ='STOCK 03 a 009'!K23 -> 4922 | ... Y4: ='STOCK 03 a 009'!Y23 -> 43
B5: 45364 | C5: JH FERROC | H5: 2500
B6: 45364 | C6: M8B-893 | D6: 2500
B7: 45365 | C7: M8B-893 | W7: 1200
B8: 45365 | C8: M6I-897 | U8: 2500
B9: 45366 | C9: M6I-897 | P9: 1200
B10: 45366 | C10: M8B-893 | E10: 1000
A14: SALIDADA | B14: 44996 | C14: VENTAS H&C | D14: 200 | G14: 1000 | U14: =2000 -> 2000
B15: 44997 | C15: VENTAS H&C | U15: =490+110 -> 600 | V15: 10
B16: 44998 | C16: VENTAS H&C | D16: 200 | G16: 1000 | M16: =100+250 -> 350 | N16: 900 | R16: =130+160 -> 290
B17: 44999 | C17: VENTA JORDY | P17: 1000
B18: 45000 | C18: VENTAS H&C | D18: 2000 | J18: 500
B19: 45001 | C19: VENTAS H&C | H19: 14 | U19: =500+350 -> 850
A24: SALDO | D24: =SUM(D4:D13)-SUM(D14:D23) -> 17841 | E24: =SUM(E4:E13)-SUM(E14:E23) -> 2670 | F24: =SUM(F4:F13)-SUM(F14:F23) -> 506 | G24: =SUM(G4:G13)-SUM(G14:G23) -> 1060 | H24: =SUM(H4:H13)-SUM(H14:H23) -> 4452 | I24: =SUM(I4:I13)-SUM(I14:I23) -> 103 | J24: =SUM(J4:J13)-SUM(J14:J23) -> 225 | K24: =SUM(K4:K13)-SUM(K14:K23) -> 4922 | ... Y24: =SUM(Y4:Y13)-SUM(Y14:Y23) -> 43
D26: =D24*0.34+(12341*0.01) -> 6189.35 | E26: =+E24*0.4 -> 1068 | F26: =+F24*0.38 -> 192.28 | G26: =+G24*0.45 -> 477 | H26: =+H24*0.54+(1952*0.05) -> 2501.68 | I26: =+I24*0.6 -> 61.8 | J26: =+J24*0.87 -> 195.75 | K26: =+K24*0.7 -> 3445.4 | L26: =+L24*0.66 -> 0 | M26: =+M24*0.64 -> 416 | N26: =+N24*0.55 -> 0 | O26: =+O24*2.22 -> 266.4 | P26: =+P24*1.7+(486*0.05) -> 2890.5 | Q26: =+Q24*2.26 -> 162.72 | R26: =+R24*1.85 -> 1737.15 | S26: =+S24*2.47 -> 1235 | T26: =+T24*2.36 -> 2055.56 | U26: =+U24*0.42 -> 735 | V26: =+V24*0.32 -> 1377.6 | W26: =+W24*2+(400*0.3) -> 3720 | X26: =+X24*0.8 -> 224 | Y26: =+Y24*2 -> 86
Y28: =SUM(D26:Y26) -> 29037.19
D30: 16908 | E30: 2667 | F30: 497 | G30: 1046 | H30: 4520 | J30: 265 | K30: 4906 | M30: 636 | O30: 120 | P30: 1675 | Q30: 71 | R30: 800 | S30: 500 | T30: 870 | U30: =1580+155 -> 1735 | V30: 4290 | W30: 1800 | X30: 280 | Y30: 43
C32: STOCK REAL | D32: =D30-D24 -> -933 | E32: =E30-E24 -> -3 | F32: =F30-F24 -> -9 | G32: =G30-G24 -> -14 | H32: =H30-H24 -> 68 | I32: =I30-I24 -> -103 | J32: =J30-J24 -> 40 | K32: =K30-K24 -> -16 | ... Y32: =Y30-Y24 -> 0
C33: COSTO | D33: 0.35 | E33: 0.4 | F33: 0.38 | G33: 0.45 | H33: 0.54 | I33: 0.6 | J33: 0.87 | K33: 0.7 | M33: 0.64 | P33: 1.75 | Q33: 2.26 | R33: 1.85 | T33: 2.36 | U33: 0.42 | V33: 0.32
D35: =D32*D33 -> -326.55 | E35: =E32*E33 -> -1.2 | F35: =F32*F33 -> -3.42 | G35: =G32*G33 -> -6.3 | H35: =H32*H33 -> 36.72 | I35: =I32*I33 -> -61.8 | J35: =J32*J33 -> 34.8 | K35: =K32*K33 -> -11.2 | ... Y35: =Y32*Y33 -> 0
Y36: =SUM(D35:Y35) -> -640.03
Y37: =Y28+Y36 -> 28397.16

Sheet STOCK 17 a 023
D2: PANDERETA | H2: 18 HUECOS | O2: TECHO 12 | R2: TECHO 15 | U2: ARTESANAL | W2: SUPER KK | X2: TIPO 4 | Y2: TECHO 08
B3: FECHA | C3: CLIENTE | D3: SIPAN | E3: CHALPON | F3: CERAM | G3: FORTALEZA | H3: CERAM | I3: TORRE FUERTE | J3: LARK | K3: FORTALEZA | L3: CRUZ CHALPON | M3: TAISON | N3: SIPAN | O3: LARK | P3: ITAL | Q3: FORTALEZA | R3: ITAL | S3: LARK | T3: FORTALEZA | U3: BODOQUE | V3: PEQUEÑO | W3: CERAMICOS | X3: FORTALEZA | Y3: CERAM
A4: INGRESO | D4: 16908 | E4: 2667 | F4: 497 | G4: 1046 | H4: 4520 | I4: 0 | J4: 265 | K4: 4906 | L4: 0 | M4: 636 | N4: 0 | O4: 120 | P4: 1675 | Q4: 71 | R4: 800 | S4: 500 | T4: 870 | U4: 1735 | V4: 4290 | W4: 1800 | X4: 280 | Y4: 43
B5: 45369 | C5: M8B-893 | J5: 3000
B6: 45369 | C6: M6I-897 | R6: 500
B7: 45370 | C7: M8B-893 | U7: 3000
B8: 45372 | C8: M8B-893 | G8: 2000 | U8: 300
B9: 45373 | C9: M8B-893 | N9: 2000
A12: SALIDADA | B12: 45368 | C12: VENTAS H&C | P12: =6+115 -> 121 | V12: 25
B13: 45369 | C13: VENTAS H&C | G13: 1000 | P13: 130 | V13: 240
B14: 45369 | C14: VENTA JORDY | V14: 1000
B15: 45370 | C15: VENTAS H&C | D15: 1000 | U15: 1000
B16: 45371 | C16: VENTA JORDY | W16: 500
B17: 45371 | C17: VENTAS H&C | D17: 500
B18: 45372 | C18: VENTAS H&C | D18: 760 | P18: 96
B19: 45373 | C19: VENTAS H&C | G19: 500 | R19: 750
A22: SALDO | D22: =SUM(D4:D11)-SUM(D12:D21) -> 14648 | E22: =SUM(E4:E11)-SUM(E12:E21) -> 2667 | F22: =SUM(F4:F11)-SUM(F12:F21) -> 497 | G22: =SUM(G4:G11)-SUM(G12:G21) -> 1546 | H22: =SUM(H4:H11)-SUM(H12:H21) -> 4520 | I22: =SUM(I4:I11)-SUM(I12:I21) -> 0 | J22: =SUM(J4:J11)-SUM(J12:J21) -> 3265 | K22: =SUM(K4:K11)-SUM(K12:K21) -> 4906 | ... Y22: =SUM(Y4:Y11)-SUM(Y12:Y21) -> 43
D24: =D22*0.34+(9148*0.01) -> 5071.8 | E24: =+E22*0.4 -> 1066.8 | F24: =+F22*0.38 -> 188.86 | G24: =+G22*0.43 -> 664.78 | H24: =+H22*0.54+(1952*0.05) -> 2538.4 | I24: =+I22*0.6 -> 0 | J24: =+J22*0.85+(265*0.02) -> 2780.55 | K24: =+K22*0.7 -> 3434.2 | L24: =+L22*0.66 -> 0 | M24: =+M22*0.64 -> 407.04 | N24: =+N22*0.53 -> 1060 | O24: =+O22*2.22 -> 266.4 | P24: =+P22*1.7+(128*0.05) -> 2264 | Q24: =+Q22*2.26 -> 160.46 | R24: =+R22*1.8+(50*0.05) -> 992.5 | S24: =+S22*2.47 -> 1235 | T24: =+T22*2.36 -> 2053.2 | U24: =+U22*0.42 -> 1694.7 | V24: =+V22*0.32 -> 968 | W24: =+W22*2 -> 2600 | X24: =+X22*0.8 -> 224 | Y24: =+Y22*2 -> 86
Y26: =SUM(D24:Y24) -> 29756.69
T31: 4 | W31: =75*3 -> 225
C32: =20.5/1.18 -> 17.372881 | T32: 3
T33: 31
Q34: =170+116+3000 -> 3286 | T34: 10

Sheet STOCK 24 a 030
D2: PANDERETA | H2: 18 HUECOS | O2: TECHO 12 | R2: TECHO 15 | U2: ARTESANAL | W2: SUPER KK | X2: TIPO 4 | Y2: TECHO 08
B3: FECHA | C3: CLIENTE | D3: SIPAN | E3: CHALPON | F3: CERAM | G3: FORTALEZA | H3: CERAM | I3: TORRE FUERTE | J3: LARK | K3: FORTALEZA | L3: CRUZ CHALPON | M3: TAISON | N3: SIPAN | O3: LARK | P3: ITAL | Q3: FORTALEZA | R3: ITAL | S3: LARK | T3: FORTALEZA | U3: BODOQUE | V3: PEQUEÑO | W3: CERAMICOS | X3: FORTALEZA | Y3: CERAM
A4: INGRESO | D4: ='STOCK 17 a 023'!D22 -> 14648 | E4: ='STOCK 17 a 023'!E22 -> 2667 | F4: ='STOCK 17 a 023'!F22 -> 497 | G4: ='STOCK 17 a 023'!G22 -> 1546 | H4: ='STOCK 17 a 023'!H22 -> 4520 | I4: ='STOCK 17 a 023'!I22 -> 0 | J4: ='STOCK 17 a 023'!J22 -> 3265 | K4: ='STOCK 17 a 023'!K22 -> 4906 | ... Y4: ='STOCK 17 a 023'!Y22 -> 43
B5: 45377 | C5: M6I-897 | R5: 1000
A9: SALIDADA | B9: 45375 | C9: VENTAS H&C | N9: 600 | V9: 20
B10: 45376 | C10: VENTAS H&C | P10: 50 | R10: 300
B11: 45376 | C11: VENTA JORDY | J11: 1600
B12: 45377 | C12: VENTAS H&C | P12: 100 | R12: 90 | U12: 100 | V12: 70
B13: 45378 | C13: VENTAS H&C | D13: 1500 | K13: 1000 | N13: 1000 | U13: 600 | V13: 30
B14: 45379 | C14: VENTAS H&C | D14: =5000+500 -> 5500 | H14: 500
B15: 45381 | C15: VENTAS H&C | F15: =50+24 -> 74 | R15: 40 | V15: =1000+600+10+40 -> 1650
A20: SALDO | D20: =SUM(D4:D8)-SUM(D9:D19) -> 7648 | E20: =SUM(E4:E8)-SUM(E9:E19) -> 2667 | F20: =SUM(F4:F8)-SUM(F9:F19) -> 423 | G20: =SUM(G4:G8)-SUM(G9:G19) -> 1546 | H20: =SUM(H4:H8)-SUM(H9:H19) -> 4020 | I20: =SUM(I4:I8)-SUM(I9:I19) -> 0 | J20: =SUM(J4:J8)-SUM(J9:J19) -> 1665 | K20: =SUM(K4:K8)-SUM(K9:K19) -> 3906 | ... Y20: =SUM(Y4:Y8)-SUM(Y9:Y19) -> 43
D22: =D20*0.33 -> 2523.84 | E22: =+E20*0.4 -> 1066.8 | F22: =+F20*0.38 -> 160.74 | G22: =+G20*0.43 -> 664.78 | H22: =+H20*0.54 -> 2170.8 | I22: =+I20*0.6 -> 0 | J22: =+J20*0.85 -> 1415.25 | K22: =+K20*0.7 -> 2734.2 | L22: =+L20*0.66 -> 0 | M22: =+M20*0.64 -> 407.04 | N22: =+N20*0.53 -> 212 | O22: =+O20*2.22 -> 266.4 | P22: =+P20*1.7 -> 2002.6 | Q22: =+Q20*2.26 -> 160.46 | R22: =+R20*1.8 -> 2016 | S22: =+S20*2.47 -> 1235 | T22: =+T20*2.36 -> 2053.2 | U22: =+U20*0.42 -> 1400.7 | V22: =+V20*0.32 -> 401.6 | W22: =+W20*2 -> 2600 | X22: =+X20*0.8 -> 224 | Y22: =+Y20*2 -> 86
D24: 4833.84 | H24: 2440.8 | J24: 2775.25 | P24: 2002.6 | R24: 288 | Y24: =SUM(D22:Y22) -> 23801.41
D25: =9148*0.02+5500*0.01 -> 237.96 | H25: =1952*0.05 -> 97.6 | J25: =265*0.02 -> 5.3 | P25: =128*0.05 -> 6.4 | R25: =50*0.05 -> 2.5
D26: 5071.8 | H26: 2538.4 | J26: 2780.55 | P26: 2009 | R26: 290.5
C28: STOCK REAL | D28: 8110 | E28: 2267 | F28: 418 | G28: 1510 | H28: 4017 | J28: 1610 | K28: 3906 | M28: 638 | N28: 455 | O28: 120 | P28: 1180 | Q28: 71 | R28: 1111 | S28: 500 | T28: 870 | U28: 3339 | V28: 1267 | W28: 1300 | X28: 280 | Y28: 43
C30: DIF STOCK | D30: 462 | E30: -400 | F30: -5 | G30: -36 | H30: -3 | I30: 0 | J30: -55 | K30: 0 | L30: 0 | M30: 2 | N30: 55 | O30: 0 | P30: 2 | Q30: 0 | R30: -9 | S30: 0 | T30: 0 | U30: 4 | V30: 12 | W30: 0 | X30: 0 | Y30: 0
C32: DIF EN SOLES | D32: 152.46 | E32: -160 | F32: -1.9 | G32: -15.48 | H32: -1.62 | J32: -46.75 | M32: 1.28 | N32: 29.15 | P32: 3.4 | R32: -16.2 | U32: 1.68 | V32: 3.84 | Y32: =SUM(D32:X32) -> -50.14
X33: INICIO S/. | Y33: =Y24+Y32 -> 23751.27

Sheet STOCK 31 a 006
D2: PANDERETA | H2: 18 HUECOS | O2: TECHO 12 | R2: TECHO 15 | U2: ARTESANAL | W2: SUPER KK | X2: TIPO 4 | Y2: TECHO 08
B3: FECHA | C3: CLIENTE | D3: SIPAN | E3: CHALPON | F3: CERAM | G3: FORTALEZA | H3: CERAM | I3: TORRE FUERTE | J3: LARK | K3: FORTALEZA | L3: CRUZ CHALPON | M3: TAISON | N3: SIPAN | O3: LARK | P3: ITAL | Q3: FORTALEZA | R3: ITAL | S3: LARK | T3: FORTALEZA | U3: BODOQUE | V3: PEQUEÑO | W3: CERAMICOS | X3: FORTALEZA | Y3: CERAM
A4: INGRESO | D4: ='STOCK 24 a 030'!D28 -> 8110 | E4: ='STOCK 24 a 030'!E28 -> 2267 | F4: ='STOCK 24 a 030'!F28 -> 418 | G4: ='STOCK 24 a 030'!G28 -> 1510 | H4: ='STOCK 24 a 030'!H28 -> 4017 | I4: ='STOCK 24 a 030'!I28 -> 0 | J4: ='STOCK 24 a 030'!J28 -> 1610 | K4: ='STOCK 24 a 030'!K28 -> 3906 | ... Y4: ='STOCK 24 a 030'!Y28 -> 43
B5: 45384 | C5: M8B-897 | V5: 4000
B6: 45386 | C6: M8B-897 | W6: 1500
B7: 45386 | C7: M6I-897 | W7: 1000
B8: 45387 | C8: M6I-897 | K8: 1500 | Q8: 537
B9: 45387 | C9: M8B-897 | U9: 3300
B10: 45388 | C10: M8B-897 | V10: 5000
A11: SALIDADA | B11: 45383 | C11: VENTAS H&C | D11: 1000 | M11: 633 | V11: 1000
B12: 45384 | C12: VENTAS H&C | V12: 2000
B13: 45385 | C13: VENTA JORDY | D13: 2000 | J13: 1000
B14: 45386 | C14: VENTAS H&C | D14: 100 | P14: 30 | Q14: 70
B15: 45387 | C15: VENTAS H&C | D15: =500+500 -> 1000
B16: 45388 | C16: VENTAS H&C | V16: 20
A22: SALDO | D22: =SUM(D4:D10)-SUM(D11:D21) -> 4010 | E22: =SUM(E4:E10)-SUM(E11:E21) -> 2267 | F22: =SUM(F4:F10)-SUM(F11:F21) -> 418 | G22: =SUM(G4:G10)-SUM(G11:G21) -> 1510 | H22: =SUM(H4:H10)-SUM(H11:H21) -> 4017 | I22: =SUM(I4:I10)-SUM(I11:I21) -> 0 | J22: =SUM(J4:J10)-SUM(J11:J21) -> 610 | K22: =SUM(K4:K10)-SUM(K11:K21) -> 5406 | ... Y22: =SUM(Y4:Y10)-SUM(Y11:Y21) -> 43
D24: =D22*0.33 -> 1323.3 | E24: =+E22*0.4 -> 906.8 | F24: =+F22*0.38 -> 158.84 | G24: =+G22*0.43 -> 649.3 | H24: =+H22*0.54 -> 2169.18 | I24: =+I22*0.6 -> 0 | J24: =+J22*0.85 -> 518.5 | K24: =+K22*0.66+(3906*0.04) -> 3724.2 | L24: =+L22*0.66 -> 0 | M24: =+M22*0.64 -> 3.2 | N24: =+N22*0.53 -> 241.15 | O24: =+O22*2.22 -> 266.4 | P24: =+P22*1.7 -> 1955 | Q24: =+Q22*2.1+0.16 -> 1129.96 | R24: =+R22*1.8 -> 1999.8 | S24: =+S22*2.47 -> 1235 | T24: =+T22*2.36 -> 2053.2 | U24: =+U22*0.42 -> 2788.38 | V24: =+V22*0.32 -> 2319.04 | W24: =+W22*1.638157895 -> 6225 | X24: =+X22*0.8 -> 224 | Y24: =+Y22*2 -> 86
K26: =3906*0.04 -> 156.24 | Q26: 2.26 | T26: =870*0.16 -> 139.2 | Y26: =SUM(D24:Y24) -> 29976.25
W27: =SUM(D26:W26) -> 297.7
I31: CHICLAYO24h | W31: =1300*2 -> 2600
W32: =2500*1.45 -> 3625
W33: =SUM(W31:W32) -> 6225
W34: =W33/3800 -> 1.6381579

Sheet STOCK 007 a 13
D2: PANDERETA | H2: 18 HUECOS | O2: TECHO 12 | R2: TECHO 15 | U2: ARTESANAL | W2: SUPER KK | X2: TIPO 4 | Y2: TECHO 08
B3: FECHA | C3: CLIENTE | D3: SIPAN | E3: CHALPON | F3: CERAM | G3: FORTALEZA | H3: CERAM | I3: TORRE FUERTE | J3: LARK | K3: FORTALEZA | L3: CRUZ CHALPON | M3: TAISON | N3: SIPAN | O3: LARK | P3: ITAL | Q3: FORTALEZA | R3: ITAL | S3: LARK | T3: FORTALEZA | U3: BODOQUE | V3: PEQUEÑO | W3: CERAMICOS | X3: FORTALEZA | Y3: CERAM
A4: INGRESO | D4: ='STOCK 31 a 006'!D22 -> 4010 | E4: ='STOCK 31 a 006'!E22 -> 2267 | F4: ='STOCK 31 a 006'!F22 -> 418 | G4: ='STOCK 31 a 006'!G22 -> 1510 | H4: ='STOCK 31 a 006'!H22 -> 4017 | I4: ='STOCK 31 a 006'!I22 -> 0 | J4: ='STOCK 31 a 006'!J22 -> 610 | K4: ='STOCK 31 a 006'!K22 -> 5406 | ... P4: ='STOCK 31 a 006'!P22 -> 1150 | Q4: 537 | R4: ='STOCK 31 a 006'!R22 -> 1111 | S4: ='STOCK 31 a 006'!S22 -> 500 | T4: ='STOCK 31 a 006'!T22 -> 870 | U4: ='STOCK 31 a 006'!U22 -> 6639 | V4: ='STOCK 31 a 006'!V22 -> 7247 | W4: ='STOCK 31 a 006'!W22 -> 3800 | X4: ='STOCK 31 a 006'!X22 -> 280 | Y4: ='STOCK 31 a 006'!Y22 -> 43
B5: 45393 | C5: M8B-893 | W5: 1000
B6: 45395 | C6: M8B-893 | J6: 1500
A11: SALIDADA | B11: 45389 | C11: VENTAS H&C | E11: 20 | V11: 200
B12: 45390 | C12: VENTAS H&C | U12: 50
B13: 45391 | C13: VENTAS H&C | V13: 10
B14: 45391 | C14: VENTA JORDY | W14: 2500
B15: 45392 | C15: VENTAS H&C | D15: 1000 | P15: 330 | U15: 350
B16: 45393 | C16: VENTAS H&C | O16: 100
B17: 45394 | C17: VENTAS H&C | U17: 1000
B18: 45395 | C18: VENTAS H&C | U18: 500
A23: SALDO | D23: =SUM(D4:D10)-SUM(D11:D22) -> 3010 | E23: =SUM(E4:E10)-SUM(E11:E22) -> 2247 | F23: =SUM(F4:F10)-SUM(F11:F22) -> 418 | G23: =SUM(G4:G10)-SUM(G11:G22) -> 1510 | H23: =SUM(H4:H10)-SUM(H11:H22) -> 4017 | I23: =SUM(I4:I10)-SUM(I11:I22) -> 0 | J23: =SUM(J4:J10)-SUM(J11:J22) -> 2110 | K23: =SUM(K4:K10)-SUM(K11:K22) -> 5406 | ... Y23: =SUM(Y4:Y10)-SUM(Y11:Y22) -> 43
D25: =D23*0.33 -> 993.3 | E25: =+E23*0.4 -> 898.8 | F25: =+F23*0.38 -> 158.84 | G25: =+G23*0.43 -> 649.3 | H25: =+H23*0.54 -> 2169.18 | I25: =+I23*0.6 -> 0 | J25: =+J23*0.81 -> 1709.1 | K25: =+K23*0.66 -> 3567.96 | L25: =+L23*0.66 -> 0 | M25: =+M23*0.64 -> 3.2 | N25: =+N23*0.53 -> 241.15 | O25: =+O23*2.22 -> 44.4 | P25: =+P23*1.7 -> 1394 | Q25: =+Q23*2.1 -> 1127.7 | R25: =+R23*1.8 -> 1999.8 | S25: =+S23*2.47 -> 1235 | T25: =+T23*2.2 -> 1914 | U25: =+U23*0.42 -> 1990.38 | V25: =+V23*0.32 -> 2251.84 | W25: =+W23*1.69 -> 3887 | X25: =+X23*0.8 -> 224 | Y25: =+Y23*2 -> 86
J27: 24.4 | K27: =3906*0.04 -> 156.24 | Q27: 2.26 | T27: =870*0.16 -> 139.2 | Y27: =SUM(D25:Y25) -> 26544.95
J28: 1733.5 | K28: 3724.2 | Q28: 1129.96 | T28: 2053.2 | W28: =SUM(D27:W27) -> 322.1
I32: CHICLAYO24h | U32: =29976.25-297.7 -> 29678.55 | W32: =1300*1.638157895 -> 2129.6053
W33: 1750
W34: =+W32+W33 -> 3879.6053
W35: =W34/2300 -> 1.6867849
W37: 3767.76
W38: =(1.75-1.638157895)*1000 -> 111.84211
W39: =+W38+W37 -> 3879.6021
W40: =W34-W25 -> -7.3947365

Sheet STOCK 014 a 20
D2: PANDERETA | H2: 18 HUECOS | O2: TECHO 12 | R2: TECHO 15 | U2: ARTESANAL | W2: SUPER KK | X2: TIPO 4 | Y2: TECHO 08
B3: FECHA | C3: CLIENTE | D3: SIPAN | E3: CHALPON | F3: CERAM | G3: FORTALEZA | H3: CERAM | I3: TORRE FUERTE | J3: LARK | K3: FORTALEZA | L3: CRUZ CHALPON | M3: TAISON | N3: SIPAN | O3: LARK | P3: ITAL | Q3: FORTALEZA | R3: ITAL | S3: LARK | T3: FORTALEZA | U3: BODOQUE | V3: PEQUEÑO | W3: CERAMICOS | X3: FORTALEZA | Y3: CERAM
A4: INGRESO | D4: ='STOCK 007 a 13'!D23 -> 3010 | E4: ='STOCK 007 a 13'!E23 -> 2247 | F4: ='STOCK 007 a 13'!F23 -> 418 | G4: ='STOCK 007 a 13'!G23 -> 1510 | H4: ='STOCK 007 a 13'!H23 -> 4017 | I4: ='STOCK 007 a 13'!I23 -> 0 | J4: ='STOCK 007 a 13'!J23 -> 2110 | K4: ='STOCK 007 a 13'!K23 -> 5406 | ... Y4: ='STOCK 007 a 13'!Y23 -> 43
B5: 45399 | C5: M8B-893 | O5: 1000
A11: SALIDADA | B11: 45397 | C11: VENTAS H&C | N11: 50
B12: 45398 | C12: VENTAS H&C | D12: 1500 | V12: 300
B13: 45399 | C13: VENTAS H&C | K13: 500 | V13: 300
B14: 45400 | C14: VENTAS H&C | J14: 500
B15: 45401 | C15: VENTAS H&C | U15: 1000 | V15: 2000
A23: SALDO | D23: =SUM(D4:D10)-SUM(D11:D22) -> 1510 | E23: =SUM(E4:E10)-SUM(E11:E22) -> 2247 | F23: =SUM(F4:F10)-SUM(F11:F22) -> 418 | G23: =SUM(G4:G10)-SUM(G11:G22) -> 1510 | H23: =SUM(H4:H10)-SUM(H11:H22) -> 4017 | I23: =SUM(I4:I10)-SUM(I11:I22) -> 0 | J23: =SUM(J4:J10)-SUM(J11:J22) -> 1610 | K23: =SUM(K4:K10)-SUM(K11:K22) -> 4906 | ... Y23: =SUM(Y4:Y10)-SUM(Y11:Y22) -> 43
D25: =D23*0.33 -> 498.3 | E25: =+E23*0.4 -> 898.8 | F25: =+F23*0.38 -> 158.84 | G25: =+G23*0.43 -> 649.3 | H25: =+H23*0.54 -> 2169.18 | I25: =+I23*0.6 -> 0 | J25: =+J23*0.81 -> 1304.1 | K25: =+K23*0.66 -> 3237.96 | L25: =+L23*0.66 -> 0 | M25: =+M23*0.64 -> 3.2 | N25: =+N23*0.53 -> 214.65 | O25: =+O23*2.05 -> 2091 | P25: =+P23*1.7 -> 1394 | Q25: =+Q23*2.1 -> 1127.7 | R25: =+R23*1.8 -> 1999.8 | S25: =+S23*2.47 -> 1235 | T25: =+T23*2.2 -> 1914 | U25: =+U23*0.42 -> 1570.38 | V25: =+V23*0.32 -> 1419.84 | W25: =+W23*1.69 -> 3887 | X25: =+X23*0.8 -> 224 | Y25: =+Y23*2 -> 86
O27: =20*0.17 -> 3.4 | Y27: =SUM(D25:Y25) -> 26083.05
O29: =44.4+2050 -> 2094.4
O30: =+O29-O27 -> 2091

Sheet STOCK 022 a 27
D2: PANDERETA | H2: 18 HUECOS | O2: TECHO 12 | R2: TECHO 15 | U2: ARTESANAL | W2: SUPER KK | X2: TIPO 4 | Y2: TECHO 08
B3: FECHA | C3: CLIENTE | D3: SIPAN | E3: CHALPON | F3: CERAM | G3: FORTALEZA | H3: CERAM | I3: TORRE FUERTE | J3: LARK | K3: FORTALEZA | L3: CRUZ CHALPON | M3: TAISON | N3: SIPAN | O3: LARK | P3: ITAL | Q3: FORTALEZA | R3: ITAL | S3: LARK | T3: FORTALEZA | U3: BODOQUE | V3: PEQUEÑO | W3: CERAMICOS | X3: FORTALEZA | Y3: CERAM
A4: INGRESO | D4: ='STOCK 014 a 20'!D23 -> 1510 | E4: ='STOCK 014 a 20'!E23 -> 2247 | F4: ='STOCK 014 a 20'!F23 -> 418 | G4: ='STOCK 014 a 20'!G23 -> 1510 | H4: ='STOCK 014 a 20'!H23 -> 4017 | I4: ='STOCK 014 a 20'!I23 -> 0 | J4: ='STOCK 014 a 20'!J23 -> 1610 | K4: ='STOCK 014 a 20'!K23 -> 4906 | ... Y4: ='STOCK 014 a 20'!Y23 -> 43
A11: SALIDADA | B11: 45404 | C11: VENTAS H&C | U11: 20 | V11: 500
B12: 45405 | C12: VENTAS H&C | U12: 400
B13: 45405 | C13: VENTA JORDY | W13: 500
B14: 45406 | C14: VENTAS H&C | K14: 1500
B15: 45407 | C15: VENTAS H&C | P15: 750 | U15: 500
B16: 45407 | C16: VENTA JORDY
B17: 45408 | C17: VENTAS H&C | H17: 95 | N17: 405 | U17: =1000+100 -> 1100 | W17: 200
B18: 45409 | C18: VENTAS H&C | T18: 65 | W18: 250
A25: SALDO | D25: =SUM(D4:D10)-SUM(D11:D24) -> 1510 | E25: =SUM(E4:E10)-SUM(E11:E24) -> 2247 | F25: =SUM(F4:F10)-SUM(F11:F24) -> 418 | G25: =SUM(G4:G10)-SUM(G11:G24) -> 1510 | H25: =SUM(H4:H10)-SUM(H11:H24) -> 3922 | I25: =SUM(I4:I10)-SUM(I11:I24) -> 0 | J25: =SUM(J4:J10)-SUM(J11:J24) -> 1610 | K25: =SUM(K4:K10)-SUM(K11:K24) -> 3406 | ... Y25: =SUM(Y4:Y10)-SUM(Y11:Y24) -> 43
D27: =D25*0.33 -> 498.3 | E27: =+E25*0.4 -> 898.8 | F27: =+F25*0.38 -> 158.84 | G27: =+G25*0.43 -> 649.3 | H27: =+H25*0.54 -> 2117.88 | I27: =+I25*0.6 -> 0 | J27: =+J25*0.81 -> 1304.1 | K27: =+K25*0.66 -> 2247.96 | L27: =+L25*0.66 -> 0 | M27: =+M25*0.64 -> 3.2 | N27: =+N25*0.53 -> 0 | O27: =+O25*2.05 -> 2091 | P27: =+P25*1.7 -> 119 | Q27: =+Q25*2.1 -> 1127.7 | R27: =+R25*1.8 -> 1999.8 | S27: =+S25*2.47 -> 1235 | T27: =+T25*2.2 -> 1771 | U27: =+U25*0.42 -> 721.98 | V27: =+V25*0.32 -> 1259.84 | W27: =+W25*1.69 -> 2281.5 | X27: =+X25*0.8 -> 224 | Y27: =+Y25*2 -> 86
Y29: =SUM(D27:Y27) -> 20795.2
P33: 3650 | Q33: 28566.72
P34: 4625.26 | Q34: 32281.44
P35: 7709.42 | Q35: 13000
P36: 9434.79 | Q36: 10121.5
P37: 7416.1 | Q37: 200
P38: 21103.64 | Q38: 28543.9
P39: 2190.35 | Q39: 8997.31 | T39: =100*31.6 -> 3160
P40: 9259.27 | Q40: 726 | T40: =50*29.6 -> 1480
P41: 12758.19 | Q41: 1896.6 | T41: =SUM(T39:T40) -> 4640
P42: 12614 | Q42: 660
P43: 4524 | Q43: 35
P44: 3500 | Q44: 200
P45: 15000 | Q45: 50
P46: 2601 | Q46: 240
P47: 4267 | Q47: 75
P48: =SUM(P33:P47) -> 120653.02 | Q48: 2136.5
Q49: =SUM(Q33:Q48) -> 127729.97
Q51: =Q49-P48 -> 7076.95

Sheet STOCK 28 a 04
D2: PANDERETA | H2: 18 HUECOS | O2: TECHO 12 | R2: TECHO 15 | U2: ARTESANAL | W2: SUPER KK | X2: TIPO 4 | Y2: TECHO 08
B3: FECHA | C3: CLIENTE | D3: SIPAN | E3: CHALPON | F3: CERAM | G3: FORTALEZA | H3: CERAM | I3: TORRE FUERTE | J3: LARK | K3: FORTALEZA | L3: CRUZ CHALPON | M3: TAISON | N3: SIPAN | O3: LARK | P3: ITAL | Q3: FORTALEZA | R3: ITAL | S3: LARK | T3: FORTALEZA | U3: BODOQUE | V3: PEQUEÑO | W3: CERAMICOS | X3: FORTALEZA | Y3: CERAM
A4: INGRESO | D4: ='STOCK 022 a 27'!D25 -> 1510 | E4: ='STOCK 022 a 27'!E25 -> 2247 | F4: ='STOCK 022 a 27'!F25 -> 418 | G4: ='STOCK 022 a 27'!G25 -> 1510 | H4: ='STOCK 022 a 27'!H25 -> 3922 | I4: ='STOCK 022 a 27'!I25 -> 0 | J4: ='STOCK 022 a 27'!J25 -> 1610 | K4: ='STOCK 022 a 27'!K25 -> 3406 | ... Y4: ='STOCK 022 a 27'!Y25 -> 43
B5: 45411 | C5: M6I-897 | P5: 1200
B6: 45412 | C6: M8B-893 | P6: 200
B7: 45412 | C7: M8B-893 | D7: 4910
B8: 45414 | C8: M8B-893 | D8: 60
B9: 45415 | C9: M6I-897 | U9: 3000
A11: SALIDA | B11: 45411 | C11: VENTAS H&C | K11: 1000
B12: 45412 | C12: VENTAS H&C | P12: 810
B13: 45412 | C13: VENTA JORDY | D13: 800
B14: 45413 | C14: VENTAS H&C | W14: 200
B15: 45414 | C15: VENTAS H&C | W15: 200
B16: 45416 | C16: VENTAS H&C | R16: 140 | U16: 500
A26: SALDO | D26: =SUM(D4:D10)-SUM(D11:D25) -> 5680 | E26: =SUM(E4:E10)-SUM(E11:E25) -> 2247 | F26: =SUM(F4:F10)-SUM(F11:F25) -> 418 | G26: =SUM(G4:G10)-SUM(G11:G25) -> 1510 | H26: =SUM(H4:H10)-SUM(H11:H25) -> 3922 | I26: =SUM(I4:I10)-SUM(I11:I25) -> 0 | J26: =SUM(J4:J10)-SUM(J11:J25) -> 1610 | K26: =SUM(K4:K10)-SUM(K11:K25) -> 2406 | ... Y26: =SUM(Y4:Y10)-SUM(Y11:Y25) -> 43
D28: =D26*0.31 -> 1760.8 | E28: =+E26*0.4 -> 898.8 | F28: =+F26*0.38 -> 158.84 | G28: =+G26*0.43 -> 649.3 | H28: =+H26*0.54 -> 2117.88 | I28: =+I26*0.6 -> 0 | J28: =+J26*0.81 -> 1304.1 | K28: =+K26*0.66 -> 1587.96 | L28: =+L26*0.66 -> 0 | M28: =+M26*0.64 -> 3.2 | N28: =+N26*0.53 -> 0 | O28: =+O26*2.05 -> 2091 | P28: =+P26*1.65 -> 1089 | Q28: =+Q26*2.1 -> 1127.7 | R28: =+R26*1.8 -> 1747.8 | S28: =+S26*2.47 -> 1235 | T28: =+T26*2.2 -> 1771 | U28: =+U26*0.42 -> 1771.98 | V28: =+V26*0.32 -> 1259.84 | W28: =+W26*1.69 -> 1605.5 | X28: =+X26*0.8 -> 224 | Y28: =+Y26*2 -> 86
Y30: =SUM(D28:Y28) -> 22489.7
E31: =0.4-0.35 -> 0.05 | F31: =0.38-0.34 -> 0.04 | G31: =0.43-0.38 -> 0.05 | J31: =0.81-0.79 -> 0.02 | K31: =0.66-0.63 -> 0.03 | Q31: =2.1-1.89 -> 0.21 | R31: =1.8-1.7 -> 0.1 | S31: =2.47-2.08 -> 0.39 | T31: =2.2-1.97 -> 0.23
E32: =+E26*E31 -> 112.35 | F32: =+F26*F31 -> 16.72 | G32: =+G26*G31 -> 75.5 | J32: =+J26*J31 -> 32.2 | K32: =+K26*K31 -> 72.18 | M32: 3.2 | Q32: =+Q26*Q31 -> 112.77 | R32: =+R26*R31 -> 97.1 | S32: =+S26*S31 -> 195 | T32: =+T26*T31 -> 185.15
T33: =SUM(D32:Y32) -> 902.17
T34: 22489.7
T35: =T34-T33 -> 21587.53

Sheet STOCK 05 a 011
D2: PANDERETA | H2: 18 HUECOS | O2: TECHO 12 | R2: TECHO 15 | U2: ARTESANAL | W2: SUPER KK | X2: TIPO 4 | Y2: TECHO 08
B3: FECHA | C3: CLIENTE | D3: SIPAN | E3: CHALPON | F3: CERAM | G3: FORTALEZA | H3: CERAM | I3: TORRE FUERTE | J3: LARK | K3: FORTALEZA | L3: CRUZ CHALPON | M3: TAISON | N3: SIPAN | O3: LARK | P3: ITAL | Q3: FORTALEZA | R3: ITAL | S3: LARK | T3: FORTALEZA | U3: BODOQUE | V3: PEQUEÑO | W3: CERAMICOS | X3: FORTALEZA | Y3: CERAM
A4: INGRESO | D4: ='STOCK 28 a 04'!D26 -> 5680 | E4: ='STOCK 28 a 04'!E26 -> 2247 | F4: ='STOCK 28 a 04'!F26 -> 418 | G4: ='STOCK 28 a 04'!G26 -> 1510 | H4: ='STOCK 28 a 04'!H26 -> 3922 | I4: ='STOCK 28 a 04'!I26 -> 0 | J4: ='STOCK 28 a 04'!J26 -> 1610 | K4: ='STOCK 28 a 04'!K26 -> 2406 | ... Y4: ='STOCK 28 a 04'!Y26 -> 43
B5: 45419 | C5: M8B-893 | W5: 400
B6: 45420 | C6: M6I-897 | P6: 600 | R6: 500
B7: 45423 | C7: M8B-893 | U7: 3000
A11: SALIDA | B11: 45418 | C11: VENTAS H&C | V11: 6
B12: 45419 | C12: VENTAS H&C | H12: 250 | U12: =600+200 -> 800
B13: 45420 | C13: VENTAS H&C | D13: 500 | P13: 1 | V13: 1000 | W13: 80
B14: 45421 | C14: VENTAS H&C | E14: 2000 | H14: 500 | J14: 500 | R14: 400
B15: 45422 | C15: VENTA JORDY | D15: 3000
A26: SALDO | D26: =SUM(D4:D10)-SUM(D11:D25) -> 2180 | E26: =SUM(E4:E10)-SUM(E11:E25) -> 247 | F26: =SUM(F4:F10)-SUM(F11:F25) -> 418 | G26: =SUM(G4:G10)-SUM(G11:G25) -> 1510 | H26: =SUM(H4:H10)-SUM(H11:H25) -> 3172 | I26: =SUM(I4:I10)-SUM(I11:I25) -> 0 | J26: =SUM(J4:J10)-SUM(J11:J25) -> 1110 | K26: =SUM(K4:K10)-SUM(K11:K25) -> 2406 | ... Y26: =SUM(Y4:Y10)-SUM(Y11:Y25) -> 43
D28: =D26*0.31 -> 675.8 | E28: =+E26*0.4 -> 98.8 | F28: =+F26*0.38 -> 158.84 | G28: =+G26*0.43 -> 649.3 | H28: =+H26*0.54 -> 1712.88 | I28: =+I26*0.6 -> 0 | J28: =+J26*0.81 -> 899.1 | K28: =+K26*0.66 -> 1587.96 | L28: =+L26*0.66 -> 0 | M28: =+M26*0.64 -> 3.2 | N28: =+N26*0.53 -> 0 | O28: =+O26*2.05 -> 2091 | P28: =+P26*1.65 -> 2077.35 | Q28: =+Q26*2.1 -> 1127.7 | R28: =+R26*1.8-(500*0.1) -> 1877.8 | S28: =+S26*2.47 -> 1235 | T28: =+T26*2.2 -> 1771 | U28: =+U26*0.42 -> 2695.98 | V28: =+V26*0.32 -> 937.92 | W28: =+W26*1.69+(400*0.31) -> 2270.3 | X28: =+X26*0.8 -> 224 | Y28: =+Y26*2 -> 86
Y30: =SUM(D28:Y28) -> 22179.93
C31: REAL | D31: 1500 | E31: 738 | F31: 398 | G31: 1496 | H31: =1178+2000 -> 3178 | J31: 1110 | K31: 2395 | O31: 1019 | P31: 1259 | Q31: 540 | R31: 1068 | S31: 500 | T31: 805 | U31: =3409 -> 3409 | V31: 2922 | W31: =401+860 -> 1261 | X31: 280 | Y31: 43
C32: DIFERENCIA | D32: =D31-D26 -> -680 | E32: =E31-E26 -> 491 | F32: =F31-F26 -> -20 | G32: =G31-G26 -> -14 | H32: =H31-H26 -> 6 | I32: =I31-I26 -> 0 | J32: =J31-J26 -> 0 | K32: =K31-K26 -> -11 | ... T32: =T31-T26 -> 0 | U32: =U31-3419 -> -10 | V32: =V31-V26 -> -9 | W32: =W31-W26 -> -9 | X32: =X31-X26 -> 0 | Y32: =Y31-Y26 -> 0
D33: =D32*0.31 -> -210.8 | E33: =E32*0.4 -> 196.4 | F33: =F32*0.38 -> -7.6 | G33: =G32*0.43 -> -6.02 | H33: =H32*0.54 -> 3.24 | K33: =K32*0.66 -> -7.26 | M33: =M32*0.64 -> -3.2 | O33: =O32*2.05 -> -2.05 | Q33: =Q32*2.1 -> 6.3 | R33: =R32*1.7 -> -5.1 | T33: =T32*2.2 -> 0 | U33: =U32*0.42 -> -4.2 | V33: =V32*0.32 -> -2.88 | W33: =W32*1.78763779527 -> -16.08874
W34: =SUM(D33:W33) -> -59.25874
D35: 0 | E35: =0.4-0.35 -> 0.05 | F35: =0.38-0.34 -> 0.04 | G35: =0.43-0.38 -> 0.05 | H35: 0 | I35: 0 | J35: =0.81-0.79 -> 0.02 | K35: =0.66-0.63 -> 0.03 | L35: 0 | M35: 0 | N35: 0 | O35: =2.05-2.08 -> -0.03 | P35: 0 | Q35: =2.1-1.89 -> 0.21 | R35: =1.8-1.7 -> 0.1 | S35: =2.47-2.18 -> 0.29 | T35: =2.2-1.97 -> 0.23 | U35: 0 | V35: 0 | W35: =1.78763779527-1.79 -> -0.0023622047 | X35: 0 | Y35: 0
D36: 0 | E36: =738*E35 -> 36.9 | F36: =+F31*F35 -> 15.92 | G36: =+G31*G35 -> 74.8 | H36: 0 | I36: 0 | J36: =+J26*J35 -> 22.2 | K36: =+K31*K35 -> 71.85 | L36: 0 | M36: 0 | N36: 0 | O36: =+O31*O35 -> -30.57 | P36: 0 | Q36: =+Q31*Q35 -> 113.4 | R36: =571*R35 -> 57.1 | S36: =+S26*S35 -> 145 | T36: =+T26*T35 -> 185.15 | U36: 0 | V36: 0 | W36: =+W31*W35 -> -2.9787402 | X36: 0 | Y36: 0
Y37: =SUM(D36:Y36) -> 688.77126
D38: =D31*0.31 -> 465 | E38: =E31*0.35 -> 258.3 | F38: =F31*0.34 -> 135.32 | G38: =G31*0.38 -> 568.48 | H38: =H31*0.54 -> 1716.12 | I38: =I31*0.31 -> 0 | J38: =J31*0.79 -> 876.9 | K38: =K31*0.63 -> 1508.85 | L38: =L31*0.31 -> 0 | M38: =M31*0.31 -> 0 | N38: =N31*0.31 -> 0 | O38: =O31*2.08 -> 2119.52 | P38: =P31*1.65 -> 2077.35 | Q38: =Q31*1.89 -> 1020.6 | R38: =R31*1.7 -> 1815.6 | S38: =S31*2.18 -> 1090 | T38: =T31*1.97 -> 1585.85 | U38: =6409*0.42 -> 2691.78 | V38: =V31*0.32 -> 935.04 | W38: =W31*1.79 -> 2257.19 | X38: =X31*0.8 -> 224 | Y38: =Y31*2 -> 86
Y39: =SUM(D38:Y38) -> 21431.9
D41: =D31*D35 -> 0 | E41: =E31*E35 -> 36.9 | F41: =F31*F35 -> 15.92 | G41: =G31*G35 -> 74.8 | H41: =H31*H35 -> 0 | I41: =I31*I35 -> 0 | J41: =J31*J35 -> 22.2 | K41: =K31*K35 -> 71.85 | ... Q41: =Q31*Q35 -> 113.4 | R41: =571*R35 -> 57.1 | S41: =S31*S35 -> 145 | T41: =T31*T35 -> 185.15 | U41: =U31*U35 -> 0 | V41: =V31*V35 -> 0 | W41: =W31*W35 -> -2.9787402 | X41: =X31*X35 -> 0 | Y41: =Y31*Y35 -> 0
X43: =-Y37+W34 -> -748.03
X44: =-W34+Y37 -> 748.03

Sheet STOCK 12 a 018
D2: PANDERETA | I2: 18 HUECOS | P2: TECHO 12 | S2: TECHO 15 | V2: ARTESANAL | X2: SUPER KK | Y2: TIPO 4 | Z2: TECHO 08
B3: FECHA | C3: CLIENTE | D3: SIPAN | E3: CHALPON | F3: ZERAMIX | G3: CERAM | H3: FORTALEZA | I3: CERAM | J3: TORRE FUERTE | K3: LARK | L3: FORTALEZA | M3: CRUZ CHALPON | N3: TAISON | O3: SIPAN | P3: LARK | Q3: ITAL | R3: FORTALEZA | S3: ITAL | T3: LARK | U3: FORTALEZA | V3: BODOQUE | W3: PEQUEÑO | X3: CERAMICOS | Y3: FORTALEZA | Z3: CERAM
A4: INGRESO | D4: ='STOCK 05 a 011'!D31 -> 1500 | E4: ='STOCK 05 a 011'!E31 -> 738 | G4: ='STOCK 05 a 011'!F31 -> 398 | H4: ='STOCK 05 a 011'!G31 -> 1496 | I4: ='STOCK 05 a 011'!H31 -> 3178 | J4: ='STOCK 05 a 011'!I31 -> 0 | K4: ='STOCK 05 a 011'!J31 -> 1110 | L4: ='STOCK 05 a 011'!K31 -> 2395 | M4: ='STOCK 05 a 011'!L31 -> 0 | N4: ='STOCK 05 a 011'!M31 -> 0 | ... U4: ='STOCK 05 a 011'!T31 -> 805 | V4: 6409 | W4: ='STOCK 05 a 011'!V31 -> 2922 | X4: ='STOCK 05 a 011'!W31 -> 1261 | Y4: ='STOCK 05 a 011'!X31 -> 280 | Z4: ='STOCK 05 a 011'!Y31 -> 43
B5: 45428 | C5: M6I-897 | F5: 1000
B6: 45429 | C6: M8B-893 | D6: 4000
A11: SALIDA | B11: 45424 | C11: VENTAS H&C | W11: 22
B12: 45425 | C12: VENTAS H&C | X12: 1000
B13: 45426 | C13: VENTAS H&C | W13: =500+200 -> 700
B14: 45427 | C14: VENTAS H&C | I14: 150 | V14: 100
B15: 45429 | C15: VENTAS H&C | D15: 1000 | K15: 120 | V15: 1000
A26: SALDO | D26: =SUM(D4:D10)-SUM(D11:D25) -> 4500 | E26: =SUM(E4:E10)-SUM(E11:E25) -> 738 | F26: =SUM(F4:F10)-SUM(F11:F25) -> 1000 | G26: =SUM(G4:G10)-SUM(G11:G25) -> 398 | H26: =SUM(H4:H10)-SUM(H11:H25) -> 1496 | I26: =SUM(I4:I10)-SUM(I11:I25) -> 3028 | J26: =SUM(J4:J10)-SUM(J11:J25) -> 0 | K26: =SUM(K4:K10)-SUM(K11:K25) -> 990 | ... Z26: =SUM(Z4:Z10)-SUM(Z11:Z25) -> 43
D28: =D26*0.31 -> 1395 | E28: =+E26*0.35 -> 258.3 | F28: =+F26*0.29 -> 290 | G28: =+G26*0.34 -> 135.32 | H28: =+H26*0.38 -> 568.48 | I28: =+I26*0.54 -> 1635.12 | J28: =+J26*0.6 -> 0 | K28: =+K26*0.79 -> 782.1 | L28: =+L26*0.63 -> 1508.85 | M28: =+M26*0.66 -> 0 | N28: =+N26*0.64 -> 0 | O28: =+O26*0.53 -> 0 | P28: =+P26*2.08 -> 2119.52 | Q28: =+Q26*1.65 -> 2077.35 | R28: =+R26*1.89 -> 1020.6 | S28: =+S26*1.7 -> 1815.6 | T28: =+T26*2.18 -> 1090 | U28: =+U26*1.97 -> 1585.85 | V28: =+V26*0.42 -> 2229.78 | W28: =+W26*0.32 -> 704 | X28: =+X26*1.79 -> 467.19 | Y28: =+Y26*0.8 -> 224 | Z28: =+Z26*2 -> 86
Z30: =SUM(D28:Z28) -> 19993.06

Sheet STOCK 19 a 025
D2: PANDERETA | I2: 18 HUECOS | P2: TECHO 12 | S2: TECHO 15 | V2: ARTESANAL | X2: SUPER KK | Y2: TIPO 4 | Z2: TECHO 08
B3: FECHA | C3: CLIENTE | D3: SIPAN | E3: CHALPON | F3: ZERAMIX | G3: CERAM | H3: FORTALEZA | I3: CERAM | J3: TORRE FUERTE | K3: LARK | L3: FORTALEZA | M3: CRUZ CHALPON | N3: TAISON | O3: SIPAN | P3: LARK | Q3: ITAL | R3: FORTALEZA | S3: ITAL | T3: LARK | U3: FORTALEZA | V3: BODOQUE | W3: PEQUEÑO | X3: CERAMICOS | Y3: FORTALEZA | Z3: CERAM
A4: INGRESO | D4: ='STOCK 12 a 018'!D26 -> 4500 | E4: ='STOCK 12 a 018'!E26 -> 738 | F4: ='STOCK 12 a 018'!F26 -> 1000 | G4: ='STOCK 12 a 018'!G26 -> 398 | H4: ='STOCK 12 a 018'!H26 -> 1496 | I4: ='STOCK 12 a 018'!I26 -> 3028 | J4: ='STOCK 12 a 018'!J26 -> 0 | K4: ='STOCK 12 a 018'!K26 -> 990 | ... Z4: ='STOCK 12 a 018'!Z26 -> 43
B5: 45433 | C5: M6I-897 | W5: 3000
B6: 45435 | C6: M6I-897 | L6: 2000
B7: 45437 | C7: M8B-893 | F7: 2000
A11: SALIDA | B11: 45431 | C11: VENTAS H&C | W11: 1000
B12: 45432 | C12: VENTAS H&C | D12: 500 | E12: 30 | F12: 500 | I12: =1100-40 -> 1060 | V12: 500
B13: 45433 | C13: VENTA JORDY | W13: 500
B14: 45434 | C14: VENTAS H&C | Q14: 30
B15: 45436 | C15: VENTAS H&C | P15: 240
B16: 45437 | C16: VENTAS H&C | F16: 1500 | W16: =150+50 -> 200
A26: SALDO | D26: =SUM(D4:D10)-SUM(D11:D25) -> 4000 | E26: =SUM(E4:E10)-SUM(E11:E25) -> 708 | F26: =SUM(F4:F10)-SUM(F11:F25) -> 1000 | G26: =SUM(G4:G10)-SUM(G11:G25) -> 398 | H26: =SUM(H4:H10)-SUM(H11:H25) -> 1496 | I26: =SUM(I4:I10)-SUM(I11:I25) -> 1968 | J26: =SUM(J4:J10)-SUM(J11:J25) -> 0 | K26: =SUM(K4:K10)-SUM(K11:K25) -> 990 | ... Z26: =SUM(Z4:Z10)-SUM(Z11:Z25) -> 43
D28: =D26*0.31 -> 1240 | E28: =+E26*0.35 -> 247.8 | F28: =+F26*0.28 -> 280 | G28: =+G26*0.34 -> 135.32 | H28: =+H26*0.38 -> 568.48 | I28: =+I26*0.54 -> 1062.72 | J28: =+J26*0.6 -> 0 | K28: =+K26*0.79 -> 782.1 | L28: =+L26*0.6+(2395*0.03) -> 2708.85 | M28: =+M26*0.66 -> 0 | N28: =+N26*0.64 -> 0 | O28: =+O26*0.53 -> 0 | P28: =+P26*2.08 -> 1620.32 | Q28: =+Q26*1.65 -> 2027.85 | R28: =+R26*1.89 -> 1020.6 | S28: =+S26*1.7 -> 1815.6 | T28: =+T26*2.18 -> 1090 | U28: =+U26*1.97 -> 1585.85 | V28: =+V26*0.42 -> 2019.78 | W28: =+W26*0.31+(500*0.01) -> 1090 | X28: =+X26*1.79 -> 467.19 | Y28: =+Y26*0.8 -> 224 | Z28: =+Z26*2 -> 86
Z30: =SUM(D28:Z28) -> 20072.46
Y32: 19993.1
Y33: 1434.5

Sheet STOCK 26 a 01
D2: PANDERETA | I2: 18 HUECOS | P2: TECHO 12 | S2: TECHO 15 | V2: ARTESANAL | X2: SUPER KK | Y2: TIPO 4 | Z2: TECHO 08
B3: FECHA | C3: CLIENTE | D3: SIPAN | E3: CHALPON | F3: ZERAMIX | G3: CERAM | H3: FORTALEZA | I3: CERAM | J3: TORRE FUERTE | K3: LARK | L3: FORTALEZA | M3: CRUZ CHALPON | N3: TAISON | O3: SIPAN | P3: LARK | Q3: ITAL | R3: FORTALEZA | S3: ITAL | T3: LARK | U3: FORTALEZA | V3: BODOQUE | W3: PEQUEÑO | X3: CERAMICOS | Y3: FORTALEZA | Z3: CERAM
A4: INGRESO | D4: ='STOCK 19 a 025'!D26 -> 4000 | E4: ='STOCK 19 a 025'!E26 -> 708 | F4: ='STOCK 19 a 025'!F26 -> 1000 | G4: ='STOCK 19 a 025'!G26 -> 398 | H4: ='STOCK 19 a 025'!H26 -> 1496 | I4: ='STOCK 19 a 025'!I26 -> 1968 | J4: ='STOCK 19 a 025'!J26 -> 0 | K4: ='STOCK 19 a 025'!K26 -> 990 | ... Z4: ='STOCK 19 a 025'!Z26 -> 43
B5: 45441 | C5: M8B-893 | K5: 2000
A11: SALIDA | B11: 45439 | C11: VENTAS H&C | D11: 20 | F11: 500 | P11: 35 | U11: 500 | V11: 500
B12: 45440 | C12: VENTAS H&C | G12: 18 | I12: 150 | V12: 50 | W12: 500
B13: 45441 | C13: VENTAS H&C | D13: 1000 | H13: 20 | K13: 95
B14: 45442 | C14: VENTAS H&C | V14: 30 | W14: 70
B15: 45444 | C15: VENTAS H&C | W15: 60
A26: SALDO | D26: =SUM(D4:D10)-SUM(D11:D25) -> 2980 | E26: =SUM(E4:E10)-SUM(E11:E25) -> 708 | F26: =SUM(F4:F10)-SUM(F11:F25) -> 500 | G26: =SUM(G4:G10)-SUM(G11:G25) -> 380 | H26: =SUM(H4:H10)-SUM(H11:H25) -> 1476 | I26: =SUM(I4:I10)-SUM(I11:I25) -> 1818 | J26: =SUM(J4:J10)-SUM(J11:J25) -> 0 | K26: =SUM(K4:K10)-SUM(K11:K25) -> 2895 | ... Z26: =SUM(Z4:Z10)-SUM(Z11:Z25) -> 43
D28: =D26*0.31 -> 923.8 | E28: =+E26*0.35 -> 247.8 | F28: =+F26*0.28 -> 140 | G28: =+G26*0.34 -> 129.2 | H28: =+H26*0.38 -> 560.88 | I28: =+I26*0.54 -> 981.72 | J28: =+J26*0.6 -> 0 | K28: =+K26*0.79 -> 2287.05 | L28: =+L26*0.6+(2395*0.03) -> 2708.85 | M28: =+M26*0.66 -> 0 | N28: =+N26*0.64 -> 0 | O28: =+O26*0.53 -> 0 | P28: =+P26*2.08 -> 1547.52 | Q28: =+Q26*1.65 -> 2027.85 | R28: =+R26*1.89 -> 1020.6 | S28: =+S26*1.7 -> 1815.6 | T28: =+T26*2.18 -> 1090 | U28: =+U26*1.97 -> 600.85 | V28: =+V26*0.42 -> 1776.18 | W28: =+W26*0.31 -> 889.7 | X28: =+X26*1.79 -> 467.19 | Y28: =+Y26*0.8 -> 224 | Z28: =+Z26*2 -> 86
Z30: =SUM(D28:Z28) -> 19524.79
A32: SALDO | D32: 2980 | E32: 708 | F32: 500 | G32: 380 | H32: 1476 | I32: 1818 | J32: 0 | K32: 2895 | L32: 4395 | M32: 0 | N32: 0 | O32: 0 | P32: 744 | Q32: 1229 | R32: 540 | S32: 1068 | T32: 500 | U32: 305 | V32: 4229 | W32: 2870 | X32: 261 | Y32: 280 | Z32: 43
C33: FISICO | D33: 3000 | E33: 660 | F33: 596 | H33: 1500 | I33: =778+1000 -> 1778 | K33: 3000 | L33: =3000+1395 -> 4395 | P33: 744 | Q33: 1228 | R33: 540 | S33: 1068 | T33: 500 | U33: 304 | V33: 4300 | W33: 2900 | X33: 255 | Y33: 280 | Z33: 43
C35: DIFERENCIA | D35: =D33-D26 -> 20 | E35: =E33-E26 -> -48 | F35: =F33-F26 -> 96 | G35: =G33-G26 -> -380 | H35: =H33-H26 -> 24 | I35: =I33-I26 -> -40 | J35: =J33-J26 -> 0 | K35: =K33-K26 -> 105 | ... Z35: =Z33-Z26 -> 0

Sheet STOCK 02 a 08
D2: PANDERETA | I2: 18 HUECOS | P2: TECHO 12 | S2: TECHO 15 | V2: ARTESANAL | X2: SUPER KK | Y2: TIPO 4 | Z2: TECHO 08
B3: FECHA | C3: CLIENTE | D3: SIPAN | E3: CHALPON | F3: ZERAMIX | G3: CERAM | H3: FORTALEZA | I3: CERAM | J3: TORRE FUERTE | K3: LARK | L3: FORTALEZA | M3: CRUZ CHALPON | N3: TAISON | O3: SIPAN | P3: LARK | Q3: ITAL | R3: FORTALEZA | S3: ITAL | T3: LARK | U3: FORTALEZA | V3: BODOQUE | W3: PEQUEÑO | X3: CERAMICOS | Y3: FORTALEZA | Z3: CERAM
A4: INGRESO | D4: ='STOCK 26 a 01'!D26 -> 2980 | E4: ='STOCK 26 a 01'!E26 -> 708 | F4: ='STOCK 26 a 01'!F26 -> 500 | G4: ='STOCK 26 a 01'!G26 -> 380 | H4: ='STOCK 26 a 01'!H26 -> 1476 | I4: ='STOCK 26 a 01'!I26 -> 1818 | J4: ='STOCK 26 a 01'!J26 -> 0 | K4: ='STOCK 26 a 01'!K26 -> 2895 | ... Z4: ='STOCK 26 a 01'!Z26 -> 43
B5: 45449 | C5: M6I-897 | X5: 1000
B6: 45450 | C6: M6I-897 | F6: 3000
A11: SALIDA | B11: 45445 | C11: VENTAS H&C | W11: 100
B12: 45446 | C12: VENTAS H&C | D12: 1000 | F12: 500 | S12: 50
B13: 45447 | C13: VENTAS H&C | P13: 300 | Q13: 84 | V13: 500
B14: 45449 | C14: VENTAS H&C | W14: 500
B15: 45451 | C15: VENTAS H&C | D15: 1000 | F15: 500 | W15: 250
A26: SALDO | D26: =SUM(D4:D10)-SUM(D11:D25) -> 980 | E26: =SUM(E4:E10)-SUM(E11:E25) -> 708 | F26: =SUM(F4:F10)-SUM(F11:F25) -> 2500 | G26: =SUM(G4:G10)-SUM(G11:G25) -> 380 | H26: =SUM(H4:H10)-SUM(H11:H25) -> 1476 | I26: =SUM(I4:I10)-SUM(I11:I25) -> 1818 | J26: =SUM(J4:J10)-SUM(J11:J25) -> 0 | K26: =SUM(K4:K10)-SUM(K11:K25) -> 2895 | ... Z26: =SUM(Z4:Z10)-SUM(Z11:Z25) -> 43
D28: =D26*0.31 -> 303.8 | E28: =+E26*0.35 -> 247.8 | F28: =+F26*0.28 -> 700 | G28: =+G26*0.34 -> 129.2 | H28: =+H26*0.38 -> 560.88 | I28: =+I26*0.54 -> 981.72 | J28: =+J26*0.6 -> 0 | K28: =+K26*0.79 -> 2287.05 | L28: =+L26*0.6+(2395*0.03) -> 2708.85 | M28: =+M26*0.66 -> 0 | N28: =+N26*0.64 -> 0 | O28: =+O26*0.53 -> 0 | P28: =+P26*2.08 -> 923.52 | Q28: =+Q26*1.65 -> 1889.25 | R28: =+R26*1.89 -> 1020.6 | S28: =+S26*1.7 -> 1730.6 | T28: =+T26*2.18 -> 1090 | U28: =+U26*1.97 -> 600.85 | V28: =+V26*0.42 -> 1566.18 | W28: =+W26*0.31 -> 626.2 | X28: =+X26*1.9-(261*0.11) -> 2367.19 | Y28: =+Y26*0.8 -> 224 | Z28: =+Z26*2 -> 86
Z30: =SUM(D28:Z28) -> 20043.69

Sheet STOCK 09 a 15
D2: PANDERETA | I2: 18 HUECOS | P2: TECHO 12 | S2: TECHO 15 | V2: ARTESANAL | X2: SUPER KK | Y2: TIPO 4 | Z2: TECHO 08
B3: FECHA | C3: CLIENTE | D3: SIPAN | E3: CHALPON | F3: ZERAMIX | G3: CERAM | H3: FORTALEZA | I3: CERAM | J3: TORRE FUERTE | K3: LARK | L3: FORTALEZA | M3: CRUZ CHALPON | N3: TAISON | O3: SIPAN | P3: LARK | Q3: ITAL | R3: FORTALEZA | S3: ITAL | T3: LARK | U3: FORTALEZA | V3: BODOQUE | W3: PEQUEÑO | X3: CERAMICOS | Y3: FORTALEZA | Z3: CERAM
A4: INGRESO | D4: ='STOCK 02 a 08'!D26 -> 980 | E4: ='STOCK 02 a 08'!E26 -> 708 | F4: ='STOCK 02 a 08'!F26 -> 2500 | G4: ='STOCK 02 a 08'!G26 -> 380 | H4: ='STOCK 02 a 08'!H26 -> 1476 | I4: ='STOCK 02 a 08'!I26 -> 1818 | J4: ='STOCK 02 a 08'!J26 -> 0 | K4: ='STOCK 02 a 08'!K26 -> 2895 | ... Z4: ='STOCK 02 a 08'!Z26 -> 43
B5: 45454 | C5: M8B-893 | D5: 3000
A11: SALIDA | B11: 45452 | C11: VENTAS H&C | K11: 1
B12: 45453 | C12: VENTAS H&C | D12: 980 | E12: 500 | K12: 750 | L12: 1000
B13: 45454 | C13: VENTAS H&C | D13: 15 | H13: 200 | K13: =1+300 -> 301 | Q13: 20 | W13: 400 | X13: 100
B14: 45455 | C14: VENTAS H&C | H14: 100 | L14: 150
B15: 45456 | C15: VENTAS H&C | F15: =100+500 -> 600 | K15: 200
B16: 45457 | C16: VENTAS H&C | F16: 500
A26: SALDO | D26: =SUM(D4:D10)-SUM(D11:D25) -> 2985 | E26: =SUM(E4:E10)-SUM(E11:E25) -> 208 | F26: =SUM(F4:F10)-SUM(F11:F25) -> 1400 | G26: =SUM(G4:G10)-SUM(G11:G25) -> 380 | H26: =SUM(H4:H10)-SUM(H11:H25) -> 1176 | I26: =SUM(I4:I10)-SUM(I11:I25) -> 1818 | J26: =SUM(J4:J10)-SUM(J11:J25) -> 0 | K26: =SUM(K4:K10)-SUM(K11:K25) -> 1643 | ... Z26: =SUM(Z4:Z10)-SUM(Z11:Z25) -> 43
D28: =D26*0.3 -> 895.5 | E28: =+E26*0.35 -> 72.8 | F28: =+F26*0.28 -> 392 | G28: =+G26*0.34 -> 129.2 | H28: =+H26*0.38 -> 446.88 | I28: =+I26*0.54 -> 981.72 | J28: =+J26*0.6 -> 0 | K28: =+K26*0.79 -> 1297.97 | L28: =+L26*0.6+(1245*0.03) -> 1984.35 | M28: =+M26*0.66 -> 0 | N28: =+N26*0.64 -> 0 | O28: =+O26*0.53 -> 0 | P28: =+P26*2.08 -> 923.52 | Q28: =+Q26*1.65 -> 1856.25 | R28: =+R26*1.89 -> 1020.6 | S28: =+S26*1.7 -> 1730.6 | T28: =+T26*2.18 -> 1090 | U28: =+U26*1.97 -> 600.85 | V28: =+V26*0.42 -> 1566.18 | W28: =+W26*0.31 -> 502.2 | X28: =+X26*1.9-(161*0.11) -> 2188.19 | Y28: =+Y26*0.8 -> 224 | Z28: =+Z26*2 -> 86
Z30: =SUM(D28:Z28) -> 17988.81
R35: =60000-25500 -> 34500

Sheet STOCK 16 a 22
D2: PANDERETA | I2: 18 HUECOS | P2: TECHO 12 | S2: TECHO 15 | V2: ARTESANAL | X2: SUPER KK | Y2: TIPO 4 | Z2: TECHO 08
B3: FECHA | C3: CLIENTE | D3: SIPAN | E3: CHALPON | F3: ZERAMIX | G3: CERAM | H3: FORTALEZA | I3: CERAM | J3: TORRE FUERTE | K3: LARK | L3: FORTALEZA | M3: CRUZ CHALPON | N3: TAISON | O3: SIPAN | P3: LARK | Q3: ITAL | R3: FORTALEZA | S3: ITAL | T3: LARK | U3: FORTALEZA | V3: BODOQUE | W3: PEQUEÑO | X3: CERAMICOS | Y3: FORTALEZA | Z3: CERAM
A4: INGRESO | D4: ='STOCK 09 a 15'!D26 -> 2985 | E4: ='STOCK 09 a 15'!E26 -> 208 | F4: ='STOCK 09 a 15'!F26 -> 1400 | G4: ='STOCK 09 a 15'!G26 -> 380 | H4: ='STOCK 09 a 15'!H26 -> 1176 | I4: ='STOCK 09 a 15'!I26 -> 1818 | J4: ='STOCK 09 a 15'!J26 -> 0 | K4: ='STOCK 09 a 15'!K26 -> 1643 | ... Z4: ='STOCK 09 a 15'!Z26 -> 43
B5: 45462 | C5: M8B-893 | D5: 1000
B6: 45464 | C6: M6I-897 | F6: 500
B7: 45464 | C7: M8B-893 | W7: 5000
A11: SALIDA | B11: 45460 | C11: VENTAS H&C | D11: 60
B12: 45461 | C12: VENTAS H&C | S12: =600+140 -> 740 | V12: 150
B13: 45462 | C13: VENTA JORDY | D13: 2925 | V13: 600
B14: 45462 | C14: VENTAS H&C | W14: 1000
B15: 45463 | C15: VENTAS H&C | Q15: 400 | S15: 70 | V15: 100 | W15: 252
B16: 45464 | C16: VENTAS H&C | F16: 300 | L16: 1100 | W16: 650
B17: 45465 | C17: VENTAS H&C | H17: 1000 | I17: 200
A26: SALDO | D26: =SUM(D4:D10)-SUM(D11:D25) -> 1000 | E26: =SUM(E4:E10)-SUM(E11:E25) -> 208 | F26: =SUM(F4:F10)-SUM(F11:F25) -> 1600 | G26: =SUM(G4:G10)-SUM(G11:G25) -> 380 | H26: =SUM(H4:H10)-SUM(H11:H25) -> 176 | I26: =SUM(I4:I10)-SUM(I11:I25) -> 1618 | J26: =SUM(J4:J10)-SUM(J11:J25) -> 0 | K26: =SUM(K4:K10)-SUM(K11:K25) -> 1643 | ... Z26: =SUM(Z4:Z10)-SUM(Z11:Z25) -> 43
D28: =D26*0.3 -> 300 | E28: =+E26*0.35 -> 72.8 | F28: =+F26*0.28 -> 448 | G28: =+G26*0.34 -> 129.2 | H28: =+H26*0.38 -> 66.88 | I28: =+I26*0.54 -> 873.72 | J28: =+J26*0.6 -> 0 | K28: =+K26*0.79 -> 1297.97 | L28: =+L26*0.6 -> 1287 | M28: =+M26*0.66 -> 0 | N28: =+N26*0.64 -> 0 | O28: =+O26*0.53 -> 0 | P28: =+P26*2.08 -> 923.52 | Q28: =+Q26*1.58 -> 1145.5 | R28: =+R26*1.89 -> 1020.6 | S28: =+S26*1.7 -> 353.6 | T28: =+T26*2.18 -> 1090 | U28: =+U26*1.97 -> 600.85 | V28: =+V26*0.42 -> 1209.18 | W28: =+W26*0.3 -> 1415.4 | X28: =+X26*1.9-(161*0.11) -> 2188.19 | Y28: =+Y26*0.8 -> 224 | Z28: =+Z26*2 -> 86
L30: 0.03 | Q30: =1.65-1.58 -> 0.07 | Z30: =SUM(D28:Z28) -> 14732.41
L31: =+L30*1245 -> 37.35 | Q31: =+Q30*1125 -> 78.75 | W31: =368*0.01 -> 3.68
R35: =60000-25500 -> 34500

Sheet STOCK 23 a 29
D2: PANDERETA | I2: 18 HUECOS | P2: TECHO 12 | S2: TECHO 15 | V2: ARTESANAL | X2: SUPER KK | Y2: TIPO 4 | Z2: TECHO 08
B3: FECHA | C3: CLIENTE | D3: SIPAN | E3: CHALPON | F3: ZERAMIX | G3: CERAM | H3: FORTALEZA | I3: CERAM | J3: TORRE FUERTE | K3: LARK | L3: FORTALEZA | M3: CRUZ CHALPON | N3: TAISON | O3: SIPAN | P3: LARK | Q3: ITAL | R3: FORTALEZA | S3: ITAL | T3: LARK | U3: FORTALEZA | V3: BODOQUE | W3: PEQUEÑO | X3: CERAMICOS | Y3: FORTALEZA | Z3: CERAM
A4: INGRESO | D4: ='STOCK 16 a 22'!D26 -> 1000 | E4: ='STOCK 16 a 22'!E26 -> 208 | F4: ='STOCK 16 a 22'!F26 -> 1600 | G4: ='STOCK 16 a 22'!G26 -> 380 | H4: ='STOCK 16 a 22'!H26 -> 176 | I4: ='STOCK 16 a 22'!I26 -> 1618 | J4: ='STOCK 16 a 22'!J26 -> 0 | K4: ='STOCK 16 a 22'!K26 -> 1643 | ... Z4: ='STOCK 16 a 22'!Z26 -> 43
B5: 45467 | C5: M6I-893 | F5: 2500
B6: 45468 | C6: M6I-893 | S6: 500
B7: 45469 | C7: M6I-893 | O7: 3500
B8: 45470 | C8: M8B-893 | F8: 2000
B9: 45471 | C9: M8B-893 | Q9: 800 | S9: 500
A11: SALIDA | B11: 45467 | C11: VENTAS H&C | F11: 500 | K11: 250 | L11: =500+700 -> 1200 | P11: 12 | W11: =20+12 -> 32
B12: 45468 | C12: VENTAS H&C | S12: 204
B13: 45469 | C13: VENTAS H&C | D13: 500 | F13: 70
B14: 45470 | C14: VENTA JORDY | O14: 1500 | Q14: 400
B15: 45470 | C15: VENTAS H&C | V15: 30
B16: 45471 | C16: VENTAS H&C | Q16: 350
A26: SALDO | D26: =SUM(D4:D10)-SUM(D11:D25) -> 500 | E26: =SUM(E4:E10)-SUM(E11:E25) -> 208 | F26: =SUM(F4:F10)-SUM(F11:F25) -> 5530 | G26: =SUM(G4:G10)-SUM(G11:G25) -> 380 | H26: =SUM(H4:H10)-SUM(H11:H25) -> 176 | I26: =SUM(I4:I10)-SUM(I11:I25) -> 1618 | J26: =SUM(J4:J10)-SUM(J11:J25) -> 0 | K26: =SUM(K4:K10)-SUM(K11:K25) -> 1393 | ... Z26: =SUM(Z4:Z10)-SUM(Z11:Z25) -> 43
D28: =D26*0.3 -> 150 | E28: =+E26*0.35 -> 72.8 | F28: =+F26*0.28 -> 1548.4 | G28: =+G26*0.34 -> 129.2 | H28: =+H26*0.38 -> 66.88 | I28: =+I26*0.54 -> 873.72 | J28: =+J26*0.6 -> 0 | K28: =+K26*0.79 -> 1100.47 | L28: =+L26*0.6 -> 567 | M28: =+M26*0.66 -> 0 | N28: =+N26*0.64 -> 0 | O28: =+O26*0.5 -> 1000 | P28: =+P26*2.08 -> 898.56 | Q28: =+Q26*1.58 -> 1224.5 | R28: =+R26*1.89 -> 1020.6 | S28: =+S26*1.63 -> 1636.52 | T28: =+T26*2.18 -> 1090 | U28: =+U26*1.97 -> 600.85 | V28: =+V26*0.42 -> 1196.58 | W28: =+W26*0.3 -> 1405.8 | X28: =+X26*1.9-(161*0.11) -> 2188.19 | Y28: =+Y26*0.8 -> 224 | Z28: =+Z26*2 -> 86
S30: 0.07 | Z30: =SUM(D28:Z28) -> 17080.07
S31: =208*S30 -> 14.56
R35: =60000-25500 -> 34500

Sheet STOCK 30 a 06
D2: PANDERETA | I2: 18 HUECOS | P2: TECHO 12 | S2: TECHO 15 | V2: ARTESANAL | X2: SUPER KK | Y2: TIPO 4 | Z2: TECHO 08
B3: FECHA | C3: CLIENTE | D3: SIPAN | E3: CHALPON | F3: ZERAMIX | G3: CERAM | H3: FORTALEZA | I3: CERAM | J3: TORRE FUERTE | K3: LARK | L3: FORTALEZA | M3: CRUZ CHALPON | N3: TAISON | O3: SIPAN | P3: LARK | Q3: ITAL | R3: FORTALEZA | S3: ITAL | T3: LARK | U3: FORTALEZA | V3: BODOQUE | W3: PEQUEÑO | X3: CERAMICOS | Y3: FORTALEZA | Z3: CERAM
A4: INGRESO | D4: ='STOCK 23 a 29'!D26 -> 500 | E4: ='STOCK 23 a 29'!E26 -> 208 | F4: ='STOCK 23 a 29'!F26 -> 5530 | G4: ='STOCK 23 a 29'!G26 -> 380 | H4: ='STOCK 23 a 29'!H26 -> 176 | I4: ='STOCK 23 a 29'!I26 -> 1618 | J4: ='STOCK 23 a 29'!J26 -> 0 | K4: ='STOCK 23 a 29'!K26 -> 1393 | ... Z4: ='STOCK 23 a 29'!Z26 -> 43
B5: 45476 | C5: M8B-893 | E5: 1000
B6: 45477 | C6: M8B-893 | D6: 1000
B7: 45479 | C7: M8B-893 | V7: 3000
A11: SALIDA | B11: 45473 | C11: VENTAS H&C | L11: 30 | V11: 20
B12: 45474 | C12: VENTAS H&C | F12: 1000 | O12: 300 | S12: 250
B13: 45475 | C13: VENTAS H&C | O13: 500 | S13: 300 | W13: =150+30+200 -> 380
B14: 45476 | C14: VENTAS H&C | F14: 290 | S14: =200+20 -> 220 | V14: 2120 | W14: 60 | X14: 500
B15: 45477 | C15: VENTAS H&C | E15: =1124+84 -> 1208 | H15: 176 | O15: 400
B16: 45478 | C16: VENTAS H&C | L16: 500 | S16: 50
B17: 45479 | C17: VENTAS H&C | W17: =50+500 -> 550
A26: SALDO | D26: =SUM(D4:D10)-SUM(D11:D25) -> 1500 | E26: =SUM(E4:E10)-SUM(E11:E25) -> 0 | F26: =SUM(F4:F10)-SUM(F11:F25) -> 4240 | G26: =SUM(G4:G10)-SUM(G11:G25) -> 380 | H26: =SUM(H4:H10)-SUM(H11:H25) -> 0 | I26: =SUM(I4:I10)-SUM(I11:I25) -> 1618 | J26: =SUM(J4:J10)-SUM(J11:J25) -> 0 | K26: =SUM(K4:K10)-SUM(K11:K25) -> 1393 | ... Z26: =SUM(Z4:Z10)-SUM(Z11:Z25) -> 43
D28: =D26*0.3 -> 450 | E28: =+E26*0.3 -> 0 | F28: =+F26*0.28 -> 1187.2 | G28: =+G26*0.34 -> 129.2 | H28: =+H26*0.38 -> 0 | I28: =+I26*0.54 -> 873.72 | J28: =+J26*0.6 -> 0 | K28: =+K26*0.79 -> 1100.47 | L28: =+L26*0.6 -> 249 | M28: =+M26*0.66 -> 0 | N28: =+N26*0.64 -> 0 | O28: =+O26*0.5 -> 400 | P28: =+P26*2.08 -> 898.56 | Q28: =+Q26*1.58 -> 1224.5 | R28: =+R26*1.89 -> 1020.6 | S28: =+S26*1.63 -> 299.92 | T28: =+T26*2.18 -> 1090 | U28: =+U26*1.97 -> 600.85 | V28: =+V26*0.39+(709*0.03) -> 1467.78 | W28: =+W26*0.3 -> 1108.8 | X28: =+X26*1.9-(161*0.11) -> 1238.19 | Y28: =+Y26*0.8 -> 224 | Z28: =+Z26*2 -> 86
E30: =0.35-0.3 -> 0.05 | Z30: =SUM(D28:Z28) -> 13648.79
E31: =+E30*208+84*0.3 -> 35.6
R35: =60000-25500 -> 34500

Sheet STOCK  07 a 13
D2: PANDERETA | I2: 18 HUECOS | P2: TECHO 12 | S2: TECHO 15 | V2: ARTESANAL | X2: SUPER KK | Y2: TIPO 4 | Z2: TECHO 08
B3: FECHA | C3: CLIENTE | D3: SIPAN | E3: CHALPON | F3: ZERAMIX | G3: CERAM | H3: FORTALEZA | I3: CERAM | J3: TORRE FUERTE | K3: LARK | L3: FORTALEZA | M3: CRUZ CHALPON | N3: TAISON | O3: SIPAN | P3: LARK | Q3: ITAL | R3: FORTALEZA | S3: ITAL | T3: LARK | U3: FORTALEZA | V3: BODOQUE | W3: PEQUEÑO | X3: CERAMICOS | Y3: FORTALEZA | Z3: CERAM
A4: INGRESO | D4: ='STOCK 30 a 06'!D26 -> 1500 | E4: ='STOCK 30 a 06'!E26 -> 0 | F4: ='STOCK 30 a 06'!F26 -> 4240 | G4: ='STOCK 30 a 06'!G26 -> 380 | H4: ='STOCK 30 a 06'!H26 -> 0 | I4: ='STOCK 30 a 06'!I26 -> 1618 | J4: ='STOCK 30 a 06'!J26 -> 0 | K4: ='STOCK 30 a 06'!K26 -> 1393 | ... Z4: ='STOCK 30 a 06'!Z26 -> 43
B5: 45481 | C5: M8B-893 | K5: 3000
B6: 45484 | C6: M8B-893 | O6: 2500
B7: 45486 | C7: M6I-897 | S7: 1000
A11: SALIDA | B11: 45480 | C11: VENTAS H&C | S11: 15
B12: 45481 | C12: VENTA JORDY | D12: 1000 | F12: 1000
B13: 45482 | C13: VENTAS H&C | W13: 20
B14: 45483 | C14: VENTAS H&C | O14: =500+20 -> 520 | V14: 15
B15: 45484 | C15: VENTAS H&C | F15: 2000 | O15: 200 | X15: 40
B16: 45486 | C16: VENTAS H&C | D16: 500 | X16: =30+18 -> 48
A26: SALDO | D26: =SUM(D4:D10)-SUM(D11:D25) -> 0 | E26: =SUM(E4:E10)-SUM(E11:E25) -> 0 | F26: =SUM(F4:F10)-SUM(F11:F25) -> 1240 | G26: =SUM(G4:G10)-SUM(G11:G25) -> 380 | H26: =SUM(H4:H10)-SUM(H11:H25) -> 0 | I26: =SUM(I4:I10)-SUM(I11:I25) -> 1618 | J26: =SUM(J4:J10)-SUM(J11:J25) -> 0 | K26: =SUM(K4:K10)-SUM(K11:K25) -> 4393 | ... Z26: =SUM(Z4:Z10)-SUM(Z11:Z25) -> 43
D28: =D26*0.3 -> 0 | E28: =+E26*0.3 -> 0 | F28: =+F26*0.28 -> 347.2 | G28: =+G26*0.34 -> 129.2 | H28: =+H26*0.38 -> 0 | I28: =+I26*0.54 -> 873.72 | J28: =+J26*0.6 -> 0 | K28: =+K26*0.756 -> 3321.108 | L28: =+L26*0.6 -> 249 | M28: =+M26*0.66 -> 0 | N28: =+N26*0.64 -> 0 | O28: =+O26*0.5 -> 1290 | P28: =+P26*2.08 -> 898.56 | Q28: =+Q26*1.58 -> 1224.5 | R28: =+R26*1.89 -> 1020.6 | S28: =+S26*1.67-(169*0.04) -> 1945.47 | T28: =+T26*2.18 -> 1090 | U28: =+U26*1.97 -> 600.85 | V28: =+V26*0.39+(694*0.03) -> 1461.48 | W28: =+W26*0.3 -> 1102.8 | X28: =+X26*1.9-(161*0.11) -> 1070.99 | Y28: =+Y26*0.8 -> 224 | Z28: =+Z26*2 -> 86
K30: =2220+1100.47 -> 3320.47 | Z30: =SUM(D28:Z28) -> 16935.478
K31: =+K28-K30 -> 0.638

Sheet STOCK  14 a 20
D2: PANDERETA | I2: 18 HUECOS | P2: TECHO 12 | S2: TECHO 15 | V2: ARTESANAL | X2: SUPER KK | Y2: TIPO 4 | Z2: TECHO 08
B3: FECHA | C3: CLIENTE | D3: SIPAN | E3: CHALPON | F3: ZERAMIX | G3: CERAM | H3: FORTALEZA | I3: CERAM | J3: TORRE FUERTE | K3: LARK | L3: FORTALEZA | M3: CRUZ CHALPON | N3: TAISON | O3: SIPAN | P3: LARK | Q3: ITAL | R3: FORTALEZA | S3: ITAL | T3: LARK | U3: FORTALEZA | V3: BODOQUE | W3: PEQUEÑO | X3: CERAMICOS | Y3: FORTALEZA | Z3: CERAM
A4: INGRESO | D4: ='STOCK 07 a 13'!D26 -> 0 | E4: ='STOCK 07 a 13'!E26 -> 0 | F4: ='STOCK 07 a 13'!F26 -> 1240 | G4: ='STOCK 07 a 13'!G26 -> 380 | H4: ='STOCK 07 a 13'!H26 -> 0 | I4: ='STOCK 07 a 13'!I26 -> 1618 | J4: ='STOCK 07 a 13'!J26 -> 0 | K4: ='STOCK 07 a 13'!K26 -> 4393 | ... Z4: ='STOCK 07 a 13'!Z26 -> 43
B5: 45489 | C5: M8B-893 | D5: 2000
A11: SALIDA | B11: 45488 | C11: VENTAS H&C | O11: =1000+60 -> 1060 | Q11: 340 | S11: 100 | W11: 1000
B12: 45489 | C12: VENTAS H&C | G12: 50 | U12: 250 | W12: =8+15 -> 23
B13: 45490 | C13: VENTAS H&C | D13: 50 | W13: =15+200 -> 215
B14: 45491 | C14: VENTAS H&C | I14: 500
B15: 45492 | C15: VENTAS H&C | O15: 1000
B16: 45492 | C16: VENTA JORDY | K16: 2000
B17: 45493 | C17: VENTAS H&C | K17: 50 | W17: 210
A26: SALDO | D26: =SUM(D4:D10)-SUM(D11:D25) -> 1950 | E26: =SUM(E4:E10)-SUM(E11:E25) -> 0 | F26: =SUM(F4:F10)-SUM(F11:F25) -> 1240 | G26: =SUM(G4:G10)-SUM(G11:G25) -> 330 | H26: =SUM(H4:H10)-SUM(H11:H25) -> 0 | I26: =SUM(I4:I10)-SUM(I11:I25) -> 1118 | J26: =SUM(J4:J10)-SUM(J11:J25) -> 0 | K26: =SUM(K4:K10)-SUM(K11:K25) -> 2343 | ... Z26: =SUM(Z4:Z10)-SUM(Z11:Z25) -> 43
D28: =D26*0.3 -> 585 | E28: =+E26*0.3 -> 0 | F28: =+F26*0.28 -> 347.2 | G28: =+G26*0.34 -> 112.2 | H28: =+H26*0.38 -> 0 | I28: =+I26*0.54 -> 603.72 | J28: =+J26*0.6 -> 0 | K28: =+K26*0.756 -> 1771.308 | L28: =+L26*0.6 -> 249 | M28: =+M26*0.66 -> 0 | N28: =+N26*0.64 -> 0 | O28: =+O26*0.5 -> 260 | P28: =+P26*2.08 -> 898.56 | Q28: =+Q26*1.58 -> 687.3 | R28: =+R26*1.89 -> 1020.6 | S28: =+S26*1.67-(69*0.04) -> 1782.47 | T28: =+T26*2.18 -> 1090 | U28: =+U26*1.97 -> 108.35 | V28: =+V26*0.39+(694*0.03) -> 1461.48 | W28: =+W26*0.3 -> 668.4 | X28: =+X26*1.9-(161*0.11) -> 1070.99 | Y28: =+Y26*0.8 -> 224 | Z28: =+Z26*2 -> 86
Z30: =SUM(D28:Z28) -> 13026.578

Sheet STOCK  21 a 27
D2: PANDERETA | I2: 18 HUECOS | P2: TECHO 12 | S2: TECHO 15 | V2: ARTESANAL | X2: SUPER KK | Y2: TIPO 4 | Z2: TECHO 08
B3: FECHA | C3: CLIENTE | D3: SIPAN | E3: CHALPON | F3: ZERAMIX | G3: CERAM | H3: FORTALEZA | I3: CERAM | J3: TORRE FUERTE | K3: LARK | L3: FORTALEZA | M3: CRUZ CHALPON | N3: TAISON | O3: SIPAN | P3: LARK | Q3: ITAL | R3: FORTALEZA | S3: ITAL | T3: LARK | U3: FORTALEZA | V3: BODOQUE | W3: PEQUEÑO | X3: CERAMICOS | Y3: FORTALEZA | Z3: CERAM
A4: INGRESO | D4: ='STOCK 14 a 20'!D26 -> 1950 | E4: ='STOCK 14 a 20'!E26 -> 0 | F4: ='STOCK 14 a 20'!F26 -> 1240 | G4: ='STOCK 14 a 20'!G26 -> 330 | H4: ='STOCK 14 a 20'!H26 -> 0 | I4: ='STOCK 14 a 20'!I26 -> 1118 | J4: ='STOCK 14 a 20'!J26 -> 0 | K4: ='STOCK 14 a 20'!K26 -> 2343 | ... Z4: ='STOCK 14 a 20'!Z26 -> 43
B5: 45468 | C5: RAMOS | L5: 2000
B6: 45496 | C6: M6I-897 | Q6: 900 | S6: 300
A11: SALIDA | B11: 45493 | C11: VENTAS H&C | V11: 20
B12: 45494 | C12: VENTAS H&C | D12: 150
B13: 45495 | C13: VENTAS H&C | D13: 200 | I13: 250 | O13: 500 | Q13: 500 | V13: 500
B14: 45496 | C14: VENTAS H&C | G14: 50 | V14: 20 | W14: 100
A26: SALDO | D26: =SUM(D4:D10)-SUM(D11:D25) -> 1600 | E26: =SUM(E4:E10)-SUM(E11:E25) -> 0 | F26: =SUM(F4:F10)-SUM(F11:F25) -> 1240 | G26: =SUM(G4:G10)-SUM(G11:G25) -> 280 | H26: =SUM(H4:H10)-SUM(H11:H25) -> 0 | I26: =SUM(I4:I10)-SUM(I11:I25) -> 868 | J26: =SUM(J4:J10)-SUM(J11:J25) -> 0 | K26: =SUM(K4:K10)-SUM(K11:K25) -> 2343 | ... Z26: =SUM(Z4:Z10)-SUM(Z11:Z25) -> 43
D28: =D26*0.3 -> 480 | E28: =+E26*0.3 -> 0 | F28: =+F26*0.28 -> 347.2 | G28: =+G26*0.34 -> 95.2 | H28: =+H26*0.38 -> 0 | I28: =+I26*0.54 -> 468.72 | J28: =+J26*0.6 -> 0 | K28: =+K26*0.756 -> 1771.308 | L28: =+L26*0.59 -> 1424.85 | M28: =+M26*0.66 -> 0 | N28: =+N26*0.64 -> 0 | O28: =+O26*0.5 -> 10 | P28: =+P26*2.08 -> 898.56 | Q28: =+Q26*1.6 -> 1336 | R28: =+R26*1.89 -> 1020.6 | S28: =+S26*1.67-(69*0.04) -> 2283.47 | T28: =+T26*2.18 -> 1090 | U28: =+U26*1.97 -> 108.35 | V28: =+V26*0.39+(154*0.03) -> 1234.68 | W28: =+W26*0.3 -> 638.4 | X28: =+X26*1.9-(161*0.11) -> 1070.99 | Y28: =+Y26*0.8 -> 224 | Z28: =+Z26*2 -> 86
Z30: =SUM(D28:Z28) -> 14588.328
C31: STOCK REAL | D31: 1681 | F31: 68 | G31: 275 | H31: 101 | K31: 2201 | L31: 2385 | O31: 0 | P31: 427 | Q31: 870 | R31: 540 | S31: =870+500 -> 1370 | T31: 500 | U31: 52 | V31: 3000 | W31: 2000 | X31: 524 | Y31: 0 | Z31: 0
C32: DIFERENCIA | D32: =D31-D26 -> 81 | E32: =E31-E26 -> 0 | F32: =F31-F26 -> -1172 | G32: =G31-G26 -> -5 | H32: =H31-H26 -> 101 | I32: =I31-I26 -> -868 | J32: =J31-J26 -> 0 | K32: =K31-K26 -> -142 | ... Z32: =Z31-Z26 -> -43
C33: P.UNITARIO | D33: 0.3 | F33: 0.28 | G33: 0.34 | H33: 0.35 | I33: 0.54 | K33: 0.756 | L33: 0.59 | O33: 0.5 | P33: 2.08 | Q33: 1.6 | S33: 1.63 | T33: 2.18 | U33: 1.97 | V33: 0.42 | W33: 0.3 | X33: 1.79 | Y33: 0.8 | Z33: 2
C34: TOTAL S/. | D34: =D32*D33 -> 24.3 | E34: =E32*E33 -> 0 | F34: =F32*F33 -> -328.16 | G34: =G32*G33 -> -1.7 | H34: =H32*H33 -> 35.35 | I34: =I32*I33 -> -468.72 | J34: =J32*J33 -> 0 | K34: =K32*K33 -> -107.352 | ... Z34: =Z32*Z33 -> -86
Z35: =SUM(D34:Z34) -> -1333.452
Z37: =-Z30-Z35 -> -13254.876

Sheet STOCK  23 a 27
D2: PANDERETA | I2: 18 HUECOS | P2: TECHO 12 | S2: TECHO 15 | V2: ARTESANAL | X2: SUPER KK | Y2: TIPO 4 | Z2: TECHO 08
B3: FECHA | C3: CLIENTE | D3: SIPAN | E3: CHALPON | F3: ZERAMIX | G3: CERAM | H3: FORTALEZA | I3: CERAM | J3: TORRE FUERTE | K3: LARK | L3: FORTALEZA | M3: CRUZ CHALPON | N3: TAISON | O3: SIPAN | P3: LARK | Q3: ITAL | R3: FORTALEZA | S3: ITAL | T3: LARK | U3: FORTALEZA | V3: BODOQUE | W3: PEQUEÑO | X3: CERAMICOS | Y3: FORTALEZA | Z3: CERAM
A4: INGRESO | D4: ='STOCK 21 a 27'!D31 -> 1681 | E4: ='STOCK 21 a 27'!E31 -> 0 | F4: ='STOCK 21 a 27'!F31 -> 68 | G4: ='STOCK 21 a 27'!G31 -> 275 | H4: ='STOCK 21 a 27'!H31 -> 101 | I4: ='STOCK 21 a 27'!I31 -> 0 | J4: ='STOCK 21 a 27'!J31 -> 0 | K4: ='STOCK 21 a 27'!K31 -> 2201 | ... Z4: ='STOCK 21 a 27'!Z31 -> 0
B5: 45500 | C5: M6I-897 | S5: 1000
A11: SALIDA | B11: 45496 | C11: VENTAS H&C | G11: 150 | V11: 300 | W11: 200
B12: 45497 | C12: VENTAS H&C | D12: 300 | V12: 100
B13: 45498 | C13: VENTAS H&C | D13: 500 | S13: 500 | W13: 30
B14: 45499 | C14: VENTAS H&C | D14: 452 | S14: 650 | W14: =50+50 -> 100
B15: 45500 | C15: VENTAS H&C | D15: 350
A26: SALDO | D26: =SUM(D4:D10)-SUM(D11:D25) -> 79 | E26: =SUM(E4:E10)-SUM(E11:E25) -> 0 | F26: =SUM(F4:F10)-SUM(F11:F25) -> 68 | G26: =SUM(G4:G10)-SUM(G11:G25) -> 125 | H26: =SUM(H4:H10)-SUM(H11:H25) -> 101 | I26: =SUM(I4:I10)-SUM(I11:I25) -> 0 | J26: =SUM(J4:J10)-SUM(J11:J25) -> 0 | K26: =SUM(K4:K10)-SUM(K11:K25) -> 2201 | ... Z26: =SUM(Z4:Z10)-SUM(Z11:Z25) -> 0
D28: =D26*0.3 -> 23.7 | E28: =+E26*0.3 -> 0 | F28: =+F26*0.28 -> 19.04 | G28: =+G26*0.34 -> 42.5 | H28: =+H26*0.35 -> 35.35 | I28: =+I26*0.54 -> 0 | J28: =+J26*0.6 -> 0 | K28: =+K26*0.756 -> 1663.956 | L28: =+L26*0.59 -> 1407.15 | M28: =+M26*0.66 -> 0 | N28: =+N26*0.64 -> 0 | O28: =+O26*0.5 -> 0 | P28: =+P26*2.08 -> 888.16 | Q28: =+Q26*1.6 -> 1392 | R28: =+R26*1.89 -> 1020.6 | S28: =+S26*1.67 -> 2037.4 | T28: =+T26*2.18 -> 1090 | U28: =+U26*1.97 -> 102.44 | V28: =+V26*0.39 -> 1014 | W28: =+W26*0.3 -> 501 | X28: =+X26*1.9-(112*0.11) -> 983.28 | Y28: =+Y26*0.8 -> 0 | Z28: =+Z26*2 -> 0
Z30: =SUM(D28:Z28) -> 12220.576

Sheet STOCK  28 a 03
D2: PANDERETA | I2: 18 HUECOS | P2: TECHO 12 | S2: TECHO 15 | V2: ARTESANAL | X2: SUPER KK | Y2: TIPO 4 | Z2: TECHO 08
B3: FECHA | C3: CLIENTE | D3: SIPAN | E3: CHALPON | F3: ZERAMIX | G3: CERAM | H3: FORTALEZA | I3: CERAM | J3: TORRE FUERTE | K3: LARK | L3: FORTALEZA | M3: CRUZ CHALPON | N3: TAISON | O3: SIPAN | P3: LARK | Q3: ITAL | R3: FORTALEZA | S3: ITAL | T3: LARK | U3: FORTALEZA | V3: BODOQUE | W3: PEQUEÑO | X3: CERAMICOS | Y3: FORTALEZA | Z3: CERAM
A4: INGRESO | D4: ='STOCK 23 a 27'!D26 -> 79 | E4: ='STOCK 23 a 27'!E26 -> 0 | F4: ='STOCK 23 a 27'!F26 -> 68 | G4: ='STOCK 23 a 27'!G26 -> 125 | H4: ='STOCK 23 a 27'!H26 -> 101 | I4: ='STOCK 23 a 27'!I26 -> 0 | J4: ='STOCK 23 a 27'!J26 -> 0 | K4: ='STOCK 23 a 27'!K26 -> 2201 | ... Z4: ='STOCK 23 a 27'!Z26 -> 0
B5: 45505 | C5: M6I-897 | O5: 3500
B6: 45506 | C6: M6I-897 | D6: 4500
A11: SALIDA | B11: 45502 | C11: VENTAS H&C | L11: 60 | Q11: 570 | V11: 120 | W11: =50+150 -> 200
B12: 45503 | C12: VENTAS H&C | L12: 130
B13: 45504 | C13: VENTAS H&C | H13: 60 | L13: 2000 | S13: 300 | W13: 20
B14: 45505 | C14: VENTAS H&C | F14: 59 | H14: 41 | P14: 420 | V14: 300
B15: 45506 | C15: VENTAS H&C | Q15: 200
B16: 45507 | C16: VENTAS H&C | Q16: 30 | V16: 500
A26: SALDO | D26: =SUM(D4:D10)-SUM(D11:D25) -> 4579 | E26: =SUM(E4:E10)-SUM(E11:E25) -> 0 | F26: =SUM(F4:F10)-SUM(F11:F25) -> 9 | G26: =SUM(G4:G10)-SUM(G11:G25) -> 125 | H26: =SUM(H4:H10)-SUM(H11:H25) -> 0 | I26: =SUM(I4:I10)-SUM(I11:I25) -> 0 | J26: =SUM(J4:J10)-SUM(J11:J25) -> 0 | K26: =SUM(K4:K10)-SUM(K11:K25) -> 2201 | ... Z26: =SUM(Z4:Z10)-SUM(Z11:Z25) -> 0
D28: =D26*0.3 -> 1373.7 | E28: =+E26*0.3 -> 0 | F28: =+F26*0.28 -> 2.52 | G28: =+G26*0.34 -> 42.5 | H28: =+H26*0.35 -> 0 | I28: =+I26*0.54 -> 0 | J28: =+J26*0.6 -> 0 | K28: =+K26*0.756 -> 1663.956 | L28: =+L26*0.59 -> 115.05 | M28: =+M26*0.66 -> 0 | N28: =+N26*0.64 -> 0 | O28: =+O26*0.5 -> 1750 | P28: =+P26*2.08 -> 14.56 | Q28: =+Q26*1.6 -> 112 | R28: =+R26*1.89 -> 1020.6 | S28: =+S26*1.67 -> 1536.4 | T28: =+T26*2.18 -> 1090 | U28: =+U26*1.97 -> 102.44 | V28: =+V26*0.39 -> 655.2 | W28: =+W26*0.3 -> 435 | X28: =+X26*1.9-(112*0.11) -> 983.28 | Y28: =+Y26*0.8 -> 0 | Z28: =+Z26*2 -> 0
Z30: =SUM(D28:Z28) -> 10897.206

Sheet STOCK  04 a 10
D2: PANDERETA | I2: 18 HUECOS | P2: TECHO 12 | S2: TECHO 15 | V2: ARTESANAL | X2: SUPER KK | Y2: TIPO 4 | Z2: TECHO 08
B3: FECHA | C3: CLIENTE | D3: SIPAN | E3: CHALPON | F3: ZERAMIX | G3: CERAM | H3: FORTALEZA | I3: CERAM | J3: TORRE FUERTE | K3: LARK | L3: FORTALEZA | M3: CRUZ CHALPON | N3: TAISON | O3: SIPAN | P3: LARK | Q3: ITAL | R3: FORTALEZA | S3: ITAL | T3: LARK | U3: FORTALEZA | V3: BODOQUE | W3: PEQUEÑO | X3: CERAMICOS | Y3: FORTALEZA | Z3: CERAM
A4: INGRESO | D4: ='STOCK 28 a 03'!D26 -> 4579 | E4: ='STOCK 28 a 03'!E26 -> 0 | F4: ='STOCK 28 a 03'!F26 -> 9 | G4: ='STOCK 28 a 03'!G26 -> 125 | H4: ='STOCK 28 a 03'!H26 -> 0 | I4: ='STOCK 28 a 03'!I26 -> 0 | J4: ='STOCK 28 a 03'!J26 -> 0 | K4: ='STOCK 28 a 03'!K26 -> 2201 | ... Z4: ='STOCK 28 a 03'!Z26 -> 0
B5: 45511 | C5: M8B-893 | D5: 3500
B6: 45511 | C6: M6I-897 | Q6: 1200
B7: 45513 | C7: M6I-897 | L7: 3500
A11: SALIDA | B11: 45508 | C11: VENTAS H&C | L11: 70 | X11: 85
B12: 45509 | C12: VENTAS H&C | D12: 500 | Q12: 70 | X12: 150
B13: 45510 | C13: VENTAS H&C | O13: 100
B14: 45512 | C14: VENTAS H&C | O14: 2000 | W14: 150
B15: 45513 | C15: VENTAS H&C | D15: 500 | L15: 500
A26: SALDO | D26: =SUM(D4:D10)-SUM(D11:D25) -> 7079 | E26: =SUM(E4:E10)-SUM(E11:E25) -> 0 | F26: =SUM(F4:F10)-SUM(F11:F25) -> 9 | G26: =SUM(G4:G10)-SUM(G11:G25) -> 125 | H26: =SUM(H4:H10)-SUM(H11:H25) -> 0 | I26: =SUM(I4:I10)-SUM(I11:I25) -> 0 | J26: =SUM(J4:J10)-SUM(J11:J25) -> 0 | K26: =SUM(K4:K10)-SUM(K11:K25) -> 2201 | ... Z26: =SUM(Z4:Z10)-SUM(Z11:Z25) -> 0
D28: =D26*0.3 -> 2123.7 | E28: =+E26*0.3 -> 0 | F28: =+F26*0.28 -> 2.52 | G28: =+G26*0.34 -> 42.5 | H28: =+H26*0.35 -> 0 | I28: =+I26*0.54 -> 0 | J28: =+J26*0.6 -> 0 | K28: =+K26*0.756 -> 1663.956 | L28: =+L26*0.59 -> 1843.75 | M28: =+M26*0.66 -> 0 | N28: =+N26*0.64 -> 0 | O28: =+O26*0.5 -> 700 | P28: =+P26*2.08 -> 14.56 | Q28: =+Q26*1.6 -> 1920 | R28: =+R26*1.89 -> 1020.6 | S28: =+S26*1.67 -> 1536.4 | T28: =+T26*2.18 -> 1090 | U28: =+U26*1.97 -> 102.44 | V28: =+V26*0.39 -> 655.2 | W28: =+W26*0.3 -> 390 | X28: =+X26*1.9 -> 549.1 | Y28: =+Y26*0.8 -> 0 | Z28: =+Z26*2 -> 0
Z30: =SUM(D28:Z28) -> 13654.726

Sheet STOCK  11 a 17
D2: PANDERETA | I2: 18 HUECOS | P2: TECHO 12 | S2: TECHO 15 | V2: ARTESANAL | X2: SUPER KK | Y2: TIPO 4 | Z2: TECHO 08
B3: FECHA | C3: CLIENTE | D3: SIPAN | E3: CHALPON | F3: ZERAMIX | G3: CERAM | H3: FORTALEZA | I3: CERAM | J3: TORRE FUERTE | K3: LARK | L3: FORTALEZA | M3: CRUZ CHALPON | N3: TAISON | O3: SIPAN | P3: LARK | Q3: ITAL | R3: FORTALEZA | S3: ITAL | T3: LARK | U3: FORTALEZA | V3: BODOQUE | W3: PEQUEÑO | X3: CERAMICOS | Y3: FORTALEZA | Z3: CERAM
A4: INGRESO | D4: ='STOCK 04 a 10'!D26 -> 7079 | E4: ='STOCK 04 a 10'!E26 -> 0 | F4: ='STOCK 04 a 10'!F26 -> 9 | G4: ='STOCK 04 a 10'!G26 -> 125 | H4: ='STOCK 04 a 10'!H26 -> 0 | I4: ='STOCK 04 a 10'!I26 -> 0 | J4: ='STOCK 04 a 10'!J26 -> 0 | K4: ='STOCK 04 a 10'!K26 -> 2201 | ... Z4: ='STOCK 04 a 10'!Z26 -> 0
B5: 45516 | C5: M6I-897 | W5: 2500
B6: 45518 | C6: M6I-897 | D6: 500
B7: 45518 | C7: M8B-893 | O7: 2000
B8: 45519 | C8: M6I-897 | O8: 3500
B9: 45519 | C9: M8B-893 | D9: 6000
A11: SALIDA | B11: 45516 | C11: VENTAS H&C | D11: 1500 | W11: 500
B12: 45517 | C12: VENTAS H&C | O12: =500+250+200 -> 950 | X12: 70
B13: 45518 | C13: VENTAS H&C | D13: =500+500 -> 1000
B14: 45519 | C14: VENTAS H&C | D14: 1500 | L14: 1100 | O14: =500+2000+1000 -> 3500 | Q14: 500 | T14: 300
B15: 45520 | C15: VENTAS H&C | D15: 1000 | S15: 230 | V15: 500
B16: 45521 | C16: VENTAS H&C | O16: 150
A23: SALDO | D23: =SUM(D4:D10)-SUM(D11:D22) -> 8579 | E23: =SUM(E4:E10)-SUM(E11:E22) -> 0 | F23: =SUM(F4:F10)-SUM(F11:F22) -> 9 | G23: =SUM(G4:G10)-SUM(G11:G22) -> 125 | H23: =SUM(H4:H10)-SUM(H11:H22) -> 0 | I23: =SUM(I4:I10)-SUM(I11:I22) -> 0 | J23: =SUM(J4:J10)-SUM(J11:J22) -> 0 | K23: =SUM(K4:K10)-SUM(K11:K22) -> 2201 | ... Z23: =SUM(Z4:Z10)-SUM(Z11:Z22) -> 0
D25: =D23*0.3 -> 2573.7 | E25: =+E23*0.3 -> 0 | F25: =+F23*0.28 -> 2.52 | G25: =+G23*0.34 -> 42.5 | H25: =+H23*0.35 -> 0 | I25: =+I23*0.54 -> 0 | J25: =+J23*0.6 -> 0 | K25: =+K23*0.756 -> 1663.956 | L25: =+L23*0.59 -> 1194.75 | M25: =+M23*0.66 -> 0 | N25: =+N23*0.64 -> 0 | O25: =+O23*0.5 -> 1150 | P25: =+P23*2.08 -> 14.56 | Q25: =+Q23*1.6 -> 1120 | R25: =+R23*1.89 -> 1020.6 | S25: =+S23*1.67 -> 1152.3 | T25: =+T23*2.18 -> 436 | U25: =+U23*1.97 -> 102.44 | V25: =+V23*0.39 -> 460.2 | W25: =+W23*0.29+(800*0.01) -> 965 | X25: =+X23*1.9 -> 416.1 | Y25: =+Y23*0.8 -> 0 | Z25: =+Z23*2 -> 0
Z27: =SUM(D25:Z25) -> 12314.626

Sheet STOCK  18 a 24 
D2: PANDERETA | I2: 18 HUECOS | P2: TECHO 12 | S2: TECHO 15 | V2: ARTESANAL | X2: SUPER KK | Y2: TIPO 4 | Z2: TECHO 08
B3: FECHA | C3: CLIENTE | D3: SIPAN | E3: CHALPON | F3: ZERAMIX | G3: CERAM | H3: FORTALEZA | I3: CERAM | J3: TORRE FUERTE | K3: LARK | L3: FORTALEZA | M3: CRUZ CHALPON | N3: TAISON | O3: SIPAN | P3: LARK | Q3: ITAL | R3: FORTALEZA | S3: ITAL | T3: LARK | U3: FORTALEZA | V3: BODOQUE | W3: PEQUEÑO | X3: CERAMICOS | Y3: FORTALEZA | Z3: CERAM
A4: INGRESO | D4: ='STOCK 11 a 17'!D23 -> 8579 | E4: ='STOCK 11 a 17'!E23 -> 0 | F4: ='STOCK 11 a 17'!F23 -> 9 | G4: ='STOCK 11 a 17'!G23 -> 125 | H4: ='STOCK 11 a 17'!H23 -> 0 | I4: ='STOCK 11 a 17'!I23 -> 0 | J4: ='STOCK 11 a 17'!J23 -> 0 | K4: ='STOCK 11 a 17'!K23 -> 2201 | ... Z4: ='STOCK 11 a 17'!Z23 -> 0
B5: 45525 | C5: M6I-897 | V5: 3000
B6: 45526 | C6: M8B-893 | S6: 1000
B7: 45528 | C7: M8B-893 | K7: 1500
B8: 45528 | C8: M6I-897 | O8: 3500
A11: SALIDA | B11: 45523 | C11: VENTAS H&C | O11: 200 | S11: 443 | V11: 500
B12: 45524 | C12: VENTAS H&C | D12: 1000 | K12: 1400 | T12: 197 | V12: 250
B13: 45525 | C13: VENTA JORDY | D13: 4000
B14: 45525 | C14: VENTAS H&C | Q14: 400
B15: 45526 | C15: VENTAS H&C | W15: =500+200 -> 700
B16: 45527 | C16: VENTA JORDY
B17: 45527 | C17: VENTAS H&C | L17: 300
B18: 45528 | C18: VENTAS H&C | O18: 500 | V18: 50
A23: SALDO | D23: =SUM(D4:D10)-SUM(D11:D22) -> 3579 | E23: =SUM(E4:E10)-SUM(E11:E22) -> 0 | F23: =SUM(F4:F10)-SUM(F11:F22) -> 9 | G23: =SUM(G4:G10)-SUM(G11:G22) -> 125 | H23: =SUM(H4:H10)-SUM(H11:H22) -> 0 | I23: =SUM(I4:I10)-SUM(I11:I22) -> 0 | J23: =SUM(J4:J10)-SUM(J11:J22) -> 0 | K23: =SUM(K4:K10)-SUM(K11:K22) -> 2301 | ... Z23: =SUM(Z4:Z10)-SUM(Z11:Z22) -> 0
D25: =D23*0.3 -> 1073.7 | E25: =+E23*0.3 -> 0 | F25: =+F23*0.28 -> 2.52 | G25: =+G23*0.34 -> 42.5 | H25: =+H23*0.35 -> 0 | I25: =+I23*0.54 -> 0 | J25: =+J23*0.6 -> 0 | K25: =+K23*0.756 -> 1739.556 | L25: =+L23*0.59 -> 1017.75 | M25: =+M23*0.66 -> 0 | N25: =+N23*0.64 -> 0 | O25: =+O23*0.5 -> 2550 | P25: =+P23*2.08 -> 14.56 | Q25: =+Q23*1.6 -> 480 | R25: =+R23*1.89 -> 1020.6 | S25: =+S23*1.73-(247*0.06) -> 2142.49 | T25: =+T23*2.18 -> 6.54 | U25: =+U23*1.97 -> 102.44 | V25: =+V23*0.38+(380*0.01) -> 1288.2 | W25: =+W23*0.29+(100*0.01) -> 755 | X25: =+X23*1.9 -> 416.1 | Y25: =+Y23*0.8 -> 0 | Z25: =+Z23*2 -> 0
Z27: =SUM(D25:Z25) -> 12651.956
T31: 1680

Sheet STOCK  25 a 31
D2: PANDERETA | I2: 18 HUECOS | P2: TECHO 12 | S2: TECHO 15 | V2: ARTESANAL | X2: SUPER KK | Y2: TIPO 4 | Z2: TECHO 08
B3: FECHA | C3: CLIENTE | D3: SIPAN | E3: CHALPON | F3: ZERAMIX | G3: CERAM | H3: FORTALEZA | I3: CERAM | J3: TORRE FUERTE | K3: LARK | L3: FORTALEZA | M3: CRUZ CHALPON | N3: TAISON | O3: SIPAN | P3: LARK | Q3: ITAL | R3: FORTALEZA | S3: ITAL | T3: LARK | U3: FORTALEZA | V3: BODOQUE | W3: PEQUEÑO | X3: CERAMICOS | Y3: FORTALEZA | Z3: CERAM
A4: INGRESO | D4: ='STOCK 18 a 24 '!D23 -> 3579 | E4: ='STOCK 18 a 24 '!E23 -> 0 | F4: ='STOCK 18 a 24 '!F23 -> 9 | G4: ='STOCK 18 a 24 '!G23 -> 125 | H4: ='STOCK 18 a 24 '!H23 -> 0 | I4: ='STOCK 18 a 24 '!I23 -> 0 | J4: ='STOCK 18 a 24 '!J23 -> 0 | K4: ='STOCK 18 a 24 '!K23 -> 2301 | ... Z4: ='STOCK 18 a 24 '!Z23 -> 0
B5: 45525 | C5: COLEGIO | D5: 1000
B6: 45530 | C6: M6I-897 | Q6: 500
B7: 45531 | C7: M6I-897 | J7: 2500
B8: 45531 | C8: M8B-893 | J8: 2500
B9: 45533 | C9: M6I-897 | G9: 6000
B10: 45535 | C10: M6I-897 | G10: 6000
A12: SALIDA | B12: 45529 | C12: VENTAS H&C | W12: 50
B13: 45531 | C13: VENTAS H&C | D13: 1000
B14: 45532 | C14: VENTAS H&C | D14: 70 | U14: 30
B15: 45533 | C15: VENTAS H&C | V15: 300
A24: SALDO | D24: =SUM(D4:D11)-SUM(D12:D23) -> 3509 | E24: =SUM(E4:E11)-SUM(E12:E23) -> 0 | F24: =SUM(F4:F11)-SUM(F12:F23) -> 9 | G24: =SUM(G4:G11)-SUM(G12:G23) -> 12125 | H24: =SUM(H4:H11)-SUM(H12:H23) -> 0 | I24: =SUM(I4:I11)-SUM(I12:I23) -> 0 | J24: =SUM(J4:J11)-SUM(J12:J23) -> 5000 | K24: =SUM(K4:K11)-SUM(K12:K23) -> 2301 | ... Z24: =SUM(Z4:Z11)-SUM(Z12:Z23) -> 0
D26: =D24*0.3 -> 1052.7 | E26: =+E24*0.3 -> 0 | F26: =+F24*0.28 -> 2.52 | G26: =+G24*0.3+(125*0.04) -> 3642.5 | H26: =+H24*0.35 -> 0 | I26: =+I24*0.54 -> 0 | J26: =+J24*0.51 -> 2550 | K26: =+K24*0.756 -> 1739.556 | L26: =+L24*0.59 -> 1017.75 | M26: =+M24*0.66 -> 0 | N26: =+N24*0.64 -> 0 | O26: =+O24*0.5 -> 2550 | P26: =+P24*2.08 -> 14.56 | Q26: =+Q24*1.66-(300*0.06) -> 1310 | R26: =+R24*1.89 -> 1020.6 | S26: =+S24*1.73-(247*0.06) -> 2142.49 | T26: =+T24*2.18 -> 6.54 | U26: =+U24*1.97 -> 43.34 | V26: =+V24*0.38+(80*0.01) -> 1171.2 | W26: =+W24*0.29+(50*0.01) -> 740 | X26: =+X24*1.9 -> 416.1 | Y26: =+Y24*0.8 -> 0 | Z26: =+Z24*2 -> 0
Z28: =SUM(D26:Z26) -> 19419.856
L29: =20101+11592 -> 31693
L30: 891.5
L32: =L29/L30 -> 35.550196 | T32: 1680
L34: =+L30*L32 -> 31693

Sheet STOCK  01 a 07
D2: PANDERETA | I2: 18 HUECOS | P2: TECHO 12 | S2: TECHO 15 | W2: ARTESANAL | Y2: SUPER KK | Z2: TIPO 4 | AA2: TECHO 08
B3: FECHA | C3: CLIENTE | D3: SIPAN | E3: CHALPON | F3: ZERAMIX | G3: CERAM | H3: FORTALEZA | I3: CERAM | J3: TORRE FUERTE | K3: LARK | L3: FORTALEZA | M3: CRUZ CHALPON | N3: TAISON | O3: SIPAN | P3: LARK | Q3: ITAL | R3: FORTALEZA | S3: ITAL | T3: GALCA | U3: LARK | V3: FORTALEZA | W3: BODOQUE | X3: PEQUEÑO | Y3: CERAMICOS | Z3: FORTALEZA | AA3: CERAM
A4: INGRESO | D4: ='STOCK 25 a 31'!D24 -> 3509 | E4: ='STOCK 25 a 31'!E24 -> 0 | F4: ='STOCK 25 a 31'!F24 -> 9 | G4: ='STOCK 25 a 31'!G24 -> 12125 | H4: ='STOCK 25 a 31'!H24 -> 0 | I4: ='STOCK 25 a 31'!I24 -> 0 | J4: ='STOCK 25 a 31'!J24 -> 5000 | K4: ='STOCK 25 a 31'!K24 -> 2301 | ... S4: ='STOCK 25 a 31'!S24 -> 1247 | U4: ='STOCK 25 a 31'!T24 -> 3 | V4: ='STOCK 25 a 31'!U24 -> 22 | W4: ='STOCK 25 a 31'!V24 -> 3080 | X4: ='STOCK 25 a 31'!W24 -> 2550 | Y4: ='STOCK 25 a 31'!X24 -> 219 | Z4: ='STOCK 25 a 31'!Y24 -> 0 | AA4: ='STOCK 25 a 31'!Z24 -> 0
B5: 45539 | C5: M6I-897 | G5: 2000
B6: 45541 | C6: M8B-893 | O6: 3000
B7: 45542 | C7: M6I-897 | T7: 620
A12: SALIDA | B12: 45536 | C12: VENTAS H&C | W12: =70+8 -> 78
B13: 45537 | C13: VENTAS H&C | D13: 3000 | G13: 3000 | O13: 3200
B14: 45537 | C14: VENTA JORDY | J14: 1000
B15: 45538 | C15: VENTA JORDY | G15: 5000
B16: 45538 | C16: VENTAS H&C | O16: 200 | W16: 60 | X16: 250
B17: 45539 | C17: VENTAS H&C | G17: 1000 | L17: 910
B18: 45540 | C18: VENTAS H&C | D18: 500 | X18: 150
B19: 45542 | C19: VENTAS H&C | G19: 300 | Q19: 5 | W19: 1500 | X19: 1000
A24: SALDO | D24: =SUM(D4:D11)-SUM(D12:D23) -> 9 | E24: =SUM(E4:E11)-SUM(E12:E23) -> 0 | F24: =SUM(F4:F11)-SUM(F12:F23) -> 9 | G24: =SUM(G4:G11)-SUM(G12:G23) -> 4825 | H24: =SUM(H4:H11)-SUM(H12:H23) -> 0 | I24: =SUM(I4:I11)-SUM(I12:I23) -> 0 | J24: =SUM(J4:J11)-SUM(J12:J23) -> 4000 | K24: =SUM(K4:K11)-SUM(K12:K23) -> 2301 | ... AA24: =SUM(AA4:AA11)-SUM(AA12:AA23) -> 0
D26: =D24*0.3 -> 2.7 | E26: =+E24*0.3 -> 0 | F26: =+F24*0.28 -> 2.52 | G26: =+G24*0.3+(125*0.04) -> 1452.5 | H26: =+H24*0.35 -> 0 | I26: =+I24*0.54 -> 0 | J26: =+J24*0.51 -> 2040 | K26: =+K24*0.756 -> 1739.556 | L26: =+L24*0.59 -> 480.85 | M26: =+M24*0.66 -> 0 | N26: =+N24*0.64 -> 0 | O26: =+O24*0.525-(1700*0.025) -> 2425 | P26: =+P24*2.08 -> 14.56 | Q26: =+Q24*1.66-(295*0.06) -> 1302 | R26: =+R24*1.89 -> 1020.6 | S26: =+S24*1.73-(247*0.06) -> 2142.49 | T26: =+T24*1.85 -> 1147 | U26: =+U24*2.18 -> 6.54 | V26: =+V24*1.97 -> 43.34 | W26: =+W24*0.38 -> 547.96 | X26: =+X24*0.29 -> 333.5 | Y26: =+Y24*1.9 -> 416.1 | Z26: =+Z24*0.8 -> 0 | AA26: =+AA24*2 -> 0
AA28: =SUM(D26:AA26) -> 15117.216

Sheet STOCK  08 a 14
D2: PANDERETA | I2: 18 HUECOS | P2: TECHO 12 | S2: TECHO 15 | W2: ARTESANAL | Y2: SUPER KK | Z2: TIPO 4 | AA2: TECHO 08
B3: FECHA | C3: CLIENTE | D3: SIPAN | E3: CHALPON | F3: ZERAMIX | G3: CERAM | H3: FORTALEZA | I3: CERAM | J3: TORRE FUERTE | K3: LARK | L3: FORTALEZA | M3: CRUZ CHALPON | N3: TAISON | O3: SIPAN | P3: LARK | Q3: ITAL | R3: FORTALEZA | S3: ITAL | T3: GALCA | U3: LARK | V3: FORTALEZA | W3: BODOQUE | X3: PEQUEÑO | Y3: CERAMICOS | Z3: FORTALEZA | AA3: CERAM
A4: INGRESO | D4: ='STOCK 01 a 07'!D24 -> 9 | E4: ='STOCK 01 a 07'!E24 -> 0 | F4: ='STOCK 01 a 07'!F24 -> 9 | G4: ='STOCK 01 a 07'!G24 -> 4825 | H4: ='STOCK 01 a 07'!H24 -> 0 | I4: ='STOCK 01 a 07'!I24 -> 0 | J4: ='STOCK 01 a 07'!J24 -> 4000 | K4: ='STOCK 01 a 07'!K24 -> 2301 | ... AA4: ='STOCK 01 a 07'!AA24 -> 0
B5: 45544 | C5: M8B-893 | P5: 600
B6: 45544 | C6: M6I-897 | X6: 1500
B7: 45546 | C7: M6I-897 | G7: 3000
A12: SALIDA | B12: 45544 | C12: VENTA JORDY | G12: 4825
B13: 45545 | C13: VENTAS H&C | D13: 9 | F13: 9
B14: 45546 | C14: VENTAS H&C | G14: 300 | J14: 1000 | R14: 250 | S14: 160 | X14: 250
B15: 45547 | C15: VENTAS H&C | O15: 40 | R15: 290
B16: 45548 | C16: VENTAS H&C | G16: 100 | O16: 10
B17: 45549 | C17: VENTA JORDY | G17: 1500
B18: 45549 | C18: VENTAS H&C | G18: 50
A25: SALDO | D25: =SUM(D4:D11)-SUM(D12:D24) -> 0 | E25: =SUM(E4:E11)-SUM(E12:E24) -> 0 | F25: =SUM(F4:F11)-SUM(F12:F24) -> 0 | G25: =SUM(G4:G11)-SUM(G12:G24) -> 1050 | H25: =SUM(H4:H11)-SUM(H12:H24) -> 0 | I25: =SUM(I4:I11)-SUM(I12:I24) -> 0 | J25: =SUM(J4:J11)-SUM(J12:J24) -> 3000 | K25: =SUM(K4:K11)-SUM(K12:K24) -> 2301 | ... AA25: =SUM(AA4:AA11)-SUM(AA12:AA24) -> 0
D27: =D25*0.3 -> 0 | E27: =+E25*0.3 -> 0 | F27: =+F25*0.28 -> 0 | G27: =+G25*0.3 -> 315 | H27: =+H25*0.35 -> 0 | I27: =+I25*0.54 -> 0 | J27: =+J25*0.51 -> 1530 | K27: =+K25*0.756 -> 1739.556 | L27: =+L25*0.59 -> 480.85 | M27: =+M25*0.66 -> 0 | N27: =+N25*0.64 -> 0 | O27: =+O25*0.525-(1650*0.025) -> 2400 | P27: =+P25*1.9515 -> 1184.5605 | Q27: =+Q25*1.66-(295*0.06) -> 1302 | R27: =+R25*1.89 -> 0 | S27: =+S25*1.73-(87*0.06) -> 1875.29 | T27: =+T25*1.85 -> 1147 | U27: =+U25*2.18 -> 6.54 | V27: =+V25*1.97 -> 43.34 | W27: =+W25*0.38 -> 547.96 | X27: =+X25*0.29 -> 696 | Y27: =+Y25*1.9 -> 416.1 | Z27: =+Z25*0.8 -> 0 | AA27: =+AA25*2 -> 0
AA29: =SUM(D27:AA27) -> 13684.197
P31: =7*2.08 -> 14.56 | R31: =290*1.95 -> 565.5 | S31: 160*1.8
P32: =600*1.95 -> 1170 | R32: 250
P33: =+P31+P32 -> 1184.56
P34: =+P33/P25 -> 1.9514992 | S34: =290*1.89 -> 548.1
S35: =160*1.8 -> 288
S36: =SUM(S34:S35) -> 836.1
S38: =450*1.95 -> 877.5
S39: =+S38-S36 -> 41.4 | U39: 80
U40: FLETE

Sheet STOCK  15 a 21
D2: PANDERETA | I2: 18 HUECOS | P2: TECHO 12 | S2: TECHO 15 | W2: ARTESANAL | Y2: SUPER KK | Z2: TIPO 4 | AA2: TECHO 08
B3: FECHA | C3: CLIENTE | D3: SIPAN | E3: CHALPON | F3: ZERAMIX | G3: CERAM | H3: FORTALEZA | I3: CERAM | J3: TORRE FUERTE | K3: LARK | L3: FORTALEZA | M3: CRUZ CHALPON | N3: TAISON | O3: SIPAN | P3: LARK | Q3: ITAL | R3: FORTALEZA | S3: ITAL | T3: GALCA | U3: LARK | V3: FORTALEZA | W3: BODOQUE | X3: PEQUEÑO | Y3: CERAMICOS | Z3: FORTALEZA | AA3: CERAM
A4: INGRESO | D4: ='STOCK 08 a 14'!D25 -> 0 | E4: ='STOCK 08 a 14'!E25 -> 0 | F4: ='STOCK 08 a 14'!F25 -> 0 | G4: ='STOCK 08 a 14'!G25 -> 1050 | H4: ='STOCK 08 a 14'!H25 -> 0 | I4: ='STOCK 08 a 14'!I25 -> 0 | J4: ='STOCK 08 a 14'!J25 -> 3000 | K4: ='STOCK 08 a 14'!K25 -> 2301 | ... AA4: ='STOCK 08 a 14'!AA25 -> 0
B5: 45551 | C5: M6I-897 | D5: 4500
B6: 45555 | C6: M8B-893 | H6: 2000 | L6: 2000
B7: 45556 | C7: M8B-893 | Q7: 170
A12: SALIDA | B12: 45550 | C12: VENTAS H&C | O12: 28
B13: 45551 | C13: VENTAS H&C | D13: 1000 | G13: 400 | O13: 226 | Q13: 300 | X13: 500
B14: 45552 | C14: VENTAS H&C | K14: =1500+40 -> 1540 | W14: 140 | X14: 300
B15: 45553 | C15: VENTAS H&C | D15: 500 | L15: 815 | O15: 1500 | S15: 150 | W15: 40
B16: 45554 | C16: VENTAS H&C | D16: 500 | S16: 35 | W16: 20
B17: 45555 | C17: VENTAS H&C | D17: 150 | H17: 300 | L17: 1000 | Q17: 495
B18: 45556 | C18: VENTAS H&C | D18: 1000 | O18: 250 | X18: 600
A24: SALDO | D24: =SUM(D4:D11)-SUM(D12:D23) -> 1350 | E24: =SUM(E4:E11)-SUM(E12:E23) -> 0 | F24: =SUM(F4:F11)-SUM(F12:F23) -> 0 | G24: =SUM(G4:G11)-SUM(G12:G23) -> 650 | H24: =SUM(H4:H11)-SUM(H12:H23) -> 1700 | I24: =SUM(I4:I11)-SUM(I12:I23) -> 0 | J24: =SUM(J4:J11)-SUM(J12:J23) -> 3000 | K24: =SUM(K4:K11)-SUM(K12:K23) -> 761 | ... AA24: =SUM(AA4:AA11)-SUM(AA12:AA23) -> 0
D26: =D24*0.315 -> 425.25 | E26: =+E24*0.3 -> 0 | F26: =+F24*0.28 -> 0 | G26: =+G24*0.3 -> 195 | H26: =+H24*0.37 -> 629 | I26: =+I24*0.54 -> 0 | J26: =+J24*0.51 -> 1530 | K26: =+K24*0.756 -> 575.316 | L26: =+L24*0.61 -> 610 | M26: =+M24*0.66 -> 0 | N26: =+N24*0.64 -> 0 | O26: =+O24*0.525 -> 1389.15 | P26: =+P24*1.9515 -> 1184.5605 | Q26: =+Q24*1.7 -> 289 | R26: =+R24*1.89 -> 0 | S26: =+S24*1.73 -> 1560.46 | T26: =+T24*1.85 -> 1147 | U26: =+U24*2.18 -> 6.54 | V26: =+V24*1.97 -> 43.34 | W26: =+W24*0.38 -> 471.96 | X26: =+X24*0.29 -> 290 | Y26: =+Y24*1.9 -> 416.1 | Z26: =+Z24*0.8 -> 0 | AA26: =+AA24*2 -> 0
AA28: =SUM(D26:AA26) -> 10762.676

Sheet STOCK 22 a  28
D2: PANDERETA | I2: 18 HUECOS | P2: TECHO 12 | S2: TECHO 15 | W2: ARTESANAL | Y2: SUPER KK | Z2: TIPO 4 | AA2: TECHO 08
B3: FECHA | C3: CLIENTE | D3: SIPAN | E3: CHALPON | F3: ZERAMIX | G3: CERAM | H3: FORTALEZA | I3: CERAM | J3: TORRE FUERTE | K3: LARK | L3: FORTALEZA | M3: CRUZ CHALPON | N3: TAISON | O3: SIPAN | P3: LARK | Q3: ITAL | R3: FORTALEZA | S3: ITAL | T3: GALCA | U3: LARK | V3: FORTALEZA | W3: BODOQUE | X3: PEQUEÑO | Y3: CERAMICOS | Z3: FORTALEZA | AA3: CERAM
A4: INGRESO | D4: ='STOCK 15 a 21'!D24 -> 1350 | E4: ='STOCK 15 a 21'!E24 -> 0 | F4: ='STOCK 15 a 21'!F24 -> 0 | G4: ='STOCK 15 a 21'!G24 -> 650 | H4: ='STOCK 15 a 21'!H24 -> 1700 | I4: ='STOCK 15 a 21'!I24 -> 0 | J4: ='STOCK 15 a 21'!J24 -> 3000 | K4: ='STOCK 15 a 21'!K24 -> 761 | ... AA4: ='STOCK 15 a 21'!AA24 -> 0
B5: 45558 | C5: ANGEL | D5: 1500
B6: 45559 | C6: M6I-897 | L6: 500
A12: SALIDA | B12: 45556 | C12: VENTAS H&C | W12: 1000
B13: 45558 | C13: VENTAS H&C | D13: 1250 | W13: 150
B14: 45559 | C14: VENTAS H&C | D14: 200 | T14: 80 | X14: 150
B15: 45560 | C15: VENTAS H&C | S15: 300 | W15: 92
B16: 45561 | C16: VENTA JORDY | K16: 500 | S16: 400
B17: 45563 | C17: VENTAS H&C | S17: 140
A25: SALDO | D25: =SUM(D4:D11)-SUM(D12:D24) -> 1400 | E25: =SUM(E4:E11)-SUM(E12:E24) -> 0 | F25: =SUM(F4:F11)-SUM(F12:F24) -> 0 | G25: =SUM(G4:G11)-SUM(G12:G24) -> 650 | H25: =SUM(H4:H11)-SUM(H12:H24) -> 1700 | I25: =SUM(I4:I11)-SUM(I12:I24) -> 0 | J25: =SUM(J4:J11)-SUM(J12:J24) -> 3000 | K25: =SUM(K4:K11)-SUM(K12:K24) -> 261 | ... AA25: =SUM(AA4:AA11)-SUM(AA12:AA24) -> 0
D27: =D25*0.315 -> 441 | E27: =+E25*0.3 -> 0 | F27: =+F25*0.28 -> 0 | G27: =+G25*0.3 -> 195 | H27: =+H25*0.37 -> 629 | I27: =+I25*0.54 -> 0 | J27: =+J25*0.51 -> 1530 | K27: =+K25*0.756 -> 197.316 | L27: =+L25*0.61 -> 915 | M27: =+M25*0.66 -> 0 | N27: =+N25*0.64 -> 0 | O27: =+O25*0.525 -> 1389.15 | P27: =+P25*1.9515 -> 1184.5605 | Q27: =+Q25*1.7 -> 289 | R27: =+R25*1.89 -> 0 | S27: =+S25*1.73 -> 107.26 | T27: =+T25*1.85 -> 999 | U27: =+U25*2.18 -> 6.54 | V27: =+V25*1.97 -> 43.34 | W27: =+W25*0.38 -> 0 | X27: =+X25*0.29 -> 246.5 | Y27: =+Y25*1.9 -> 416.1 | Z27: =+Z25*0.8 -> 0 | AA27: =+AA25*2 -> 0
AA29: =SUM(D27:AA27) -> 8588.7665

Sheet STOCK 29 a  05
D2: PANDERETA | I2: 18 HUECOS | P2: TECHO 12 | S2: TECHO 15 | W2: ARTESANAL | Y2: SUPER KK | Z2: TIPO 4 | AA2: TECHO 08
B3: FECHA | C3: CLIENTE | D3: SIPAN | E3: CHALPON | F3: ZERAMIX | G3: CERAM | H3: FORTALEZA | I3: CERAM | J3: TORRE FUERTE | K3: LARK | L3: FORTALEZA | M3: CRUZ CHALPON | N3: TAISON | O3: SIPAN | P3: LARK | Q3: ITAL | R3: SIPAN | S3: ITAL | T3: GALCA | U3: LARK | V3: FORTALEZA | W3: BODOQUE | X3: PEQUEÑO | Y3: CERAMICOS | Z3: FORTALEZA | AA3: CERAM
A4: INGRESO | D4: ='STOCK 22 a 28'!D25 -> 1400 | E4: ='STOCK 22 a 28'!E25 -> 0 | F4: ='STOCK 22 a 28'!F25 -> 0 | G4: ='STOCK 22 a 28'!G25 -> 650 | H4: ='STOCK 22 a 28'!H25 -> 1700 | I4: ='STOCK 22 a 28'!I25 -> 0 | J4: ='STOCK 22 a 28'!J25 -> 3000 | K4: ='STOCK 22 a 28'!K25 -> 261 | ... AA4: ='STOCK 22 a 28'!AA25 -> 0
B5: 45566 | C5: M6I-897 | I5: 4000
B6: 45566 | C6: M8B-893 | R6: 1300 | W6: 3000
A12: SALIDA | B12: 45565 | C12: VENTAS H&C | O12: 10 | X12: 20
B13: 45567 | C13: VENTAS H&C | H13: 1030 | Q13: 170
B14: 45568 | C14: VENTAS H&C | J14: 1000
B15: 45569 | C15: VENTAS H&C | Y15: 200
B16: 45570 | C16: VENTA JORDY | I16: 4000
B17: 45570 | C17: VENTAS H&C | D17: 200 | X17: 700
A25: SALDO | D25: =SUM(D4:D11)-SUM(D12:D24) -> 1200 | E25: =SUM(E4:E11)-SUM(E12:E24) -> 0 | F25: =SUM(F4:F11)-SUM(F12:F24) -> 0 | G25: =SUM(G4:G11)-SUM(G12:G24) -> 650 | H25: =SUM(H4:H11)-SUM(H12:H24) -> 670 | I25: =SUM(I4:I11)-SUM(I12:I24) -> 0 | J25: =SUM(J4:J11)-SUM(J12:J24) -> 2000 | K25: =SUM(K4:K11)-SUM(K12:K24) -> 261 | ... AA25: =SUM(AA4:AA11)-SUM(AA12:AA24) -> 0
D27: =D25*0.315 -> 378 | E27: =+E25*0.3 -> 0 | F27: =+F25*0.28 -> 0 | G27: =+G25*0.3 -> 195 | H27: =+H25*0.37 -> 247.9 | I27: =+I25*0.5 -> 0 | J27: =+J25*0.51 -> 1020 | K27: =+K25*0.756 -> 197.316 | L27: =+L25*0.61 -> 915 | M27: =+M25*0.66 -> 0 | N27: =+N25*0.64 -> 0 | O27: =+O25*0.525 -> 1383.9 | P27: =+P25*1.9515 -> 1184.5605 | Q27: =+Q25*1.7 -> 0 | R27: =+R25*1.57 -> 2041 | S27: =+S25*1.73 -> 107.26 | T27: =+T25*1.85 -> 999 | U27: =+U25*2.18 -> 6.54 | V27: =+V25*1.97 -> 43.34 | W27: =+W25*0.39 -> 1170 | X27: =+X25*0.29 -> 37.7 | Y27: =+Y25*1.9 -> 36.1 | Z27: =+Z25*0.8 -> 0 | AA27: =+AA25*2 -> 0
AA29: =SUM(D27:AA27) -> 9962.6165

Sheet STOCK 06 a  12
D2: PANDERETA | I2: 18 HUECOS | P2: TECHO 12 | S2: TECHO 15 | W2: ARTESANAL | Y2: SUPER KK | Z2: TIPO 4 | AA2: TECHO 08
B3: FECHA | C3: CLIENTE | D3: SIPAN | E3: CHALPON | F3: ZERAMIX | G3: CERAM | H3: FORTALEZA | I3: CERAM | J3: TORRE FUERTE | K3: LARK | L3: FORTALEZA | M3: CRUZ CHALPON | N3: TAISON | O3: SIPAN | P3: LARK | Q3: ITAL | R3: SIPAN | S3: ITAL | T3: GALCA | U3: LARK | V3: FORTALEZA | W3: BODOQUE | X3: PEQUEÑO | Y3: CERAMICOS | Z3: FORTALEZA | AA3: CERAM
A4: INGRESO | D4: ='STOCK 29 a 05'!D25 -> 1200 | E4: ='STOCK 29 a 05'!E25 -> 0 | F4: ='STOCK 29 a 05'!F25 -> 0 | G4: ='STOCK 29 a 05'!G25 -> 650 | H4: ='STOCK 29 a 05'!H25 -> 670 | I4: ='STOCK 29 a 05'!I25 -> 0 | J4: ='STOCK 29 a 05'!J25 -> 2000 | K4: ='STOCK 29 a 05'!K25 -> 261 | ... AA4: ='STOCK 29 a 05'!AA25 -> 0
B6: 45573 | C6: ANGEL | X6: 1500
B7: 45575 | C7: M8B-893 | G7: 8000
B8: 45576 | C8: M8B-893 | D8: 2000
B9: 45577 | C9: M8B-893 | S9: 1200
A12: SALIDA | B12: 45572 | C12: VENTAS H&C | D12: 100
B13: 45573 | C13: VENTAS H&C | L13: =200+300 -> 500 | W13: 100
B14: 45574 | C14: VENTAS H&C | D14: =150+940 -> 1090 | G14: 500 | R14: 270 | T14: 300 | W14: 1000
B15: 45576 | C15: VENTAS H&C | D15: 640 | H15: 670 | O15: =1000+1500 -> 2500 | X15: 200
B16: 45577 | C16: VENTAS H&C | S16: 400
A25: SALDO | D25: =SUM(D4:D11)-SUM(D12:D24) -> 1370 | E25: =SUM(E4:E11)-SUM(E12:E24) -> 0 | F25: =SUM(F4:F11)-SUM(F12:F24) -> 0 | G25: =SUM(G4:G11)-SUM(G12:G24) -> 8150 | H25: =SUM(H4:H11)-SUM(H12:H24) -> 0 | I25: =SUM(I4:I11)-SUM(I12:I24) -> 0 | J25: =SUM(J4:J11)-SUM(J12:J24) -> 2000 | K25: =SUM(K4:K11)-SUM(K12:K24) -> 261 | ... AA25: =SUM(AA4:AA11)-SUM(AA12:AA24) -> 0
D27: =D25*0.33 -> 452.1 | E27: =+E25*0.3 -> 0 | F27: =+F25*0.28 -> 0 | G27: =+G25*0.34-(150*0.04) -> 2765 | H27: =+H25*0.37 -> 0 | I27: =+I25*0.5 -> 0 | J27: =+J25*0.51 -> 1020 | K27: =+K25*0.756 -> 197.316 | L27: =+L25*0.61 -> 610 | M27: =+M25*0.66 -> 0 | N27: =+N25*0.64 -> 0 | O27: =+O25*0.525 -> 71.4 | P27: =+P25*1.9515 -> 1184.5605 | Q27: =+Q25*1.7 -> 0 | R27: =+R25*1.57 -> 1617.1 | S27: =+S25*1.82 -> 1568.84 | T27: =+T25*1.85 -> 444 | U27: =+U25*2.18 -> 6.54 | V27: =+V25*1.97 -> 43.34 | W27: =+W25*0.39 -> 741 | X27: =+X25*0.29 -> 414.7 | Y27: =+Y25*1.9 -> 36.1 | Z27: =+Z25*0.8 -> 0 | AA27: =+AA25*2 -> 0
AA29: =SUM(D27:AA27) -> 11171.997

Sheet STOCK 13 a  19
D2: PANDERETA | I2: 18 HUECOS | P2: TECHO 12 | S2: TECHO 15 | W2: ARTESANAL | Y2: SUPER KK | Z2: TIPO 4 | AA2: TECHO 08
B3: FECHA | C3: CLIENTE | D3: SIPAN | E3: CHALPON | F3: ZERAMIX | G3: CERAM | H3: FORTALEZA | I3: CERAM | J3: TORRE FUERTE | K3: LARK | L3: FORTALEZA | M3: CRUZ CHALPON | N3: TAISON | O3: SIPAN | P3: LARK | Q3: ITAL | R3: SIPAN | S3: ITAL | T3: GALCA | U3: LARK | V3: FORTALEZA | W3: BODOQUE | X3: PEQUEÑO | Y3: CERAMICOS | Z3: FORTALEZA | AA3: CERAM
A4: INGRESO | D4: ='STOCK 06 a 12'!D25 -> 1370 | E4: ='STOCK 06 a 12'!E25 -> 0 | F4: ='STOCK 06 a 12'!F25 -> 0 | G4: ='STOCK 06 a 12'!G25 -> 8150 | H4: ='STOCK 06 a 12'!H25 -> 0 | I4: ='STOCK 06 a 12'!I25 -> 0 | J4: ='STOCK 06 a 12'!J25 -> 2000 | K4: ='STOCK 06 a 12'!K25 -> 261 | ... AA4: ='STOCK 06 a 12'!AA25 -> 0
B5: 45580 | C5: M6I-897 | D5: 2500
B6: 45580 | C6: M8B-893 | K6: 900
B7: 45581 | C7: M6I-897 | W7: 3000
B8: 45582 | C8: M8B-893 | D8: 6000
B9: 45584 | C9: M6I-897 | W9: 3000
A12: SALIDA | C12: FALTANTE
B13: 45579 | C13: VENTAS H&C | S13: 350 | W13: 500 | X13: 500
B14: 45580 | C14: VENTAS H&C | G14: 100 | W14: 1000 | X14: 200
B15: 45581 | C15: VENTAS H&C | J15: 200 | K15: 400 | P15: 600
B16: 45582 | C16: VENTAS H&C | W16: 500
B17: 45583 | C17: VENTAS H&C | D17: 200
B18: 45584 | C18: VENTAS H&C | W18: 1000 | X18: 7
A25: SALDO | D25: =SUM(D4:D11)-SUM(D12:D24) -> 9670 | E25: =SUM(E4:E11)-SUM(E12:E24) -> 0 | F25: =SUM(F4:F11)-SUM(F12:F24) -> 0 | G25: =SUM(G4:G11)-SUM(G12:G24) -> 8050 | H25: =SUM(H4:H11)-SUM(H12:H24) -> 0 | I25: =SUM(I4:I11)-SUM(I12:I24) -> 0 | J25: =SUM(J4:J11)-SUM(J12:J24) -> 1800 | K25: =SUM(K4:K11)-SUM(K12:K24) -> 761 | ... AA25: =SUM(AA4:AA11)-SUM(AA12:AA24) -> 0
D27: =D25*0.33 -> 3191.1 | E27: =+E25*0.3 -> 0 | F27: =+F25*0.28 -> 0 | G27: =+G25*0.34-(50*0.04) -> 2735 | H27: =+H25*0.37 -> 0 | I27: =+I25*0.5 -> 0 | J27: =+J25*0.51 -> 918 | K27: =+K25*0.82-(261*0.06398) -> 607.32122 | L27: =+L25*0.61 -> 610 | M27: =+M25*0.66 -> 0 | N27: =+N25*0.64 -> 0 | O27: =+O25*0.525 -> 71.4 | P27: =+P25*1.9515 -> 13.6605 | Q27: =+Q25*1.7 -> 0 | R27: =+R25*1.57 -> 1617.1 | S27: =+S25*1.82 -> 931.84 | T27: =+T25*1.85 -> 444 | U27: =+U25*2.18 -> 6.54 | V27: =+V25*1.97 -> 43.34 | W27: =+W25*0.39 -> 1911 | X27: =+X25*0.29 -> 209.67 | Y27: =+Y25*1.9 -> 36.1 | Z27: =+Z25*0.8 -> 0 | AA27: =+AA25*2 -> 0
AA29: =SUM(D27:AA27) -> 13346.072

Sheet STOCK 20 a  26
D2: PANDERETA | I2: 18 HUECOS | P2: TECHO 12 | S2: TECHO 15 | W2: ARTESANAL | Y2: SUPER KK | Z2: TIPO 4 | AA2: TECHO 08
B3: FECHA | C3: CLIENTE | D3: SIPAN | E3: CHALPON | F3: ZERAMIX | G3: CERAM | H3: FORTALEZA | I3: CERAM | J3: TORRE FUERTE | K3: LARK | L3: FORTALEZA | M3: CRUZ CHALPON | N3: TAISON | O3: SIPAN | P3: LARK | Q3: ITAL | R3: SIPAN | S3: ITAL | T3: GALCA | U3: LARK | V3: FORTALEZA | W3: BODOQUE | X3: PEQUEÑO | Y3: CERAMICOS | Z3: FORTALEZA | AA3: CERAM
A4: INGRESO | D4: ='STOCK 13 a 19'!D25 -> 9670 | E4: ='STOCK 13 a 19'!E25 -> 0 | F4: ='STOCK 13 a 19'!F25 -> 0 | G4: ='STOCK 13 a 19'!G25 -> 8050 | H4: ='STOCK 13 a 19'!H25 -> 0 | I4: ='STOCK 13 a 19'!I25 -> 0 | J4: ='STOCK 13 a 19'!J25 -> 1800 | K4: ='STOCK 13 a 19'!K25 -> 761 | ... AA4: ='STOCK 13 a 19'!AA25 -> 0
B5: 45586 | C5: M6I-897 | S5: 1000
B6: 45587 | C6: M8B-893 | Q6: 500
B7: 45588 | C7: M6I-897 | J7: 1000 | V7: 260
A12: SALIDA | B12: 45586 | C12: VENTAS H&C | D12: 500 | X12: 50
B13: 45587 | C13: VENTAS H&C | K13: 200 | R13: 5 | W13: =3000+1000 -> 4000 | X13: 200
B14: 45588 | C14: VENTAS H&C | D14: =2000+1000 -> 3000 | S14: 300
B15: 45589 | C15: VENTAS H&C | D15: 500 | J15: 30 | S15: 170 | W15: =125+150+400 -> 675
B16: 45590 | C16: VENTAS H&C | D16: 250 | S16: 450
B17: 45591 | C17: VENTAS H&C | D17: 200 | J17: 1000 | T17: 50 | X17: 3
B19: ANTERIOR | C19: PROMAT-JH | R19: 300
A25: SALDO | D25: =SUM(D4:D11)-SUM(D12:D24) -> 5220 | E25: =SUM(E4:E11)-SUM(E12:E24) -> 0 | F25: =SUM(F4:F11)-SUM(F12:F24) -> 0 | G25: =SUM(G4:G11)-SUM(G12:G24) -> 8050 | H25: =SUM(H4:H11)-SUM(H12:H24) -> 0 | I25: =SUM(I4:I11)-SUM(I12:I24) -> 0 | J25: =SUM(J4:J11)-SUM(J12:J24) -> 1770 | K25: =SUM(K4:K11)-SUM(K12:K24) -> 561 | ... AA25: =SUM(AA4:AA11)-SUM(AA12:AA24) -> 0
D27: =D25*0.33 -> 1722.6 | E27: =+E25*0.3 -> 0 | F27: =+F25*0.28 -> 0 | G27: =+G25*0.34-(50*0.04) -> 2735 | H27: =+H25*0.37 -> 0 | I27: =+I25*0.5 -> 0 | J27: =+J25*0.51 -> 902.7 | K27: =+K25*0.82-(261*0.06398) -> 443.32122 | L27: =+L25*0.61 -> 610 | M27: =+M25*0.66 -> 0 | N27: =+N25*0.64 -> 0 | O27: =+O25*0.525 -> 71.4 | P27: =+P25*1.9515 -> 13.6605 | Q27: =+Q25*1.78 -> 890 | R27: =+R25*1.57 -> 1138.25 | S27: =+S25*1.82 -> 1077.44 | T27: =+T25*1.85 -> 351.5 | U27: =+U25*2.18 -> 6.54 | V27: =+V25*1.8+(22*0.17) -> 511.34 | W27: =+W25*0.39 -> 87.75 | X27: =+X25*0.29 -> 136.3 | Y27: =+Y25*1.9 -> 36.1 | Z27: =+Z25*0.8 -> 0 | AA27: =+AA25*2 -> 0
S29: =2.1-1.82 -> 0.28 | AA29: =SUM(D27:AA27) -> 10733.902
S30: =+S29*300 -> 84
M32: =2.2*2000 -> 4400

Sheet STOCK 27 a  02
D2: PANDERETA | I2: 18 HUECOS | P2: TECHO 12 | S2: TECHO 15 | W2: ARTESANAL | Y2: SUPER KK | Z2: TIPO 4 | AA2: TECHO 08
B3: FECHA | C3: CLIENTE | D3: SIPAN | E3: CHALPON | F3: ZERAMIX | G3: CERAM | H3: FORTALEZA | I3: CERAM | J3: TORRE FUERTE | K3: LARK | L3: FORTALEZA | M3: CRUZ CHALPON | N3: TAISON | O3: SIPAN | P3: LARK | Q3: ITAL | R3: SIPAN | S3: ITAL | T3: GALCA | U3: LARK | V3: FORTALEZA | W3: BODOQUE | X3: PEQUEÑO | Y3: CERAMICOS | Z3: TAYSON | AA3: CERAM
A4: INGRESO | D4: ='STOCK 20 a 26'!D25 -> 5220 | E4: ='STOCK 20 a 26'!E25 -> 0 | F4: ='STOCK 20 a 26'!F25 -> 0 | G4: ='STOCK 20 a 26'!G25 -> 8050 | H4: ='STOCK 20 a 26'!H25 -> 0 | I4: ='STOCK 20 a 26'!I25 -> 0 | J4: ='STOCK 20 a 26'!J25 -> 1770 | K4: ='STOCK 20 a 26'!K25 -> 561 | ... AA4: ='STOCK 20 a 26'!AA25 -> 0
B5: 45595 | C5: M6I-897 | Z5: 700
B6: 45595 | C6: M8B-893 | Z6: 800
B7: 45595 | C7: M7A-897 | W7: 400
B8: 45596 | C8: M6I-897 | N8: 1500
B9: 45598 | C9: M6I-897 | Q9: 350
A14: SALIDA | B14: 45593 | C14: VENTAS H&C | D14: =2000+50 -> 2050 | J14: =28+500 -> 528
B15: 45594 | C15: VENTAS H&C | D15: 500 | J15: 100 | S15: 100
B16: 45595 | C16: VENTAS H&C | J16: =500+60+100 -> 660
B17: 45596 | C17: VENTA JORDY | G17: 3000
B18: 45596 | C18: VENTAS H&C | J18: =154+239 -> 393 | Q18: 360 | W18: 40 | X18: 300
B19: 45597 | C19: VENTA JORDY | Z19: 1500
B20: 45597 | C20: VENTAS H&C | Q20: 30
B21: 45598 | C21: VENTAS H&C | D21: 60 | S21: 484 | W21: 300
A28: SALDO | D28: =SUM(D4:D13)-SUM(D14:D27) -> 2610 | E28: =SUM(E4:E13)-SUM(E14:E27) -> 0 | F28: =SUM(F4:F13)-SUM(F14:F27) -> 0 | G28: =SUM(G4:G13)-SUM(G14:G27) -> 5050 | H28: =SUM(H4:H13)-SUM(H14:H27) -> 0 | I28: =SUM(I4:I13)-SUM(I14:I27) -> 0 | J28: =SUM(J4:J13)-SUM(J14:J27) -> 89 | K28: =SUM(K4:K13)-SUM(K14:K27) -> 561 | ... AA28: =SUM(AA4:AA13)-SUM(AA14:AA27) -> 0
D30: =D28*0.33 -> 861.3 | E30: =+E28*0.3 -> 0 | F30: =+F28*0.28 -> 0 | G30: =+G28*0.34 -> 1717 | H30: =+H28*0.37 -> 0 | I30: =+I28*0.5 -> 0 | J30: =+J28*0.51 -> 45.39 | K30: =+K28*0.82-(261*0.06398) -> 443.32122 | L30: =+L28*0.61 -> 610 | M30: =+M28*0.66 -> 0 | N30: =+N28*0.63 -> 945 | O30: =+O28*0.525 -> 71.4 | P30: =+P28*1.9515 -> 13.6605 | Q30: =+Q28*1.78 -> 818.8 | R30: =+R28*1.57 -> 1138.25 | S30: =+S28*1.82 -> 14.56 | T30: =+T28*1.85 -> 351.5 | U30: =+U28*2.18 -> 6.54 | V30: =+V28*1.8+(22*0.17) -> 511.34 | W30: =+W28*0.39 -> 111.15 | X30: =+X28*0.29 -> 49.3 | Y30: =+Y28*1.9 -> 36.1 | Z30: =+Z28*0.93 -> 0 | AA30: =+AA28*2 -> 0
G32: =2950*0.34 -> 1003 | S32: =2.1-1.82 -> 0.28 | AA32: =SUM(D30:AA30) -> 7744.6117
G33: =50*0.3 -> 15 | S33: =+S32*300 -> 84
M35: =2.2*2000 -> 4400
J42: 1971.6
J44: =850*1.85 -> 1572.5
J45: =+J42+J44 -> 3544.1

Sheet STOCK 03 a  09
D2: PANDERETA | I2: 18 HUECOS | P2: TECHO 12 | S2: TECHO 15 | W2: ARTESANAL | Y2: SUPER KK | Z2: TIPO 4 | AA2: TECHO 08
B3: FECHA | C3: CLIENTE | D3: SIPAN | E3: CHALPON | F3: ZERAMIX | G3: CERAM | H3: FORTALEZA | I3: CERAM | J3: TORRE FUERTE | K3: LARK | L3: FORTALEZA | M3: CRUZ CHALPON | N3: TAISON | O3: SIPAN | P3: LARK | Q3: ITAL | R3: SIPAN | S3: ITAL | T3: GALCA | U3: LARK | V3: FORTALEZA | W3: BODOQUE | X3: PEQUEÑO | Y3: CERAMICOS | Z3: TAYSON | AA3: CERAM
A4: INGRESO | D4: ='STOCK 27 a 02'!D28 -> 2610 | E4: ='STOCK 27 a 02'!E28 -> 0 | F4: ='STOCK 27 a 02'!F28 -> 0 | G4: ='STOCK 27 a 02'!G28 -> 5050 | H4: ='STOCK 27 a 02'!H28 -> 0 | I4: ='STOCK 27 a 02'!I28 -> 0 | J4: ='STOCK 27 a 02'!J28 -> 89 | K4: ='STOCK 27 a 02'!K28 -> 561 | ... AA4: ='STOCK 27 a 02'!AA28 -> 0
B5: 45600 | C5: M6I-897 | Z5: 700
B6: 45600 | C6: M8B-893 | Z6: 800
B7: 45601 | C7: M6I-897 | Z7: 2500
B8: 45601 | C8: M7A-897 | X8: 1000
B9: 45603 | C9: M6I-897 | O9: 3500
B10: 45603 | C10: M7A-897 | Z10: 500
B11: 45604 | C11: M8B-893 | G11: 4000
B12: 45604 | C12: FLETE | Q12: =1500+800 -> 2300 | S12: 1200
B13: 45605 | C13: FLETE | S13: 1000
B14: 45605 | C14: M8B-893 | L14: 2000
A19: SALIDA | B19: 45600 | C19: VENTA H&C | D19: =600+1600 -> 2200 | G19: 500
B20: 45601 | C20: VENTAS JORDY | T20: 160
B21: 45601 | C21: VENTA H&C | D21: 300 | G21: 455 | Q21: 350 | W21: 40
B22: 45602 | C22: VENTA H&C | G22: =40+500 -> 540 | J22: 89 | O22: =500+11 -> 511 | Q22: 17
B23: 45602 | C23: VENTAS JORDY | Z23: 1800
B24: 45603 | C24: VENTA H&C | G24: =4000+200+500 -> 4700 | O24: 100 | Q24: 800 | X24: =125+60 -> 185
B25: 45604 | C25: VENTA H&C | O25: 1000 | Q25: 200 | S25: =450+1000 -> 1450
B26: 45605 | C26: VENTA H&C | G26: 1000 | N26: 1000 | S26: 20 | X26: 200
A30: SALDO | D30: =SUM(D4:D18)-SUM(D19:D29) -> 110 | E30: =SUM(E4:E18)-SUM(E19:E29) -> 0 | F30: =SUM(F4:F18)-SUM(F19:F29) -> 0 | G30: =SUM(G4:G18)-SUM(G19:G29) -> 1855 | H30: =SUM(H4:H18)-SUM(H19:H29) -> 0 | I30: =SUM(I4:I18)-SUM(I19:I29) -> 0 | J30: =SUM(J4:J18)-SUM(J19:J29) -> 0 | K30: =SUM(K4:K18)-SUM(K19:K29) -> 561 | ... AA30: =SUM(AA4:AA18)-SUM(AA19:AA29) -> 0
D32: =D30*0.33 -> 36.3 | E32: =+E30*0.3 -> 0 | F32: =+F30*0.28 -> 0 | G32: =+G30*0.33 -> 612.15 | H32: =+H30*0.37 -> 0 | I32: =+I30*0.5 -> 0 | J32: =+J30*0.51 -> 0 | K32: =+K30*0.82-(261*0.06398) -> 443.32122 | L32: =+L30*0.61 -> 1830 | M32: =+M30*0.66 -> 0 | N32: =+N30*0.63 -> 315 | O32: =+O30*0.54 -> 1093.5 | P32: =+P30*1.9515 -> 13.6605 | Q32: =+Q30*1.75 -> 2437.75 | R32: =+R30*1.57 -> 1138.25 | S32: =+S30*1.8 -> 1328.4 | T32: =+T30*1.85 -> 55.5 | U32: =+U30*2.18 -> 6.54 | V32: =+V30*1.8+(22*0.17) -> 511.34 | W32: =+W30*0.39 -> 95.55 | X32: =+X30*0.29 -> 227.65 | Y32: =+Y30*1.9 -> 36.1 | Z32: =+Z30*0.93 -> 2511 | AA32: =+AA30*2 -> 0
G34: =2950*0.34 -> 1003 | S34: =2.1-1.82 -> 0.28 | AA34: =SUM(D32:AA32) -> 12692.012
G35: =50*0.3 -> 15 | O35: =136*0.525 -> 71.4 | S35: =+S34*300 -> 84
M37: =2.2*2000 -> 4400 | Q37: =243*1.78 -> 432.54 | S37: =8*1.82 -> 14.56 | T37: =+S30-470 -> 268
O38: =540-480 -> 60 | Q38: =557*1.75 -> 974.75 | S38: =12*1.8 -> 21.6
Q39: =+Q37+Q38 -> 1407.29 | S39: =+S37+S38 -> 36.16
Q40: =+Q39/800 -> 1.7591125 | S40: =+S39/20 -> 1.808
Q41: =+S39/20 -> 1.808
J44: 1971.6
J46: =850*1.85 -> 1572.5
J47: =+J44+J46 -> 3544.1

Sheet STOCK 10 a  16
D2: PANDERETA | I2: 18 HUECOS | P2: TECHO 12 | S2: TECHO 15 | W2: ARTESANAL | Y2: SUPER KK | Z2: TIPO 4 | AA2: TECHO 08
B3: FECHA | C3: CLIENTE | D3: SIPAN | E3: CHALPON | F3: ZERAMIX | G3: CERAM | H3: FORTALEZA | I3: CERAM | J3: TORRE FUERTE | K3: LARK | L3: FORTALEZA | M3: CRUZ CHALPON | N3: TAISON | O3: SIPAN | P3: LARK | Q3: ITAL | R3: SIPAN | S3: ITAL | T3: GALCA | U3: LARK | V3: FORTALEZA | W3: BODOQUE | X3: PEQUEÑO | Y3: CERAMICOS | Z3: TAYSON | AA3: CERAM
A4: INGRESO | D4: ='STOCK 03 a 09'!D30 -> 110 | E4: ='STOCK 03 a 09'!E30 -> 0 | F4: ='STOCK 03 a 09'!F30 -> 0 | G4: ='STOCK 03 a 09'!G30 -> 1855 | H4: ='STOCK 03 a 09'!H30 -> 0 | I4: ='STOCK 03 a 09'!I30 -> 0 | J4: ='STOCK 03 a 09'!J30 -> 0 | K4: ='STOCK 03 a 09'!K30 -> 561 | ... O4: ='STOCK 03 a 09'!O30 -> 2025 | P4: 0 | Q4: ='STOCK 03 a 09'!Q30 -> 1393 | R4: ='STOCK 03 a 09'!R30 -> 725 | S4: ='STOCK 03 a 09'!S30 -> 738 | T4: ='STOCK 03 a 09'!T30 -> 30 | U4: ='STOCK 03 a 09'!U30 -> 3 | V4: ='STOCK 03 a 09'!V30 -> 282 | W4: ='STOCK 03 a 09'!W30 -> 245 | X4: ='STOCK 03 a 09'!X30 -> 785 | ... AA4: ='STOCK 03 a 09'!AA30 -> 0
B5: 45607 | C5: M8B-973 | Z5: 800
B6: 45607 | C6: M6I-897 | Z6: 700
B7: 45608 | C7: M6I-897 | G7: 1500
B8: 45609 | C8: M8B-973 | P8: 1000
B9: 45609 | C9: M6I-897 | G9: 2500
B10: 45610 | C10: JBC-BLANCO | W10: 500
B11: 45611 | C11: JBC-BLANCO | X11: 1500
B12: 45612 | C12: ESTELA | S12: 1000
B13: 45612 | C13: CORPORACION | I13: 6700
A15: SALIDA | B15: 45607 | C15: VENTAS H&C | G15: =500+100+120 -> 720 | L15: 500
B16: 45608 | C16: VENTAS H&C | S16: 170
B17: 45609 | C17: VENTAS H&C | G17: 50 | O17: =150+500 -> 650 | S17: 300 | X17: 500
B18: 45610 | C18: VENTAS H&C | Q18: 38
B19: 45611 | C19: VENTAS H&C | I19: 500
B20: 45612 | C20: VENTAS H&C | O20: =100+15 -> 115 | W20: 100
A26: SALDO | D26: =SUM(D4:D14)-SUM(D15:D25) -> 110 | E26: =SUM(E4:E14)-SUM(E15:E25) -> 0 | F26: =SUM(F4:F14)-SUM(F15:F25) -> 0 | G26: =SUM(G4:G14)-SUM(G15:G25) -> 5085 | H26: =SUM(H4:H14)-SUM(H15:H25) -> 0 | I26: =SUM(I4:I14)-SUM(I15:I25) -> 6200 | J26: =SUM(J4:J14)-SUM(J15:J25) -> 0 | K26: =SUM(K4:K14)-SUM(K15:K25) -> 561 | ... AA26: =SUM(AA4:AA14)-SUM(AA15:AA25) -> 0
D28: =D26*0.33 -> 36.3 | E28: =+E26*0.3 -> 0 | F28: =+F26*0.28 -> 0 | G28: =+G26*0.33 -> 1678.05 | H28: =+H26*0.37 -> 0 | I28: =+I26*0.5 -> 3100 | J28: =+J26*0.51 -> 0 | K28: =+K26*0.82-(261*0.06398) -> 443.32122 | L28: =+L26*0.61 -> 1525 | M28: =+M26*0.66 -> 0 | N28: =+N26*0.63 -> 315 | O28: =+O26*0.54 -> 680.4 | P28: =+P26*2.04 -> 2040 | Q28: =+Q26*1.75 -> 2371.25 | R28: =+R26*1.57 -> 1138.25 | S28: =+S26*1.8 -> 2282.4 | T28: =+T26*1.85 -> 55.5 | U28: =+U26*2.18 -> 6.54 | V28: =+V26*1.8+(22*0.17) -> 511.34 | W28: =+W26*0.39 -> 251.55 | X28: =+X26*0.29 -> 517.65 | Y28: =+Y26*1.9 -> 36.1 | Z28: =+Z26*0.93 -> 3906 | AA28: =+AA26*2 -> 0
AA30: =SUM(D28:AA28) -> 20894.651
M31: =480+80 -> 560
M32: =550+80 -> 630
M33: =750+110 -> 860
M34: =280+70 -> 350
M35: =340+60 -> 400
L38: =1105*8 -> 8840
L39: =L38*3.799+2275 -> 35858.16
L40: =L39-30500 -> 5358.16
L43: soldar tanque radeador, tapa de radeador, gasolina
L45: 250 | M45: ricardo

Sheet STOCK 17 a  23
D2: PANDERETA | I2: 18 HUECOS | P2: TECHO 12 | T2: TECHO 15 | X2: ARTESANAL | Z2: SUPER KK | AA2: TIPO 4 | AB2: TECHO 08
B3: FECHA | C3: CLIENTE | D3: SIPAN | E3: CHALPON | F3: ZERAMIX | G3: CERAM | H3: FORTALEZA | I3: CERAM | J3: TORRE FUERTE | K3: LARK | L3: FORTALEZA | M3: CRUZ CHALPON | N3: TAISON | O3: SIPAN | P3: LARK | Q3: ZERAMIK | R3: ITAL | S3: SIPAN | T3: ITAL | U3: GALCA | V3: LARK | W3: FORTALEZA | X3: BODOQUE | Y3: PEQUEÑO | Z3: CERAMICOS | AA3: TAYSON | AB3: CERAM
A4: INGRESO | D4: ='STOCK 10 a 16'!D26 -> 110 | E4: ='STOCK 10 a 16'!E26 -> 0 | F4: ='STOCK 10 a 16'!F26 -> 0 | G4: ='STOCK 10 a 16'!G26 -> 5085 | H4: ='STOCK 10 a 16'!H26 -> 0 | I4: ='STOCK 10 a 16'!I26 -> 6200 | J4: ='STOCK 10 a 16'!J26 -> 0 | K4: ='STOCK 10 a 16'!K26 -> 561 | ... P4: ='STOCK 10 a 16'!P26 -> 1000 | R4: ='STOCK 10 a 16'!Q26 -> 1355 | S4: ='STOCK 10 a 16'!R26 -> 725 | T4: ='STOCK 10 a 16'!S26 -> 1268 | U4: ='STOCK 10 a 16'!T26 -> 30 | V4: ='STOCK 10 a 16'!U26 -> 3 | W4: ='STOCK 10 a 16'!V26 -> 282 | X4: ='STOCK 10 a 16'!W26 -> 645 | Y4: ='STOCK 10 a 16'!X26 -> 1785 | ... AB4: ='STOCK 10 a 16'!AA26 -> 0
B5: 45614 | C5: M6I-897 | AA5: 700
B6: 45614 | C6: M2Q-717 | L6: 1400 | Q6: 1000
B7: 45615 | C7: M6I-897 | J7: 1000
B8: 45616 | C8: M8B-893 | D8: 4000
B9: 45617 | C9: M6I-897 | G9: 2000
B10: 45617 | C10: M8B-893 | X10: 1000
B11: 45618 | C11: M6I-897 | D11: 4500
B12: 45619 | C12: M8B-893 | D12: 5000
A17: SALIDA | B17: 45614 | C17: VENTA JORDY | AA17: 2200
B18: 45614 | C18: VENTAS H&C | L18: 1000 | O18: 500 | R18: 380 | X18: =300+200+50+15 -> 565 | Y18: 200
B19: 45615 | C19: VENTAS H&C | G19: 3500 | K19: 70 | Y19: 10
B20: 45616 | C20: VENTAS H&C | K20: 20 | O20: 100
B21: 45617 | C21: VENTAS H&C | Y21: 700
B22: 45618 | C22: VENTAS H&C | N22: 230 | R22: 15 | X22: 200
B24: 45602 | C24: VENTA JORDY | AA24: 2200
A28: SALDO | D28: =SUM(D4:D16)-SUM(D17:D27) -> 13610 | E28: =SUM(E4:E16)-SUM(E17:E27) -> 0 | F28: =SUM(F4:F16)-SUM(F17:F27) -> 0 | G28: =SUM(G4:G16)-SUM(G17:G27) -> 3585 | H28: =SUM(H4:H16)-SUM(H17:H27) -> 0 | I28: =SUM(I4:I16)-SUM(I17:I27) -> 6200 | J28: =SUM(J4:J16)-SUM(J17:J27) -> 1000 | K28: =SUM(K4:K16)-SUM(K17:K27) -> 471 | ... AB28: =SUM(AB4:AB16)-SUM(AB17:AB27) -> 0
D30: =D28*0.33 -> 4491.3 | E30: =+E28*0.3 -> 0 | F30: =+F28*0.28 -> 0 | G30: =+G28*0.33 -> 1183.05 | H30: =+H28*0.37 -> 0 | I30: =+I28*0.53 -> 3286 | J30: =+J28*0.54 -> 540 | K30: =+K28*0.82-(171*0.06398) -> 375.27942 | L30: =+L28*0.61 -> 1769 | M30: =+M28*0.66 -> 0 | N30: =+N28*0.63 -> 170.1 | O30: =+O28*0.54 -> 356.4 | P30: =+P28*2.04 -> 2040 | Q30: =+Q28*1.57 -> 1570 | R30: =+R28*1.75 -> 1680 | S30: =+S28*1.57 -> 1138.25 | T30: =+T28*1.8 -> 2282.4 | U30: =+U28*1.85 -> 55.5 | V30: =+V28*2.18 -> 6.54 | W30: =+W28*1.8+(22*0.17) -> 511.34 | X30: =+X28*0.39 -> 343.2 | Y30: =+Y28*0.29 -> 253.75 | Z30: =+Z28*1.9 -> 36.1 | AA30: =+AA28*0.93 -> 465 | AB30: =+AB28*2 -> 0
AB32: =SUM(D30:AB30) -> 22553.209
D34: 13670 | E34: 0 | F34: 0 | G34: 1630 | I34: 7313 | J34: 1000 | K34: 215 | L34: 1900 | N34: 270 | O34: 711 | P34: 1000 | Q34: 1000 | R34: 955 | S34: 725 | T34: 1268 | U34: 20 | V34: 0 | W34: 284 | X34: 1586 | Y34: 740 | Z34: 15 | AA34: 500 | AB34: 0
D35: =D34-D28 -> 60 | E35: =E34-E28 -> 0 | F35: =F34-F28 -> 0 | G35: =G34-G28 -> -1955 | H35: =H34-H28 -> 0 | I35: =I34-I28 -> 1113 | J35: =J34-J28 -> 0 | K35: =K34-K28 -> -256 | ... AB35: =AB34-AB28 -> 0
D36: =D35*0.33 -> 19.8 | G36: =G35*0.33 -> -645.15 | I36: =I35*0.53 -> 589.89 | K36: =-171*0.75602-85*0.82 -> -198.97942 | L36: =L35*0.61 -> -610 | O36: =O35*0.54 -> 27.54 | R36: =R35*1.75 -> -8.75 | U36: =U35*1.85 -> -18.5 | V36: =V35*2.18 -> -6.54 | W36: =W35*1.8 -> 3.6 | X36: =X35*0.39 -> 275.34 | Y36: =Y35*0.29 -> -39.15 | Z36: =Z35*1.9 -> -7.6 | AB36: =SUM(D36:AA36) -> -618.49942
AB38: =AB32+AB36 -> 21934.71

Sheet STOCK 24 a  30
D2: PANDERETA | I2: 18 HUECOS | P2: TECHO 12 | T2: TECHO 15 | X2: ARTESANAL | Z2: SUPER KK | AA2: TIPO 4 | AB2: TECHO 08
B3: FECHA | C3: CLIENTE | D3: SIPAN | E3: CHALPON | F3: ZERAMIX | G3: CERAM | H3: FORTALEZA | I3: CERAM | J3: TORRE FUERTE | K3: LARK | L3: FORTALEZA | M3: CRUZ CHALPON | N3: TAISON | O3: SIPAN | P3: LARK | Q3: ZERAMIK | R3: ITAL | S3: SIPAN | T3: ITAL | U3: GALCA | V3: LARK | W3: FORTALEZA | X3: BODOQUE | Y3: PEQUEÑO | Z3: CERAMICOS | AA3: TAYSON | AB3: CERAM
A4: INGRESO | D4: ='STOCK 17 a 23'!D34 -> 13670 | E4: ='STOCK 17 a 23'!E34 -> 0 | F4: ='STOCK 17 a 23'!F34 -> 0 | G4: ='STOCK 17 a 23'!G34 -> 1630 | H4: ='STOCK 17 a 23'!H34 -> 0 | I4: ='STOCK 17 a 23'!I34 -> 7313 | J4: ='STOCK 17 a 23'!J34 -> 1000 | K4: ='STOCK 17 a 23'!K34 -> 215 | ... AB4: ='STOCK 17 a 23'!AB34 -> 0
B5: 45621 | C5: M6I-897 | D5: 4500
B6: 45623 | C6: M6I-897 | G6: 8000
B7: 45624 | C7: M6I-897 | O7: 2000
B8: 45624 | C8: ESTELA | R8: 1500
B9: 45625 | C9: M6I-897 | N9: 2000
B10: 45626 | C10: JBC | Y10: 1500
A17: SALIDA
B18: 45622 | C18: VENTA JORDY | W18: 284
B19: 45622 | C19: VENTAS H&C | X19: 40 | Y19: 100
B20: 45623 | C20: VENTA JORDY | Q20: 500
B21: 45623 | C21: VENTAS H&C | L21: 1000 | X21: 12
B22: 45624 | C22: VENTAS H&C | D22: 1000 | G22: 50 | I22: =30+80 -> 110 | R22: =500+455 -> 955 | T22: 500 | Y22: 400
B23: 45625 | C23: VENTAS H&C | I23: 500 | Y23: 50
B24: 45626 | C24: VENTAS H&C | Y24: 300
A28: SALDO | D28: =SUM(D4:D16)-SUM(D17:D27) -> 17170 | E28: =SUM(E4:E16)-SUM(E17:E27) -> 0 | F28: =SUM(F4:F16)-SUM(F17:F27) -> 0 | G28: =SUM(G4:G16)-SUM(G17:G27) -> 9580 | H28: =SUM(H4:H16)-SUM(H17:H27) -> 0 | I28: =SUM(I4:I16)-SUM(I17:I27) -> 6703 | J28: =SUM(J4:J16)-SUM(J17:J27) -> 1000 | K28: =SUM(K4:K16)-SUM(K17:K27) -> 215 | ... AB28: =SUM(AB4:AB16)-SUM(AB17:AB27) -> 0
D30: =D28*0.33 -> 5666.1 | E30: =+E28*0.3 -> 0 | F30: =+F28*0.28 -> 0 | G30: =+G28*0.33 -> 3161.4 | H30: =+H28*0.37 -> 0 | I30: =+I28*0.53 -> 3552.59 | J30: =+J28*0.54 -> 540 | K30: =+K28*0.82 -> 176.3 | L30: =+L28*0.61 -> 549 | M30: =+M28*0.66 -> 0 | N30: =+N28*0.63 -> 1430.1 | O30: =+O28*0.54 -> 1463.94 | P30: =+P28*2.04 -> 2040 | Q30: =+Q28*1.57 -> 785 | R30: =+R28*1.8 -> 2700 | S30: =+S28*1.57 -> 1138.25 | T30: =+T28*1.8 -> 1382.4 | U30: =+U28*1.85 -> 37 | V30: =+V28*2.18 -> 0 | W30: =+W28*1.8 -> 0 | X30: =+X28*0.39 -> 598.26 | Y30: =+Y28*0.29 -> 403.1 | Z30: =+Z28*1.9 -> 28.5 | AA30: =+AA28*0.93 -> 465 | AB30: =+AB28*2 -> 0
AB32: =SUM(D30:AB30) -> 26116.94

Sheet STOCK 01 a  07
D2: PANDERETA | I2: 18 HUECOS | P2: TECHO 12 | T2: TECHO 15 | X2: ARTESANAL | Z2: SUPER KK | AA2: TIPO 4 | AB2: TECHO 08
B3: FECHA | C3: CLIENTE | D3: SIPAN | E3: CHALPON | F3: ZERAMIX | G3: CERAM | H3: FORTALEZA | I3: CERAM | J3: TORRE FUERTE | K3: LARK | L3: FORTALEZA | M3: CRUZ CHALPON | N3: TAISON | O3: SIPAN | P3: LARK | Q3: ZERAMIK | R3: ITAL | S3: SIPAN | T3: ITAL | U3: GALCA | V3: LARK | W3: FORTALEZA | X3: BODOQUE | Y3: PEQUEÑO | Z3: CERAMICOS | AA3: TAYSON | AB3: CERAM
A4: INGRESO | D4: ='STOCK 24 a 30'!D28 -> 17170 | E4: ='STOCK 24 a 30'!E28 -> 0 | F4: ='STOCK 24 a 30'!F28 -> 0 | G4: ='STOCK 24 a 30'!G28 -> 9580 | H4: ='STOCK 24 a 30'!H28 -> 0 | I4: ='STOCK 24 a 30'!I28 -> 6703 | J4: ='STOCK 24 a 30'!J28 -> 1000 | K4: ='STOCK 24 a 30'!K28 -> 215 | ... AB4: ='STOCK 24 a 30'!AB28 -> 0
B5: 45628 | C5: MB8-893 | L5: 1000
B6: 45629 | C6: M6I-897 | X6: 3000 | Y6: 3000
B7: 45630 | C7: M6I-897 | L7: 3500
B8: 45631 | C8: JBC | Y8: 1500
B9: 45631 | C9: M8B-893 | N9: 2000
B10: 45632 | C10: M6I-897 | G10: 5000
B11: 45632 | C11: FUSO | N11: 1000
A19: SALIDA | B19: 45627 | C19: VENTAS H&C | Y19: 322
B20: 45628 | C20: VENTAS H&C | G20: =1000+500 -> 1500 | O20: 100 | R20: 170 | X20: 100 | Y20: =200+100 -> 300
B21: 45629 | C21: VENTAS H&C | O21: 400 | P21: 64 | R21: 35
B22: 45630 | C22: VENTAS H&C | G22: =1000+2000 -> 3000 | O22: 1000 | R22: 220 | T22: 360 | X22: 350 | Y22: =450+500 -> 950
B23: 45631 | C23: VENTAS H&C | R23: 70
B24: 45632 | C24: VENTAS H&C | D24: 1000 | G24: 3000 | Y24: 50
A30: SALDO | D30: =SUM(D4:D18)-SUM(D19:D29) -> 16170 | E30: =SUM(E4:E18)-SUM(E19:E29) -> 0 | F30: =SUM(F4:F18)-SUM(F19:F29) -> 0 | G30: =SUM(G4:G18)-SUM(G19:G29) -> 7080 | H30: =SUM(H4:H18)-SUM(H19:H29) -> 0 | I30: =SUM(I4:I18)-SUM(I19:I29) -> 6703 | J30: =SUM(J4:J18)-SUM(J19:J29) -> 1000 | K30: =SUM(K4:K18)-SUM(K19:K29) -> 215 | ... AB30: =SUM(AB4:AB18)-SUM(AB19:AB29) -> 0
D32: =D30*0.33 -> 5336.1 | E32: =+E30*0.3 -> 0 | F32: =+F30*0.28 -> 0 | G32: =+G30*0.33 -> 2336.4 | H32: =+H30*0.37 -> 0 | I32: =+I30*0.53 -> 3552.59 | J32: =+J30*0.54 -> 540 | K32: =+K30*0.82 -> 176.3 | L32: =+L30*0.61 -> 3294 | M32: =+M30*0.66 -> 0 | N32: =+N30*0.63 -> 3320.1 | O32: =+O30*0.54 -> 653.94 | P32: =+P30*2.04 -> 1909.44 | Q32: =+Q30*1.57 -> 785 | R32: =+R30*1.8 -> 1809 | S32: =+S30*1.57 -> 1138.25 | T32: =+T30*1.8 -> 734.4 | U32: =+U30*1.85 -> 37 | V32: =+V30*2.18 -> 0 | W32: =+W30*1.8 -> 0 | X32: =+X30*0.39 -> 1592.76 | Y32: =+Y30*0.29 -> 1237.72 | Z32: =+Z30*1.9 -> 28.5 | AA32: =+AA30*0.93 -> 465 | AB32: =+AB30*2 -> 0
AB34: =SUM(D32:AB32) -> 28946.5

Sheet STOCK 08 a  14
D2: PANDERETA | I2: 18 HUECOS | P2: TECHO 12 | T2: TECHO 15 | X2: ARTESANAL | Z2: SUPER KK | AA2: TIPO 4 | AB2: TECHO 08
B3: FECHA | C3: CLIENTE | D3: SIPAN | E3: CHALPON | F3: ZERAMIX | G3: CERAM | H3: FORTALEZA | I3: CERAM | J3: TORRE FUERTE | K3: LARK | L3: FORTALEZA | M3: CRUZ CHALPON | N3: TAISON | O3: SIPAN | P3: LARK | Q3: ZERAMIK | R3: ITAL | S3: SIPAN | T3: ITAL | U3: GALCA | V3: LARK | W3: FORTALEZA | X3: BODOQUE | Y3: PEQUEÑO | Z3: CERAMICOS | AA3: TAYSON | AB3: CERAM
A4: INGRESO | D4: ='STOCK 01 a 07'!D30 -> 16170 | E4: ='STOCK 01 a 07'!E30 -> 0 | F4: ='STOCK 01 a 07'!F30 -> 0 | G4: ='STOCK 01 a 07'!G30 -> 7080 | H4: ='STOCK 01 a 07'!H30 -> 0 | I4: ='STOCK 01 a 07'!I30 -> 6703 | J4: ='STOCK 01 a 07'!J30 -> 1000 | K4: ='STOCK 01 a 07'!K30 -> 215 | ... AB4: ='STOCK 01 a 07'!AB30 -> 0
B5: 45636 | C5: M6I-897 | G5: 6000
B6: 45637 | C6: M8B-893 | G6: 8000
B7: 45637 | C7: M6I-897 | G7: 1000
B8: 45640 | C8: M8B-893 | T8: 1200
B10: DIF STOCK | T10: -12
A13: SALIDA | B13: 45635 | C13: VENTAS H&C | D13: 1500 | G13: 1000 | L13: 540 | R13: 18 | Y13: 60
B14: 45636 | C14: VENTAS H&C | D14: 1000 | G14: =50+3000+1000+1000 -> 5050 | K14: 215 | X14: 50 | Y14: 50
B15: 45637 | C15: VENTAS H&C | D15: 100 | G15: 1000 | X15: 60
B16: 45638 | C16: VENTAS H&C | G16: 1000 | O16: 500 | R16: 300 | T16: 300
B17: 45639 | C17: VENTAS H&C | I17: 1000 | R17: 200 | T17: 96
B18: 45640 | C18: VENTAS H&C | G18: 1000
A24: SALDO | D24: =SUM(D4:D12)-SUM(D13:D23) -> 13570 | E24: =SUM(E4:E12)-SUM(E13:E23) -> 0 | F24: =SUM(F4:F12)-SUM(F13:F23) -> 0 | G24: =SUM(G4:G12)-SUM(G13:G23) -> 13030 | H24: =SUM(H4:H12)-SUM(H13:H23) -> 0 | I24: =SUM(I4:I12)-SUM(I13:I23) -> 5703 | J24: =SUM(J4:J12)-SUM(J13:J23) -> 1000 | K24: =SUM(K4:K12)-SUM(K13:K23) -> 0 | ... AB24: =SUM(AB4:AB12)-SUM(AB13:AB23) -> 0
D26: =D24*0.33 -> 4478.1 | E26: =+E24*0.3 -> 0 | F26: =+F24*0.28 -> 0 | G26: =+G24*0.33 -> 4299.9 | H26: =+H24*0.37 -> 0 | I26: =+I24*0.53 -> 3022.59 | J26: =+J24*0.54 -> 540 | K26: =+K24*0.82 -> 0 | L26: =+L24*0.61 -> 2964.6 | M26: =+M24*0.66 -> 0 | N26: =+N24*0.63 -> 3320.1 | O26: =+O24*0.54 -> 383.94 | P26: =+P24*2.04 -> 1909.44 | Q26: =+Q24*1.57 -> 785 | R26: =+R24*1.8 -> 876.6 | S26: =+S24*1.57 -> 1138.25 | T26: =+T24*1.81 -> 2172 | U26: =+U24*1.85 -> 37 | V26: =+V24*2.18 -> 0 | W26: =+W24*1.8 -> 0 | X26: =+X24*0.39 -> 1549.86 | Y26: =+Y24*0.29 -> 1205.82 | Z26: =+Z24*1.9 -> 28.5 | AA26: =+AA24*0.93 -> 465 | AB26: =+AB24*2 -> 0
AB28: =SUM(D26:AB26) -> 29176.7
M31: 3274.4
M32: =+M31-4044.74 -> -770.34

Sheet STOCK 15 a  21
D2: PANDERETA | I2: 18 HUECOS | P2: TECHO 12 | T2: TECHO 15 | X2: ARTESANAL | Z2: SUPER KK | AA2: TIPO 4 | AB2: TIPO 12
B3: FECHA | C3: CLIENTE | D3: SIPAN | E3: CHALPON | F3: ZERAMIX | G3: CERAM | H3: FORTALEZA | I3: CERAM | J3: TORRE FUERTE | K3: LARK | L3: FORTALEZA | M3: CRUZ CHALPON | N3: TAISON | O3: SIPAN | P3: LARK | Q3: ZERAMIK | R3: ITAL | S3: SIPAN | T3: ITAL | U3: GALCA | V3: LARK | W3: FORTALEZA | X3: BODOQUE | Y3: PEQUEÑO | Z3: CERAMICOS | AA3: TAYSON | AB3: CONCRETO
A4: INGRESO | D4: ='STOCK 08 a 14'!D24 -> 13570 | E4: ='STOCK 08 a 14'!E24 -> 0 | F4: ='STOCK 08 a 14'!F24 -> 0 | G4: ='STOCK 08 a 14'!G24 -> 13030 | H4: ='STOCK 08 a 14'!H24 -> 0 | I4: ='STOCK 08 a 14'!I24 -> 5703 | J4: ='STOCK 08 a 14'!J24 -> 1000 | K4: ='STOCK 08 a 14'!K24 -> 0 | ... AB4: ='STOCK 08 a 14'!AB24 -> 0
B5: 45642 | C5: M6I-897
B6: 45647 | C6: M6I-897 | R6: 1200
B7: 45647 | C7: H&C | AB7: 424
B9: DIF STOCK
A13: SALIDA | B13: 45641 | C13: VENTAS H&C | X13: 100 | Y13: =1000+50+500 -> 1550
B14: 45642 | C14: VENTAS H&C | G14: =1000+2000+1500 -> 4500 | R14: 482 | Y14: =1000+10+50 -> 1060
B15: 45643 | C15: VENTAS H&C | O15: 20
B16: 45644 | C16: VENTAS H&C | D16: 1000 | J16: 500 | T16: 235
B17: 45645 | C17: VENTAS H&C | I17: 500 | N17: 50 | X17: 500 | Y17: =35+25+10 -> 70
B18: 45645 | C18: VENTA JORDY | L18: 1000
B19: 45646 | C19: VENTA JORDY | G19: 2000
B20: 45646 | C20: VENTAS H&C | J20: 110
B21: 45647 | C21: VENTAS H&C | X21: 100
A25: SALDO | D25: =SUM(D4:D12)-SUM(D13:D24) -> 12570 | E25: =SUM(E4:E12)-SUM(E13:E24) -> 0 | F25: =SUM(F4:F12)-SUM(F13:F24) -> 0 | G25: =SUM(G4:G12)-SUM(G13:G24) -> 6530 | H25: =SUM(H4:H12)-SUM(H13:H24) -> 0 | I25: =SUM(I4:I12)-SUM(I13:I24) -> 5203 | J25: =SUM(J4:J12)-SUM(J13:J24) -> 390 | K25: =SUM(K4:K12)-SUM(K13:K24) -> 0 | ... AB25: =SUM(AB4:AB12)-SUM(AB13:AB24) -> 424
D27: =D25*0.33 -> 4148.1 | E27: =+E25*0.3 -> 0 | F27: =+F25*0.28 -> 0 | G27: =+G25*0.33 -> 2154.9 | H27: =+H25*0.37 -> 0 | I27: =+I25*0.53 -> 2757.59 | J27: =+J25*0.54 -> 210.6 | K27: =+K25*0.82 -> 0 | L27: =+L25*0.61 -> 2354.6 | M27: =+M25*0.66 -> 0 | N27: =+N25*0.63 -> 3288.6 | O27: =+O25*0.54 -> 373.14 | P27: =+P25*2.04 -> 1909.44 | Q27: =+Q25*1.57 -> 785 | R27: =+R25*1.76 -> 2120.8 | S27: =+S25*1.57 -> 1138.25 | T27: =+T25*1.81 -> 1746.65 | U27: =+U25*1.85 -> 37 | V27: =+V25*2.18 -> 0 | W27: =+W25*1.8 -> 0 | X27: =+X25*0.39 -> 1276.86 | Y27: =+Y25*0.29 -> 428.62 | Z27: =+Z25*1.9 -> 28.5 | AA27: =+AA25*0.93 -> 465 | AB27: =+AB25*1.5 -> 636
AB28: =SUM(D27:AB27) -> 25859.65
C29: REAL | D29: =12334+132 -> 12466 | G29: 6578 | I29: 5211 | J29: 409 | L29: 3864 | N29: 5225 | O29: 697 | P29: 937 | Q29: 450 | R29: 1200 | S29: 725 | T29: 965 | U29: 20 | X29: 3278 | Y29: 1448 | AA29: 500 | AB29: 424
C31: FIFERENCIA | D31: =D29-D25 -> -104 | E31: =E29-E25 -> 0 | F31: =F29-F25 -> 0 | G31: =G29-G25 -> 48 | H31: =H29-H25 -> 0 | I31: =I29-I25 -> 8 | J31: =J29-J25 -> 19 | K31: =K29-K25 -> 0 | ... AB31: =AB29-AB25 -> 0
C32: PRECIO | D32: 0.33 | G32: 0.33 | I32: 0.53 | J32: 0.54 | L32: 0.61 | N32: 0.63 | O32: 0.54 | P32: 2.04 | Q32: 1.57 | R32: 1.76 | S32: 1.57 | X32: 0.39 | Y32: 0.29 | Z32: 1.9
C34: TOTAL | D34: =D31*D32 -> -34.32 | E34: =E31*E32 -> 0 | F34: =F31*F32 -> 0 | G34: =G31*G32 -> 15.84 | H34: =H31*H32 -> 0 | I34: =I31*I32 -> 4.24 | J34: =J31*J32 -> 10.26 | K34: =K31*K32 -> 0 | ... Z34: =Z31*Z32 -> -28.5
Z36: =SUM(D34:Z34) -> -116.05 | AB36: =AB28+Z36 -> 25743.6

Sheet STOCK 21 a  28
D2: PANDERETA | I2: 18 HUECOS | P2: TECHO 12 | T2: TECHO 15 | X2: ARTESANAL | Z2: SUPER KK | AA2: TIPO 4 | AB2: TIPO 12
B3: FECHA | C3: CLIENTE | D3: SIPAN | E3: CHALPON | F3: ZERAMIX | G3: CERAM | H3: FORTALEZA | I3: CERAM | J3: TORRE FUERTE | K3: LARK | L3: FORTALEZA | M3: CRUZ CHALPON | N3: TAISON | O3: SIPAN | P3: LARK | Q3: ZERAMIK | R3: ITAL | S3: SIPAN | T3: ITAL | U3: GALCA | V3: LARK | W3: FORTALEZA | X3: BODOQUE | Y3: PEQUEÑO | Z3: CERAMICOS | AA3: TAYSON | AB3: CONCRETO
A4: INGRESO | D4: ='STOCK 15 a 21'!D29 -> 12466 | E4: ='STOCK 15 a 21'!E29 -> 0 | F4: ='STOCK 15 a 21'!F29 -> 0 | G4: ='STOCK 15 a 21'!G29 -> 6578 | H4: ='STOCK 15 a 21'!H29 -> 0 | I4: ='STOCK 15 a 21'!I29 -> 5211 | J4: ='STOCK 15 a 21'!J29 -> 409 | K4: ='STOCK 15 a 21'!K29 -> 0 | ... AB4: ='STOCK 15 a 21'!AB29 -> 424
B6: 45650 | C6: M6I-897 | D6: 4500
A13: SALIDA | B13: 45649 | C13: VENTAS H&C | AB13: 60
B14: 45650 | C14: VENTA JORDY | G14: 4000
B15: 45652 | C15: VENTAS H&C | D15: 20 | T15: 320 | AB15: 22
B16: 45653 | C16: VENTAS H&C | G16: =200+2000 -> 2200 | O16: 300
B17: 45654 | C17: VENTAS H&C | Q17: 29 | R17: 6 | S17: 3
A25: SALDO | D25: =SUM(D4:D12)-SUM(D13:D24) -> 16946 | E25: =SUM(E4:E12)-SUM(E13:E24) -> 0 | F25: =SUM(F4:F12)-SUM(F13:F24) -> 0 | G25: =SUM(G4:G12)-SUM(G13:G24) -> 378 | H25: =SUM(H4:H12)-SUM(H13:H24) -> 0 | I25: =SUM(I4:I12)-SUM(I13:I24) -> 5211 | J25: =SUM(J4:J12)-SUM(J13:J24) -> 409 | K25: =SUM(K4:K12)-SUM(K13:K24) -> 0 | ... AB25: =SUM(AB4:AB12)-SUM(AB13:AB24) -> 342
D27: =D25*0.33 -> 5592.18 | E27: =+E25*0.3 -> 0 | F27: =+F25*0.28 -> 0 | G27: =+G25*0.33 -> 124.74 | H27: =+H25*0.37 -> 0 | I27: =+I25*0.53 -> 2761.83 | J27: =+J25*0.54 -> 220.86 | K27: =+K25*0.82 -> 0 | L27: =+L25*0.61 -> 2357.04 | M27: =+M25*0.66 -> 0 | N27: =+N25*0.63 -> 3291.75 | O27: =+O25*0.54 -> 214.38 | P27: =+P25*2.04 -> 1911.48 | Q27: =+Q25*1.57 -> 660.97 | R27: =+R25*1.76 -> 2101.44 | S27: =+S25*1.57 -> 1133.54 | T27: =+T25*1.81 -> 1167.45 | U27: =+U25*1.85 -> 37 | V27: =+V25*2.18 -> 0 | W27: =+W25*1.8 -> 0 | X27: =+X25*0.39 -> 1278.42 | Y27: =+Y25*0.29 -> 419.92 | Z27: =+Z25*1.9 -> 0 | AA27: =+AA25*0.93 -> 465 | AB27: =+AB25*1.5 -> 513
AB28: =SUM(D27:AB27) -> 24251

Sheet STOCK 29 a  04
D2: PANDERETA | I2: 18 HUECOS | P2: TECHO 12 | T2: TECHO 15 | X2: ARTESANAL | Z2: SUPER KK | AA2: TIPO 4 | AB2: TIPO 12
B3: FECHA | C3: CLIENTE | D3: SIPAN | E3: CHALPON | F3: ZERAMIX | G3: CERAM | H3: FORTALEZA | I3: CERAM | J3: TORRE FUERTE | K3: LARK | L3: FORTALEZA | M3: CRUZ CHALPON | N3: TAISON | O3: SIPAN | P3: LARK | Q3: ZERAMIK | R3: ITAL | S3: SIPAN | T3: ITAL | U3: GALCA | V3: LARK | W3: FORTALEZA | X3: BODOQUE | Y3: PEQUEÑO | Z3: CERAMICOS | AA3: TAYSON | AB3: CONCRETO
A4: INGRESO | D4: ='STOCK 21 a 28'!D25 -> 16946 | E4: ='STOCK 21 a 28'!E25 -> 0 | F4: ='STOCK 21 a 28'!F25 -> 0 | G4: ='STOCK 21 a 28'!G25 -> 378 | H4: ='STOCK 21 a 28'!H25 -> 0 | I4: ='STOCK 21 a 28'!I25 -> 5211 | J4: ='STOCK 21 a 28'!J25 -> 409 | K4: ='STOCK 21 a 28'!K25 -> 0 | ... AB4: ='STOCK 21 a 28'!AB25 -> 342
AB5: 58
B6: 45656 | C6: M6I-897 | T6: 1000
A13: SALIDA | B13: 45656 | C13: VENTAS H&C | D13: 2500 | I13: 500 | R13: 220 | T13: =400+245 -> 645 | U13: 5
B14: 45656 | C14: VENTA JORDY | I14: 3000
B15: 45657 | C15: VENTA JORDY | AB15: 400
B16: 45659 | C16: VENTAS H&C | D16: 3000 | I16: 500
B17: 45660 | C17: VENTAS H&C | D17: 3500 | G17: 100
B18: 45661 | C18: VENTAS H&C | D18: 500 | L18: 600 | Y18: =1000+30 -> 1030
B20: 46020 | C20: VENTA JORDY | L20: 3000
A25: SALDO | D25: =SUM(D4:D12)-SUM(D13:D24) -> 7446 | E25: =SUM(E4:E12)-SUM(E13:E24) -> 0 | F25: =SUM(F4:F12)-SUM(F13:F24) -> 0 | G25: =SUM(G4:G12)-SUM(G13:G24) -> 278 | H25: =SUM(H4:H12)-SUM(H13:H24) -> 0 | I25: =SUM(I4:I12)-SUM(I13:I24) -> 1211 | J25: =SUM(J4:J12)-SUM(J13:J24) -> 409 | K25: =SUM(K4:K12)-SUM(K13:K24) -> 0 | ... AB25: =SUM(AB4:AB12)-SUM(AB13:AB24) -> 0
D27: =D25*0.33 -> 2457.18 | E27: =+E25*0.3 -> 0 | F27: =+F25*0.28 -> 0 | G27: =+G25*0.33 -> 91.74 | H27: =+H25*0.37 -> 0 | I27: =+I25*0.53 -> 641.83 | J27: =+J25*0.54 -> 220.86 | K27: =+K25*0.82 -> 0 | L27: =+L25*0.61 -> 161.04 | M27: =+M25*0.66 -> 0 | N27: =+N25*0.63 -> 3291.75 | O27: =+O25*0.54 -> 214.38 | P27: =+P25*2.04 -> 1911.48 | Q27: =+Q25*1.57 -> 660.97 | R27: =+R25*1.76 -> 1714.24 | S27: =+S25*1.57 -> 1133.54 | T27: =+T25*1.81 -> 1810 | U27: =+U25*1.85 -> 27.75 | V27: =+V25*2.18 -> 0 | W27: =+W25*1.8 -> 0 | X27: =+X25*0.39 -> 1278.42 | Y27: =+Y25*0.29 -> 121.22 | Z27: =+Z25*1.9 -> 0 | AA27: =+AA25*0.93 -> 465 | AB27: =+AB25*1.5 -> 0
AB28: =SUM(D27:AB27) -> 16201.4

Sheet STOCK 05 a  11
D2: PANDERETA | I2: 18 HUECOS | P2: TECHO 12 | T2: TECHO 15 | X2: ARTESANAL | Z2: SUPER KK | AA2: TIPO 4 | AB2: TIPO 12
B3: FECHA | C3: CLIENTE | D3: SIPAN | E3: CHALPON | F3: ZERAMIX | G3: CERAM | H3: FORTALEZA | I3: CERAM | J3: TORRE FUERTE | K3: LARK | L3: FORTALEZA | M3: CRUZ CHALPON | N3: TAISON | O3: SIPAN | P3: LARK | Q3: ZERAMIK | R3: ITAL | S3: SIPAN | T3: ITAL | U3: GALCA | V3: LARK | W3: FORTALEZA | X3: BODOQUE | Y3: PEQUEÑO | Z3: CERAMICOS | AA3: TAYSON | AB3: CONCRETO
A4: INGRESO | D4: ='STOCK 29 a 04'!D25 -> 7446 | E4: ='STOCK 29 a 04'!E25 -> 0 | F4: ='STOCK 29 a 04'!F25 -> 0 | G4: ='STOCK 29 a 04'!G25 -> 278 | H4: ='STOCK 29 a 04'!H25 -> 0 | I4: ='STOCK 29 a 04'!I25 -> 1211 | J4: ='STOCK 29 a 04'!J25 -> 409 | K4: ='STOCK 29 a 04'!K25 -> 0 | ... AB4: ='STOCK 29 a 04'!AB25 -> 0
B5: 45663 | C5: M8B-893 | H5: 2500
B6: 45664 | C6: M6I-897 | G6: 8000
B7: 45665 | C7: M6I-897 | T7: 600 | X7: 3000
B8: 45666 | C8: M8B-893 | I8: 2500
B9: 45667 | C9: M6I-897 | G9: 6000
B10: 45667 | C10: M8B-893 | I10: 4000
B11: 45668 | C11: M8B-893 | D11: 6000
B12: 45668 | C12: M6I-897 | H12: 3000
A13: SALIDA | B13: 45663 | C13: VENTA JORDY | D13: 4500
B14: 45663 | C14: VENTAS H&C | D14: =1000+20+938 -> 1958 | T14: 40 | X14: 500 | Y14: =150+250 -> 400
B15: 45664 | C15: VENTAS H&C | T15: 230
B16: 45665 | C16: VENTA JORDY | G16: 1000
B17: 45665 | C17: VENTAS H&C | X17: =500+25+10+2000 -> 2535
B18: 45666 | C18: VENTAS H&C | X18: 300
B19: 45667 | C19: VENTA JORDY | G19: 3000 | AA19: 500
B20: 45667 | C20: VENTAS H&C | G20: 150 | I20: 1000 | S20: 450 | X20: 120
B21: 45668 | C21: VENTAS H&C | G21: 75 | I21: 350 | X21: 80
B22: 45668 | C22: NAPO | D22: 988
A25: SALDO | D25: =SUM(D4:D12)-SUM(D13:D24) -> 6000 | E25: =SUM(E4:E12)-SUM(E13:E24) -> 0 | F25: =SUM(F4:F12)-SUM(F13:F24) -> 0 | G25: =SUM(G4:G12)-SUM(G13:G24) -> 10053 | H25: =SUM(H4:H12)-SUM(H13:H24) -> 5500 | I25: =SUM(I4:I12)-SUM(I13:I24) -> 6361 | J25: =SUM(J4:J12)-SUM(J13:J24) -> 409 | K25: =SUM(K4:K12)-SUM(K13:K24) -> 0 | ... AB25: =SUM(AB4:AB12)-SUM(AB13:AB24) -> 0
D27: =D25*0.33 -> 1980 | E27: =+E25*0.3 -> 0 | F27: =+F25*0.28 -> 0 | G27: =+G25*0.33 -> 3317.49 | H27: =+H25*0.4 -> 2200 | I27: =+I25*0.54-(861*0.01) -> 3426.33 | J27: =+J25*0.54 -> 220.86 | K27: =+K25*0.82 -> 0 | L27: =+L25*0.61 -> 161.04 | M27: =+M25*0.66 -> 0 | N27: =+N25*0.63 -> 3291.75 | O27: =+O25*0.54 -> 214.38 | P27: =+P25*2.04 -> 1911.48 | Q27: =+Q25*1.57 -> 660.97 | R27: =+R25*1.76 -> 1714.24 | S27: =+S25*1.57 -> 427.04 | T27: =+T25*1.81 -> 2407.3 | U27: =+U25*1.85 -> 27.75 | V27: =+V25*2.18 -> 0 | W27: =+W25*1.8 -> 0 | X27: =+X25*0.39 -> 1069.77 | Y27: =+Y25*0.29 -> 5.22 | Z27: =+Z25*1.9 -> 0 | AA27: =+AA25*0.93 -> 0 | AB27: =+AB25*1.5 -> 0
AB28: =SUM(D27:AB27) -> 23035.62
Q32: =1680/2 -> 840 | X32: =50*11 -> 550
Q33: =+Q32*4 -> 3360 | X33: =15*42.5 -> 637.5

Sheet STOCK 12 a  18
D2: PANDERETA | I2: 18 HUECOS | P2: TECHO 12 | T2: TECHO 15 | X2: ARTESANAL | Z2: SUPER KK | AA2: TIPO 4 | AB2: TIPO 12
B3: FECHA | C3: CLIENTE | D3: SIPAN | E3: CHALPON | F3: ZERAMIX | G3: CERAM | H3: FORTALEZA | I3: CERAM | J3: TORRE FUERTE | K3: LARK | L3: FORTALEZA | M3: CRUZ CHALPON | N3: TAISON | O3: SIPAN | P3: LARK | Q3: ZERAMIK | R3: ITAL | S3: SIPAN | T3: ITAL | U3: GALCA | V3: LARK | W3: FORTALEZA | X3: BODOQUE | Y3: PEQUEÑO | Z3: CERAMICOS | AA3: TAYSON | AB3: CONCRETO
A4: INGRESO | D4: ='STOCK 05 a 11'!D25 -> 6000 | E4: ='STOCK 05 a 11'!E25 -> 0 | F4: ='STOCK 05 a 11'!F25 -> 0 | G4: ='STOCK 05 a 11'!G25 -> 10053 | H4: ='STOCK 05 a 11'!H25 -> 5500 | I4: ='STOCK 05 a 11'!I25 -> 6361 | J4: ='STOCK 05 a 11'!J25 -> 409 | K4: ='STOCK 05 a 11'!K25 -> 0 | ... AB4: ='STOCK 05 a 11'!AB25 -> 0
B5: 45304 | C5: M8B-893 | T5: 550
B6: 45670 | C6: M6I-897 | G6: 1500
B7: 45304 | C7: JBC | Y7: 500
B8: 45674 | C8: M6I-897 | I8: 3500
B9: 45675 | C9: M6I-897 | O9: 1000
B10: 45675 | C10: M8B-893 | G10: 2000
A14: SALIDA | B14: 45670 | C14: VENTAS H&C | D14: 4500 | G14: =1000+70 -> 1070 | X14: =150+1000+250 -> 1400
B15: 45671 | C15: VENTA JORDY | I15: 2000 | T15: 1000
B16: 45671 | C16: VENTAS H&C | D16: 1000 | P16: 198 | R16: 160
B17: 45672 | C17: VENTAS H&C | R17: =22+10 -> 32 | T17: 330
B18: 45673 | C18: VENTAS H&C | G18: 12 | T18: 15 | X18: 1000
B19: 45674 | C19: VENTAS H&C | G19: 150 | X19: 250 | Y19: 200
B20: 45675 | C20: VENTAS H&C | Y20: 150
A26: SALDO | D26: =SUM(D4:D13)-SUM(D14:D25) -> 500 | E26: =SUM(E4:E13)-SUM(E14:E25) -> 0 | F26: =SUM(F4:F13)-SUM(F14:F25) -> 0 | G26: =SUM(G4:G13)-SUM(G14:G25) -> 12321 | H26: =SUM(H4:H13)-SUM(H14:H25) -> 5500 | I26: =SUM(I4:I13)-SUM(I14:I25) -> 7861 | J26: =SUM(J4:J13)-SUM(J14:J25) -> 409 | K26: =SUM(K4:K13)-SUM(K14:K25) -> 0 | ... AB26: =SUM(AB4:AB13)-SUM(AB14:AB25) -> 0
D28: =D26*0.33 -> 165 | E28: =+E26*0.3 -> 0 | F28: =+F26*0.28 -> 0 | G28: =+G26*0.33 -> 4065.93 | H28: =+H26*0.4 -> 2200 | I28: =+I26*0.49+(361*0.05) -> 3869.94 | J28: =+J26*0.54 -> 220.86 | K28: =+K26*0.82 -> 0 | L28: =+L26*0.61 -> 161.04 | M28: =+M26*0.66 -> 0 | N28: =+N26*0.63 -> 3291.75 | O28: =+O26*0.54 -> 754.38 | P28: =+P26*2.04 -> 1507.56 | Q28: =+Q26*1.57 -> 660.97 | R28: =+R26*1.76 -> 1376.32 | S28: =+S26*1.57 -> 427.04 | T28: =+T26*1.81 -> 968.35 | U28: =+U26*1.85 -> 27.75 | V28: =+V26*2.18 -> 0 | W28: =+W26*1.8 -> 0 | X28: =+X26*0.39 -> 36.27 | Y28: =+Y26*0.29 -> 48.72 | Z28: =+Z26*1.9 -> 0 | AA28: =+AA26*0.93 -> 0 | AB28: =+AB26*1.5 -> 0
AB29: =SUM(D28:AB28) -> 19781.88
Q33: =1680/2 -> 840 | X33: =50*11 -> 550
Q34: =+Q33*4 -> 3360 | X34: =15*42.5 -> 637.5

Sheet STOCK 19a25
D2: PANDERETA | I2: 18 HUECOS | P2: TECHO 12 | T2: TECHO 15 | X2: ARTESANAL | Z2: SUPER KK | AA2: TIPO 4 | AB2: TIPO 12
B3: FECHA | C3: CLIENTE | D3: SIPAN | E3: CHALPON | F3: ZERAMIX | G3: CERAM | H3: FORTALEZA | I3: CERAM | J3: TORRE FUERTE | K3: LARK | L3: FORTALEZA | M3: CRUZ CHALPON | N3: TAISON | O3: SIPAN | P3: LARK | Q3: ZERAMIK | R3: ITAL | S3: SIPAN | T3: ITAL | U3: GALCA | V3: LARK | W3: FORTALEZA | X3: BODOQUE | Y3: PEQUEÑO | Z3: CERAMICOS | AA3: TAYSON | AB3: CONCRETO
A4: INGRESO | D4: ='STOCK 12 a 18'!D26 -> 500 | E4: ='STOCK 12 a 18'!E26 -> 0 | F4: ='STOCK 12 a 18'!F26 -> 0 | G4: ='STOCK 12 a 18'!G26 -> 12321 | H4: ='STOCK 12 a 18'!H26 -> 5500 | I4: ='STOCK 12 a 18'!I26 -> 7861 | J4: ='STOCK 12 a 18'!J26 -> 409 | K4: ='STOCK 12 a 18'!K26 -> 0 | ... AB4: ='STOCK 12 a 18'!AB26 -> 0
B5: 45680 | C5: M6I-897 | X5: =1500+1470 -> 2970 | Y5: 1030
B6: 45681 | C6: M6I-897 | T6: 1000
B7: 45681 | C7: M8B-983 | G7: 8000
B8: 45682 | C8: M8B-983 | L8: 3500
A12: SALIDA | B12: 45677 | C12: VENTAS H&C | D12: 150 | I12: 1000 | N12: 2000 | R12: 100 | X12: 93 | Y12: 160
B13: 45678 | C13: VENTAS H&C | G13: 1000 | I13: 1000 | L13: 264
B14: 45679 | C14: VENTA JORDY | G14: 2000
B15: 45679 | C15: VENTAS H&C | G15: 30 | H15: 500
B16: 45680 | C16: VENTAS H&C | N16: 100 | R16: 250
B17: 45681 | C17: VENTAS H&C | G17: 2484 | N17: 1000
B18: 45682 | C18: VENTAS H&C | I18: 1500
A23: SALDO | D23: =SUM(D4:D11)-SUM(D12:D22) -> 350 | E23: =SUM(E4:E11)-SUM(E12:E22) -> 0 | F23: =SUM(F4:F11)-SUM(F12:F22) -> 0 | G23: =SUM(G4:G11)-SUM(G12:G22) -> 14807 | H23: =SUM(H4:H11)-SUM(H12:H22) -> 5000 | I23: =SUM(I4:I11)-SUM(I12:I22) -> 4361 | J23: =SUM(J4:J11)-SUM(J12:J22) -> 409 | K23: =SUM(K4:K11)-SUM(K12:K22) -> 0 | ... AB23: =SUM(AB4:AB11)-SUM(AB12:AB22) -> 0
D25: =D23*0.33 -> 115.5 | E25: =+E23*0.3 -> 0 | F25: =+F23*0.28 -> 0 | G25: =+G23*0.33 -> 4886.31 | H25: =+H23*0.4 -> 2000 | I25: =+I23*0.49 -> 2136.89 | J25: =+J23*0.54 -> 220.86 | K25: =+K23*0.82 -> 0 | L25: =+L23*0.62 -> 2170 | M25: =+M23*0.66 -> 0 | N25: =+N23*0.63 -> 1338.75 | O25: =+O23*0.54 -> 754.38 | P25: =+P23*2.04 -> 1507.56 | Q25: =+Q23*1.57 -> 660.97 | R25: =+R23*1.76 -> 760.32 | S25: =+S23*1.57 -> 427.04 | T25: =+T23*1.83-(535*0.02) -> 2798.35 | U25: =+U23*1.85 -> 27.75 | V25: =+V23*2.18 -> 0 | W25: =+W23*1.8 -> 0 | X25: =+X23*0.39 -> 1158.3 | Y25: =+Y23*0.29 -> 301.02 | Z25: =+Z23*1.9 -> 0 | AA25: =+AA23*0.93 -> 0 | AB25: =+AB23*1.5 -> 0
AB26: =SUM(D25:AB25) -> 21264
S30: =32*50 -> 1600
Q31: =35+23+25+26 -> 109 | S31: =500*42.5 -> 21250
Q32: =+Q31+50 -> 159

Sheet STOCK 26a01
D2: PANDERETA | I2: 18 HUECOS | P2: TECHO 12 | T2: TECHO 15 | X2: ARTESANAL | Z2: SUPER KK | AA2: TIPO 4 | AB2: TIPO 12
B3: FECHA | C3: CLIENTE | D3: SIPAN | E3: CHALPON | F3: ZERAMIX | G3: CERAM | H3: FORTALEZA | I3: CERAM | J3: TORRE FUERTE | K3: LARK | L3: FORTALEZA | M3: CRUZ CHALPON | N3: TAISON | O3: SIPAN | P3: LARK | Q3: ZERAMIK | R3: ITAL | S3: SIPAN | T3: ITAL | U3: GALCA | V3: LARK | W3: FORTALEZA | X3: BODOQUE | Y3: PEQUEÑO | Z3: CERAMICOS | AA3: TAYSON | AB3: CONCRETO
A4: INGRESO | D4: ='STOCK 19a25'!D23 -> 350 | E4: ='STOCK 19a25'!E23 -> 0 | F4: ='STOCK 19a25'!F23 -> 0 | G4: ='STOCK 19a25'!G23 -> 14807 | H4: ='STOCK 19a25'!H23 -> 5000 | I4: ='STOCK 19a25'!I23 -> 4361 | J4: ='STOCK 19a25'!J23 -> 409 | K4: ='STOCK 19a25'!K23 -> 0 | ... AB4: ='STOCK 19a25'!AB23 -> 0
B5: 45685 | C5: M8B-893 | R5: 880
B6: 45684 | C6: CARLOS | Y6: 500
B7: 45687 | C7: M6I-897 | G7: 6000
A12: SALIDA | B12: 45684 | C12: VENTA JORDY | X12: 2970
B13: 45683 | C13: VENTAS H&C | D13: 14
B14: 45684 | C14: VENTAS H&C | G14: 2000 | H14: 3000 | L14: 3000 | T14: 1 | Y14: 1000
B15: 45685 | C15: VENTAS H&C | G15: 1000 | I15: 500 | R15: 70
B16: 45685 | C16: VENTA JORDY | G16: 4000
B17: 45686 | C17: VENTAS H&C | G17: 1500 | L17: 500 | Q17: 170
B18: 45687 | C18: VENTAS H&C | I18: =200+1000+2000 -> 3200 | R18: 550
B19: 45688 | C19: VENTAS H&C | G19: 500 | I19: 300
B20: 45689 | C20: VENTAS H&C | G20: =1000+20 -> 1020
A24: SALDO | D24: =SUM(D4:D11)-SUM(D12:D23) -> 336 | E24: =SUM(E4:E11)-SUM(E12:E23) -> 0 | F24: =SUM(F4:F11)-SUM(F12:F23) -> 0 | G24: =SUM(G4:G11)-SUM(G12:G23) -> 10787 | H24: =SUM(H4:H11)-SUM(H12:H23) -> 2000 | I24: =SUM(I4:I11)-SUM(I12:I23) -> 361 | J24: =SUM(J4:J11)-SUM(J12:J23) -> 409 | K24: =SUM(K4:K11)-SUM(K12:K23) -> 0 | ... AB24: =SUM(AB4:AB11)-SUM(AB12:AB23) -> 0
D26: =D24*0.33 -> 110.88 | E26: =+E24*0.3 -> 0 | F26: =+F24*0.28 -> 0 | G26: =+G24*0.33 -> 3559.71 | H26: =+H24*0.4 -> 800 | I26: =+I24*0.49 -> 176.89 | J26: =+J24*0.54 -> 220.86 | K26: =+K24*0.82 -> 0 | L26: =+L24*0.62 -> 0 | M26: =+M24*0.66 -> 0 | N26: =+N24*0.63 -> 1338.75 | O26: =+O24*0.54 -> 754.38 | P26: =+P24*2.04 -> 1507.56 | Q26: =+Q24*1.57 -> 394.07 | R26: =+R24*1.76 -> 1217.92 | S26: =+S24*1.57 -> 427.04 | T26: =+T24*1.83-(534*0.02) -> 2796.54 | U26: =+U24*1.85 -> 27.75 | V26: =+V24*2.18 -> 0 | W26: =+W24*1.8 -> 0 | X26: =+X24*0.39 -> 0 | Y26: =+Y24*0.29 -> 156.02 | Z26: =+Z24*1.9 -> 0 | AA26: =+AA24*0.93 -> 0 | AB26: =+AB24*1.5 -> 0
AB27: =SUM(D26:AB26) -> 13488.37
Q32: =35+23+25+26 -> 109
Q33: =+Q32+50 -> 159

Sheet STOCK 02a08
D2: PANDERETA | I2: 18 HUECOS | P2: TECHO 12 | T2: TECHO 15 | X2: ARTESANAL | Z2: SUPER KK | AA2: TIPO 4 | AB2: TIPO 12
B3: FECHA | C3: CLIENTE | D3: SIPAN | E3: CHALPON | F3: ZERAMIX | G3: CERAM | H3: FORTALEZA | I3: CERAM | J3: TORRE FUERTE | K3: LARK | L3: FORTALEZA | M3: CRUZ CHALPON | N3: TAISON | O3: SIPAN | P3: LARK | Q3: ZERAMIK | R3: ITAL | S3: SIPAN | T3: ITAL | U3: GALCA | V3: LARK | W3: FORTALEZA | X3: BODOQUE | Y3: PEQUEÑO | Z3: CERAMICOS | AA3: TAYSON | AB3: CONCRETO
A4: INGRESO | D4: ='STOCK 26a01'!D24 -> 336 | E4: ='STOCK 26a01'!E24 -> 0 | F4: ='STOCK 26a01'!F24 -> 0 | G4: ='STOCK 26a01'!G24 -> 10787 | H4: ='STOCK 26a01'!H24 -> 2000 | I4: ='STOCK 26a01'!I24 -> 361 | J4: ='STOCK 26a01'!J24 -> 409 | K4: ='STOCK 26a01'!K24 -> 0 | ... AB4: ='STOCK 26a01'!AB24 -> 0
B5: 45691 | C5: M6I-897 | L5: 3500
B6: 45691 | C6: M8B-893 | N6: 2000
B7: 45693 | C7: M6I-897 | I7: 1000
B8: 45694 | C8: JAIRO | I8: 5000
B9: 45664 | C9: M6I-897 | G9: 1000 | I9: 2000
A14: SALIDA | B14: 45691 | C14: VENTAS H&C | G14: 2000 | H14: 988 | Y14: 529
B15: 45692 | C15: VENTAS H&C | G15: =1000+40 -> 1040 | L15: =1000+1 -> 1001
B16: 45693 | C16: VENTAS H&C | G16: 350 | R16: 250
B17: 45694 | C17: VENTAS H&C | G17: 700 | I17: 850 | L17: 500
B18: 45695 | C18: VENTAS H&C | G18: 400 | I18: 900 | N18: 1000 | R18: 60 | T18: 190
B19: 45695 | C19: VENTA JORDY | I19: 2000
B20: 45696 | C20: VENTAS H&C | G20: 1500 | I20: =300+500+150 -> 950 | L20: 500 | N20: 2000
B23: 45682 | C23: VENTAS H&C | R23: 270
A26: SALDO | D26: =SUM(D4:D13)-SUM(D14:D25) -> 336 | E26: =SUM(E4:E13)-SUM(E14:E25) -> 0 | F26: =SUM(F4:F13)-SUM(F14:F25) -> 0 | G26: =SUM(G4:G13)-SUM(G14:G25) -> 5797 | H26: =SUM(H4:H13)-SUM(H14:H25) -> 1012 | I26: =SUM(I4:I13)-SUM(I14:I25) -> 3661 | J26: =SUM(J4:J13)-SUM(J14:J25) -> 409 | K26: =SUM(K4:K13)-SUM(K14:K25) -> 0 | ... AB26: =SUM(AB4:AB13)-SUM(AB14:AB25) -> 0
D28: =D26*0.33 -> 110.88 | E28: =+E26*0.3 -> 0 | F28: =+F26*0.28 -> 0 | G28: =+G26*0.33 -> 1913.01 | H28: =+H26*0.4 -> 404.8 | I28: =+I26*0.51 -> 1867.11 | J28: =+J26*0.54 -> 220.86 | K28: =+K26*0.82 -> 0 | L28: =+L26*0.62 -> 929.38 | M28: =+M26*0.66 -> 0 | N28: =+N26*0.64 -> 720 | O28: =+O26*0.54 -> 754.38 | P28: =+P26*2.04 -> 1507.56 | Q28: =+Q26*1.57 -> 394.07 | R28: =+R26*1.76 -> 197.12 | S28: =+S26*1.57 -> 427.04 | T28: =+T26*1.83-(344*0.02) -> 2452.64 | U28: =+U26*1.85 -> 27.75 | V28: =+V26*2.18 -> 0 | W28: =+W26*1.8 -> 0 | X28: =+X26*0.39 -> 0 | Y28: =+Y26*0.29 -> 2.61 | Z28: =+Z26*1.9 -> 0 | AA28: =+AA26*0.93 -> 0 | AB28: =+AB26*1.5 -> 0
AB29: =SUM(D28:AB28) -> 11929.21
N31: =1125*0.63 -> 708.75
N32: =875*0.64 -> 560
N33: =+N31+N32 -> 1268.75
N34: =N33/2000 -> 0.634375 | Q34: =35+23+25+26 -> 109
Q35: =+Q34+50 -> 159

Sheet STOCK 09a15-02
D2: PANDERETA | I2: 18 HUECOS | P2: TECHO 12 | T2: TECHO 15 | X2: ARTESANAL | Z2: SUPER KK | AA2: TIPO 4 | AB2: TIPO 12
B3: FECHA | C3: CLIENTE | D3: SIPAN | E3: CHALPON | F3: ZERAMIX | G3: CERAM | H3: FORTALEZA | I3: CERAM | J3: TORRE FUERTE | K3: LARK | L3: FORTALEZA | M3: CRUZ CHALPON | N3: TAISON | O3: SIPAN | P3: LARK | Q3: ZERAMIK | R3: ITAL | S3: SIPAN | T3: ITAL | U3: GALCA | V3: LARK | W3: FORTALEZA | X3: BODOQUE | Y3: PEQUEÑO | Z3: CERAMICOS | AA3: TAYSON | AB3: CONCRETO
A4: INGRESO | D4: ='STOCK 02a08'!D26 -> 336 | E4: ='STOCK 02a08'!E26 -> 0 | F4: ='STOCK 02a08'!F26 -> 0 | G4: ='STOCK 02a08'!G26 -> 5797 | H4: ='STOCK 02a08'!H26 -> 1012 | I4: ='STOCK 02a08'!I26 -> 3661 | J4: ='STOCK 02a08'!J26 -> 409 | K4: ='STOCK 02a08'!K26 -> 0 | ... AB4: ='STOCK 02a08'!AB26 -> 0
B5: 45698 | C5: M6I-897 | R5: 1200
B6: 45698 | C6: M8B-893 | D6: 4500
B7: 45699 | C7: M6I-897 | X7: 7000
B8: 45698 | C8: JAIRO | I8: 8000
B9: 45701 | C9: M6I-897 | X9: 1300 | Y9: 2200
B10: 45701 | C10: M8B-893 | G10: 6500
A15: SALIDA | B15: 45698 | C15: VENTA JORDY | G15: 3000
B16: 45698 | C16: VENTAS H&C | G16: 30 | R16: 125
B17: 45668 | C17: VENTAS H&C | I17: =2000+1000 -> 3000
B18: 45669 | C18: VENTA JORDY | G18: 2000
B19: 45669 | C19: VENTAS H&C | G19: 500 | I19: 500 | L19: 1000 | R19: 110 | T19: =120+150 -> 270 | X19: =300+300 -> 600
B20: 45670 | C20: VENTAS H&C | G20: =1000+1000 -> 2000 | I20: =1000+360 -> 1360 | L20: 499 | N20: 500
B21: 45671 | C21: VENTAS H&C | N21: 500 | R21: 30
B22: 45672 | C22: VENTAS H&C | G22: 1000 | R22: =150+270 -> 420 | X22: 500 | Y22: =400+70 -> 470
A28: SALDO | D28: =SUM(D4:D14)-SUM(D15:D27) -> 4836 | E28: =SUM(E4:E14)-SUM(E15:E27) -> 0 | F28: =SUM(F4:F14)-SUM(F15:F27) -> 0 | G28: =SUM(G4:G14)-SUM(G15:G27) -> 3767 | H28: =SUM(H4:H14)-SUM(H15:H27) -> 1012 | I28: =SUM(I4:I14)-SUM(I15:I27) -> 6801 | J28: =SUM(J4:J14)-SUM(J15:J27) -> 409 | K28: =SUM(K4:K14)-SUM(K15:K27) -> 0 | ... AB28: =SUM(AB4:AB14)-SUM(AB15:AB27) -> 0
D30: =D28*0.36-(336*0.03) -> 1730.88 | E30: =+E28*0.3 -> 0 | F30: =+F28*0.28 -> 0 | G30: =+G28*0.33 -> 1243.11 | H30: =+H28*0.4 -> 404.8 | I30: =+I28*0.51 -> 3468.51 | J30: =+J28*0.54 -> 220.86 | K30: =+K28*0.82 -> 0 | L30: =+L28*0.62 -> 0 | M30: =+M28*0.66 -> 0 | N30: =+N28*0.64 -> 80 | O30: =+O28*0.54 -> 754.38 | P30: =+P28*2.04 -> 1507.56 | Q30: =+Q28*1.57 -> 394.07 | R30: =+R28*1.83 -> 1147.41 | S30: =+S28*1.57 -> 427.04 | T30: =+T28*1.83-(74*0.02) -> 1963.94 | U30: =+U28*1.85 -> 27.75 | V30: =+V28*2.18 -> 0 | W30: =+W28*1.8 -> 0 | X30: =+X28*0.46 -> 3312 | Y30: =+Y28*0.35-(9*0.06) -> 608.11 | Z30: =+Z28*1.9 -> 0 | AA30: =+AA28*0.93 -> 0 | AB30: =+AB28*1.5 -> 0
AB31: =SUM(D30:AB30) -> 17290.42
R33: =112*1.76 -> 197.12
R34: =13*1.83 -> 23.79
R35: =SUM(R33:R34) -> 220.91
R36: =R35/125 -> 1.76728

Sheet STOCK 16a22-02
D2: PANDERETA | I2: 18 HUECOS | P2: TECHO 12 | U2: TECHO 15 | Y2: ARTESANAL | AA2: SUPER KK | AB2: TIPO 4 | AC2: TIPO 12
B3: FECHA | C3: CLIENTE | D3: SIPAN | E3: CHALPON | F3: ZERAMIX | G3: CERAM | H3: FORTALEZA | I3: CERAM | J3: TORRE FUERTE | K3: LARK | L3: FORTALEZA | M3: CRUZ CHALPON | N3: TAISON | O3: SIPAN | P3: LARK | Q3: ZERAMIK | R3: FORTALEZA | S3: ITAL | T3: SIPAN | U3: ITAL | V3: GALCA | W3: LARK | X3: FORTALEZA | Y3: BODOQUE | Z3: PEQUEÑO | AA3: CERAMICOS | AB3: TAYSON | AC3: CONCRETO
A4: INGRESO | D4: ='STOCK 09a15-02'!D28 -> 4836 | E4: ='STOCK 09a15-02'!E28 -> 0 | F4: ='STOCK 09a15-02'!F28 -> 0 | G4: ='STOCK 09a15-02'!G28 -> 3767 | H4: ='STOCK 09a15-02'!H28 -> 1012 | I4: ='STOCK 09a15-02'!I28 -> 6801 | J4: ='STOCK 09a15-02'!J28 -> 409 | K4: ='STOCK 09a15-02'!K28 -> 0 | ... Q4: ='STOCK 09a15-02'!Q28 -> 251 | S4: ='STOCK 09a15-02'!R28 -> 627 | T4: ='STOCK 09a15-02'!S28 -> 272 | U4: ='STOCK 09a15-02'!T28 -> 1074 | V4: ='STOCK 09a15-02'!U28 -> 15 | W4: ='STOCK 09a15-02'!V28 -> 0 | X4: ='STOCK 09a15-02'!W28 -> 0 | Y4: ='STOCK 09a15-02'!X28 -> 7200 | Z4: ='STOCK 09a15-02'!Y28 -> 1739 | ... AC4: ='STOCK 09a15-02'!AB28 -> 0
B5: 45706 | C5: M8B-893 | G5: 1000 | O5: 2000
B6: 45706 | C6: M6I-897 | S6: 1200
B7: 45707 | C7: M8B-893 | G7: 4000
B8: 45708 | C8: M6I-897 | H8: 2500 | I8: 2500 | R8: 500
B9: 45709 | C9: M6I-897 | X9: 200
B10: 45710 | C10: M6I-897 | L10: 3500 | S10: 1200
A15: SALIDA | B15: 45705 | C15: VENTA JORDY | G15: 4000
B16: 45704 | C16: VENTAS H&C | Y16: 600
B17: 45705 | C17: VENTAS H&C | G17: 1000 | S17: 216 | Y17: 150
B18: 45706 | C18: VENTAS H&C | I18: =500+400+500+2300 -> 3700 | Y18: 500
B19: 45707 | C19: VENTAS H&C | G19: 200 | I19: =500+35+40 -> 575 | U19: 420
B20: 45708 | C20: VENTA JORDY | G20: 2000 | Q20: 234 | T20: 266
B21: 45708 | C21: VENTAS H&C | G21: 500 | S21: 25 | Y21: 200 | Z21: 20
B22: 45709 | C22: VENTAS H&C | I22: 500 | O22: =1000+500+150 -> 1650 | R22: 420 | Z22: 400
B23: 45710 | C23: VENTAS H&C | G23: 250
C27: FALTANTE | Q27: 17
A29: SALDO | D29: =SUM(D4:D14)-SUM(D15:D28) -> 4836 | E29: =SUM(E4:E14)-SUM(E15:E28) -> 0 | F29: =SUM(F4:F14)-SUM(F15:F28) -> 0 | G29: =SUM(G4:G14)-SUM(G15:G28) -> 817 | H29: =SUM(H4:H14)-SUM(H15:H28) -> 3512 | I29: =SUM(I4:I14)-SUM(I15:I28) -> 4526 | J29: =SUM(J4:J14)-SUM(J15:J28) -> 409 | K29: =SUM(K4:K14)-SUM(K15:K28) -> 0 | ... AC29: =SUM(AC4:AC14)-SUM(AC15:AC28) -> 0
D31: =D29*0.36-(336*0.03) -> 1730.88 | E31: =+E29*0.3 -> 0 | F31: =+F29*0.28 -> 0 | G31: =+G29*0.335 -> 273.695 | H31: =+H29*0.4 -> 1404.8 | I31: =+I29*0.52-(2026*0.01) -> 2333.26 | J31: =+J29*0.54 -> 220.86 | K31: =+K29*0.82 -> 0 | L31: =+L29*0.62 -> 2170 | M31: =+M29*0.66 -> 0 | N31: =+N29*0.64 -> 80 | O31: =+O29*0.57 -> 995.79 | P31: =+P29*2.04 -> 1507.56 | Q31: =+Q29*1.57 -> 0 | R31: =R29*1.8 -> 144 | S31: =+S29*1.83 -> 5098.38 | T31: =+T29*1.57 -> 9.42 | U31: =+U29*1.83 -> 1196.82 | V31: =+V29*1.85 -> 27.75 | W31: =+W29*2.18 -> 0 | X31: =+X29*1.9 -> 380 | Y31: =+Y29*0.46 -> 2645 | Z31: =+Z29*0.35-(9*0.06) -> 461.11 | AA31: =+AA29*1.9 -> 0 | AB31: =+AB29*0.93 -> 0 | AC31: =+AC29*1.5 -> 0
AC32: =SUM(D31:AC31) -> 20679.325
S34: =112*1.76 -> 197.12
S35: =13*1.83 -> 23.79
S36: =SUM(S34:S35) -> 220.91
S37: =S36/125 -> 1.76728

Sheet STOCK 23a01-03
D2: PANDERETA | I2: 18 HUECOS | O2: TECHO 12 | T2: TECHO 15 | X2: ARTESANAL | Z2: SUPER KK | AA2: TIPO 4 | AB2: TIPO 12
B3: FECHA | C3: CLIENTE | D3: SIPAN | E3: CHALPON | F3: ZERAMIX | G3: CERAM | H3: FORTALEZA | I3: CERAM | J3: TORRE FUERTE | K3: LARK | L3: FORTALEZA | M3: TAISON | N3: SIPAN | O3: LARK | P3: CERAMICOS | Q3: FORTALEZA | R3: ITAL | S3: SIPAN | T3: ITAL | U3: GALCA | V3: LARK | W3: FORTALEZA | X3: BODOQUE | Y3: PEQUEÑO | Z3: CERAMICOS | AA3: TAYSON | AB3: CONCRETO
A4: INGRESO | D4: ='STOCK 16a22-02'!D29 -> 4836 | E4: ='STOCK 16a22-02'!E29 -> 0 | F4: ='STOCK 16a22-02'!F29 -> 0 | G4: ='STOCK 16a22-02'!G29 -> 817 | H4: ='STOCK 16a22-02'!H29 -> 3512 | I4: ='STOCK 16a22-02'!I29 -> 4526 | J4: ='STOCK 16a22-02'!J29 -> 409 | K4: ='STOCK 16a22-02'!K29 -> 0 | L4: ='STOCK 16a22-02'!L29 -> 3500 | M4: ='STOCK 16a22-02'!N29 -> 125 | N4: ='STOCK 16a22-02'!O29 -> 1747 | O4: ='STOCK 16a22-02'!P29 -> 739 | P4: ='STOCK 16a22-02'!Q29 -> 0 | Q4: ='STOCK 16a22-02'!R29 -> 80 | R4: ='STOCK 16a22-02'!S29 -> 2786 | S4: ='STOCK 16a22-02'!T29 -> 6 | T4: ='STOCK 16a22-02'!U29 -> 654 | ... AB4: ='STOCK 16a22-02'!AC29 -> 0
B5: 45712 | C5: M8B-893 | N5: 2000
B6: 45714 | C6: M6I-897 | R6: 350
B7: 45714 | C7: M8B-893 | D7: 4000
B8: 45716 | C8: M8B-893 | T8: 220
B9: 45712 | C9: JAIRO | I9: 8000
B10: 45716 | C10: M8B-893 | I10: 3000
B11: 45716 | C11: M6I-897 | P11: 1200
T12: 1000
B13: 45717 | C13: M6I-897 | D13: 6000
B14: DIF STOCK | G14: 1000
A16: SALIDA
B17: 45712 | C17: VENTA JORDY | G17: 1500
B18: 45712 | C18: VENTAS H&C | G18: 2000 | N18: 1000 | R18: =400+400 -> 800
B19: 45713 | C19: VENTAS H&C | D19: =300+2000 -> 2300 | G19: 290 | I19: 100 | R19: 220
B20: 45714 | C20: VENTAS H&C | D20: 2000 | H20: 2000 | I20: 36 | N20: 100 | R20: 5 | X20: 500
B21: 45715 | C21: VENTAS H&C | I21: =1000+3000 -> 4000 | T21: 80
B22: 45716 | C22: VENTAS H&C | D22: =1000+1500+300 -> 2800 | I22: 1000
B23: 45717 | C23: VENTA JORDY | L23: 3500
B24: 45717 | C24: VENTAS H&C | D24: =1000+185 -> 1185 | H24: 6 | T24: =300+20 -> 320
B28: DIF STOCK | H28: 1000
A30: SALDO | D30: =SUM(D4:D15)-SUM(D16:D29) -> 6551 | E30: =SUM(E4:E15)-SUM(E16:E29) -> 0 | F30: =SUM(F4:F15)-SUM(F16:F29) -> 0 | G30: =SUM(G4:G15)-SUM(G16:G29) -> -1973 | H30: =SUM(H4:H15)-SUM(H16:H29) -> 506 | I30: =SUM(I4:I15)-SUM(I16:I29) -> 10390 | J30: =SUM(J4:J15)-SUM(J16:J29) -> 409 | K30: =SUM(K4:K15)-SUM(K16:K29) -> 0 | ... AB30: =SUM(AB4:AB15)-SUM(AB16:AB29) -> 0
D32: =D30*0.37 -> 2423.87 | E32: =+E30*0.3 -> 0 | F32: =+F30*0.28 -> 0 | G32: =+G30*0.335 -> -660.955 | H32: =+H30*0.4 -> 202.4 | I32: =+I30*0.55 -> 5714.5 | J32: =+J30*0.54 -> 220.86 | K32: =+K30*0.82 -> 0 | L32: =+L30*0.62 -> 0 | M32: =+M30*0.64 -> 80 | N32: =+N30*0.57 -> 1508.79 | O32: =+O30*2.04 -> 1507.56 | P32: =+P30*1.575 -> 1890 | Q32: =Q30*1.8 -> 144 | R32: =+R30*1.83 -> 3863.13 | S32: =+S30*1.57 -> 9.42 | T32: =+T30*1.88-(254*0.05) -> 2758.42 | U32: =+U30*1.85 -> 27.75 | V32: =+V30*2.18 -> 0 | W32: =+W30*1.9 -> 380 | X32: =+X30*0.46 -> 2415 | Y32: =+Y30*0.35-(9*0.06) -> 461.11 | Z32: =+Z30*1.9 -> 0 | AA32: =+AA30*0.93 -> 0 | AB32: =+AB30*1.5 -> 0
AB33: =SUM(D32:AB32) -> 22945.855
D35: =36*0.33 -> 11.88 | R35: =112*1.76 -> 197.12
D36: =1964*0.36 -> 707.04 | R36: =13*1.83 -> 23.79
D37: =+D35+D36 -> 718.92 | R37: =SUM(R35:R36) -> 220.91
D38: =D37/2000 -> 0.35946 | R38: =R37/125 -> 1.76728
C49: =1110*8*3.689 -> 32758.32 | O49: =580*32.2 -> 18676
C50: 4500 | O50: =570*30 -> 17100
C51: =SUM(C49:C50) -> 37258.32

Sheet STOCK 02a08-03
D2: PANDERETA | I2: 18 HUECOS | O2: TECHO 12 | T2: TECHO 15 | X2: ARTESANAL | Z2: SUPER KK | AA2: TIPO 4 | AB2: TIPO 12
B3: FECHA | C3: CLIENTE | D3: SIPAN | E3: CHALPON | F3: ZERAMIX | G3: CERAM | H3: FORTALEZA | I3: CERAM | J3: TORRE FUERTE | K3: LARK | L3: FORTALEZA | M3: TAISON | N3: SIPAN | O3: LARK | P3: CERAMICOS | Q3: FORTALEZA | R3: ITAL | S3: SIPAN | T3: ITAL | U3: GALCA | V3: LARK | W3: FORTALEZA | X3: BODOQUE | Y3: PEQUEÑO | Z3: CERAMICOS | AA3: TAYSON | AB3: CONCRETO
A4: INGRESO | D4: ='STOCK 23a01-03'!D30 -> 6551 | E4: ='STOCK 23a01-03'!E30 -> 0 | F4: ='STOCK 23a01-03'!F30 -> 0 | G4: 0 | H4: ='STOCK 23a01-03'!H30 -> 506 | I4: ='STOCK 23a01-03'!I30 -> 10390 | J4: ='STOCK 23a01-03'!J30 -> 409 | K4: ='STOCK 23a01-03'!K30 -> 0 | L4: ='STOCK 23a01-03'!L30 -> 0 | M4: ='STOCK 23a01-03'!M30 -> 125 | N4: ='STOCK 23a01-03'!N30 -> 2647 | O4: ='STOCK 23a01-03'!O30 -> 739 | ... AB4: ='STOCK 23a01-03'!AB30 -> 0
B6: 45722 | C6: M6I-897 | I6: 4000
B7: 45723 | C7: M8B-893 | D7: 6000
B8: 45724 | C8: M6I-897 | P8: 300
A16: SALIDA | B16: 45719 | C16: VENTAS H&C | D16: =1500+1500+250+2500 -> 5750 | Y16: =1000+319 -> 1319
B17: 45720 | C17: VENTAS H&C | I17: 500
B18: 45721 | C18: VENTAS H&C | D18: 500 | I18: 500 | N18: 1500 | X18: 2000
B19: 45722 | C19: VENTAS H&C | J19: 300 | T19: 500 | X19: =200+150 -> 350
B20: 45723 | C20: VENTAS H&C | D20: =10+650 -> 660 | T20: 250
B21: 45724 | C21: VENTAS H&C | I21: 100 | J21: 100 | X21: 2000
A30: SALDO | D30: =SUM(D4:D15)-SUM(D16:D29) -> 5641 | E30: =SUM(E4:E15)-SUM(E16:E29) -> 0 | F30: =SUM(F4:F15)-SUM(F16:F29) -> 0 | G30: =SUM(G4:G15)-SUM(G16:G29) -> 0 | H30: =SUM(H4:H15)-SUM(H16:H29) -> 506 | I30: =SUM(I4:I15)-SUM(I16:I29) -> 13290 | J30: =SUM(J4:J15)-SUM(J16:J29) -> 9 | K30: =SUM(K4:K15)-SUM(K16:K29) -> 0 | ... AB30: =SUM(AB4:AB15)-SUM(AB16:AB29) -> 0
D32: =D30*0.37 -> 2087.17 | E32: =+E30*0.3 -> 0 | F32: =+F30*0.28 -> 0 | G32: =+G30*0.335 -> 0 | H32: =+H30*0.4 -> 202.4 | I32: =+I30*0.55 -> 7309.5 | J32: =+J30*0.54 -> 4.86 | K32: =+K30*0.82 -> 0 | L32: =+L30*0.62 -> 0 | M32: =+M30*0.64 -> 80 | N32: =+N30*0.57 -> 653.79 | O32: =+O30*2.04 -> 1507.56 | P32: =+P30*1.575+(300*0.285) -> 2448 | Q32: =Q30*1.8 -> 144 | R32: =+R30*1.83 -> 3863.13 | S32: =+S30*1.57 -> 9.42 | T32: =+T30*1.88 -> 1361.12 | U32: =+U30*1.85 -> 27.75 | V32: =+V30*2.18 -> 0 | W32: =+W30*1.9 -> 380 | X32: =+X30*0.46 -> 414 | Y32: =+Y30*0.35 -> 0 | Z32: =+Z30*1.9 -> 0 | AA32: =+AA30*0.93 -> 0 | AB32: =+AB30*1.5 -> 0
AB33: =SUM(D32:AB32) -> 20492.7
D35: =36*0.33 -> 11.88 | R35: =112*1.76 -> 197.12
D36: =1964*0.36 -> 707.04 | R36: =13*1.83 -> 23.79
D37: =+D35+D36 -> 718.92 | R37: =SUM(R35:R36) -> 220.91
D38: =D37/2000 -> 0.35946 | R38: =R37/125 -> 1.76728
C49: =1110*8*3.689 -> 32758.32 | O49: =580*32.2 -> 18676
C50: 4500 | O50: =570*30 -> 17100
C51: =SUM(C49:C50) -> 37258.32

Sheet STOCK 09a15-03
D2: PANDERETA | I2: 18 HUECOS | O2: TECHO 12 | T2: TECHO 15 | X2: ARTESANAL | Z2: SUPER KK | AA2: TIPO 4 | AB2: TIPO 12
B3: FECHA | C3: CLIENTE | D3: SIPAN | E3: CHALPON | F3: ZERAMIX | G3: CERAM | H3: FORTALEZA | I3: CERAM | J3: TORRE FUERTE | K3: LARK | L3: FORTALEZA | M3: TAISON | N3: SIPAN | O3: LARK | P3: CERAMICOS | Q3: FORTALEZA | R3: ITAL | S3: SIPAN | T3: ITAL | U3: GALCA | V3: LARK | W3: FORTALEZA | X3: BODOQUE | Y3: PEQUEÑO | Z3: CERAMICOS | AA3: TAYSON | AB3: CONCRETO
A4: INGRESO | D4: ='STOCK 02a08-03'!D30 -> 5641 | E4: ='STOCK 02a08-03'!E30 -> 0 | F4: ='STOCK 02a08-03'!F30 -> 0 | G4: ='STOCK 02a08-03'!G30 -> 0 | H4: ='STOCK 02a08-03'!H30 -> 506 | I4: ='STOCK 02a08-03'!I30 -> 13290 | J4: ='STOCK 02a08-03'!J30 -> 9 | K4: ='STOCK 02a08-03'!K30 -> 0 | ... AB4: ='STOCK 02a08-03'!AB30 -> 0
B5: 45726 | C5: M8B-893 | D5: 1000
B6: 45727 | C6: M6I-897 | D6: 4500
B7: 45728 | C7: M6I-897 | G7: 4200 | X7: 1250
B8: 45729 | C8: M6I-897 | Y8: 4150
B9: 45730 | C9: M8B-893 | I9: 4000
A16: SALIDA
B17: 45726 | C17: VENTA H&C | D17: =2000+800+1000 -> 3800 | I17: 1000 | X17: 400
B18: 45727 | C18: VENTAS JORDY | I18: 2000
B19: 45727 | C19: VENTA H&C | D19: =200+500+1000+1000+300 -> 3000 | R19: 210 | T19: 400 | X19: 50
B20: 45728 | C20: VENTA H&C | D20: 1000 | I20: =1500+1500 -> 3000 | R20: 200 | X20: =50+1000 -> 1050
B21: 45729 | C21: VENTA H&C | D21: =300+1000 -> 1300 | I21: 1000 | R21: =230+30 -> 260 | T21: 115 | Y21: 200
B22: 45730 | C22: VENTA H&C | D22: 1000 | G22: 1700 | I22: 260
B23: 45731 | C23: VENTA H&C | D23: 1000 | H23: 300 | I23: 2500 | X23: 416
A30: SALDO | D30: =SUM(D4:D15)-SUM(D16:D29) -> 41 | E30: =SUM(E4:E15)-SUM(E16:E29) -> 0 | F30: =SUM(F4:F15)-SUM(F16:F29) -> 0 | G30: =SUM(G4:G15)-SUM(G16:G29) -> 2500 | H30: =SUM(H4:H15)-SUM(H16:H29) -> 206 | I30: =SUM(I4:I15)-SUM(I16:I29) -> 7530 | J30: =SUM(J4:J15)-SUM(J16:J29) -> 9 | K30: =SUM(K4:K15)-SUM(K16:K29) -> 0 | ... AB30: =SUM(AB4:AB15)-SUM(AB16:AB29) -> 0
D32: =D30*0.37 -> 15.17 | E32: =+E30*0.3 -> 0 | F32: =+F30*0.28 -> 0 | G32: =+G30*0.37 -> 925 | H32: =+H30*0.4 -> 82.4 | I32: =+I30*0.55 -> 4141.5 | J32: =+J30*0.54 -> 4.86 | K32: =+K30*0.82 -> 0 | L32: =+L30*0.62 -> 0 | M32: =+M30*0.64 -> 80 | N32: =+N30*0.57 -> 653.79 | O32: =+O30*2.04 -> 1507.56 | P32: =+P30*1.575+(300*0.285) -> 2448 | Q32: =Q30*1.8 -> 144 | R32: =+R30*1.83 -> 2637.03 | S32: =+S30*1.57 -> 9.42 | T32: =+T30*1.88 -> 392.92 | U32: =+U30*1.85 -> 27.75 | V32: =+V30*2.18 -> 0 | W32: =+W30*1.9 -> 380 | X32: =+X30*0.46 -> 107.64 | Y32: =+Y30*0.35 -> 1382.5 | Z32: =+Z30*1.9 -> 0 | AA32: =+AA30*0.93 -> 0 | AB32: =+AB30*1.5 -> 0
